{"msg":"OK","server_time":"2026-04-08 05:07:25","status":200,"result":{"total_pages":133,"files":[{"download_url":"https://lulustream.com/d/gj90gh62wfp3","single_img":"https://img.lulucdn.com/gj90gh62wfp3_t.jpg","file_code":"gj90gh62wfp3","length":"00:04:37","views":"573","vw_fmt":"573","uploaded":"2025-09-20 18:02:58","up_fmt":"20 Sep 2025","up_short":"20 Sep","title":"Nikmati Abg Chindo Enak Bngt B Kong Super Mulus Dood Jilbab Viral","t_esc":"Nikmati Abg Chindo Enak Bngt B Kong Super Mulus Dood Jilbab Viral"},{"download_url":"https://lulustream.com/d/it3g2ygfuvg1","single_img":"https://img.lulucdn.com/it3g2ygfuvg1_t.jpg","file_code":"it3g2ygfuvg1","length":"00:43:06","views":"1544","vw_fmt":"1.5K","uploaded":"2025-09-20 18:02:58","up_fmt":"20 Sep 2025","up_short":"20 Sep","title":"Sma Live Omek Bodynya Mulus Link Web Toketbagus Bokep31 Twitter Ngentot","t_esc":"Sma Live Omek Bodynya Mulus Link Web Toketbagus Bokep31 Twitter Ngentot"},{"download_url":"https://lulustream.com/d/frn9qcn0zl6d","single_img":"https://img.lulucdn.com/frn9qcn0zl6d_t.jpg","file_code":"frn9qcn0zl6d","length":"00:02:02","views":"532","vw_fmt":"532","uploaded":"2025-09-20 18:02:58","up_fmt":"20 Sep 2025","up_short":"20 Sep","title":"Dapet Cewe Mulus Langsung Di Ew Memeksiana Sotwe Bokep31 Toketbagus Links","t_esc":"Dapet Cewe Mulus Langsung Di Ew Memeksiana Sotwe Bokep31 Toketbagus Links"},{"download_url":"https://lulustream.com/d/ywvuaspxjt5s","single_img":"https://img.lulucdn.com/ywvuaspxjt5s_t.jpg","file_code":"ywvuaspxjt5s","length":"00:16:13","views":"146","vw_fmt":"146","uploaded":"2025-09-20 18:02:58","up_fmt":"20 Sep 2025","up_short":"20 Sep","title":"Bening Mulus Temenin Buka Anu Yuk Sylvia Id Mango Tele Pejuang Lendir","t_esc":"Bening Mulus Temenin Buka Anu Yuk Sylvia Id Mango Tele Pejuang Lendir"},{"download_url":"https://lulustream.com/d/fr2may9xnj1v","single_img":"https://img.lulucdn.com/fr2may9xnj1v_t.jpg","file_code":"fr2may9xnj1v","length":"00:01:03","views":"615","vw_fmt":"615","uploaded":"2025-09-20 18:02:56","up_fmt":"20 Sep 2025","up_short":"20 Sep","title":"Abg Mulus Kobel Memey Bebasindo Cantik Tobrut Bokep Dood Video Colmek Update","t_esc":"Abg Mulus Kobel Memey Bebasindo Cantik Tobrut Bokep Dood Video Colmek Update"},{"download_url":"https://lulustream.com/d/ncigq4cjek0f","single_img":"https://img.lulucdn.com/ncigq4cjek0f_t.jpg","file_code":"ncigq4cjek0f","length":"00:03:05","views":"569","vw_fmt":"569","uploaded":"2025-09-20 18:02:56","up_fmt":"20 Sep 2025","up_short":"20 Sep","title":"Omahbokep Remaja Memek Pink Mulus Indah Xbokepfb Org Indo Live Bokepsatset Downloader","t_esc":"Omahbokep Remaja Memek Pink Mulus Indah Xbokepfb Org Indo Live Bokepsatset Downloader"},{"download_url":"https://lulustream.com/d/wlao1ueij4x1","single_img":"https://img.lulucdn.com/wlao1ueij4x1_t.jpg","file_code":"wlao1ueij4x1","length":"00:07:07","views":"209","vw_fmt":"209","uploaded":"2025-09-20 18:02:55","up_fmt":"20 Sep 2025","up_short":"20 Sep","title":"Jatah Mingguan Dari Adik Tiri Cantik Tobrut Doods Pro Live Streaming Bebasindo","t_esc":"Jatah Mingguan Dari Adik Tiri Cantik Tobrut Doods Pro Live Streaming Bebasindo"},{"download_url":"https://lulustream.com/d/lw9b62ht9xtv","single_img":"https://img.lulucdn.com/lw9b62ht9xtv_t.jpg","file_code":"lw9b62ht9xtv","length":"00:06:05","views":"3132","vw_fmt":"3.1K","uploaded":"2025-09-20 18:02:55","up_fmt":"20 Sep 2025","up_short":"20 Sep","title":"Kakak Adek Takut Ngentot Di Kamar Mandi Doostream Link Web Update Telegram","t_esc":"Kakak Adek Takut Ngentot Di Kamar Mandi Doostream Link Web Update Telegram"},{"download_url":"https://lulustream.com/d/7g44pxjnynnr","single_img":"https://img.lulucdn.com/7g44pxjnynnr_t.jpg","file_code":"7g44pxjnynnr","length":"00:06:10","views":"272","vw_fmt":"272","uploaded":"2025-09-20 18:02:55","up_fmt":"20 Sep 2025","up_short":"20 Sep","title":"Wanita Sales Rokok Bisa Di Bawa Check In Ke Hotel Dood Bokep","t_esc":"Wanita Sales Rokok Bisa Di Bawa Check In Ke Hotel Dood Bokep"},{"download_url":"https://lulustream.com/d/0gvgatazj7px","single_img":"https://img.lulucdn.com/0gvgatazj7px_t.jpg","file_code":"0gvgatazj7px","length":"00:01:49","views":"579","vw_fmt":"579","uploaded":"2025-09-20 18:02:55","up_fmt":"20 Sep 2025","up_short":"20 Sep","title":"Janda Pirangminta Didoggy Sales Dikamar Mandi Bokepsatset Tobrut Downloader Pemersatu Terabox","t_esc":"Janda Pirangminta Didoggy Sales Dikamar Mandi Bokepsatset Tobrut Downloader Pemersatu Terabox"},{"download_url":"https://lulustream.com/d/eeiw1l60tad5","single_img":"https://img.lulucdn.com/eeiw1l60tad5_t.jpg","file_code":"eeiw1l60tad5","length":"00:01:20","views":"260","vw_fmt":"260","uploaded":"2025-09-20 18:02:55","up_fmt":"20 Sep 2025","up_short":"20 Sep","title":"Sales Harus Terima Hukuman Dari Kepala Toko Bokepdewasa Com Full Album Cilbo","t_esc":"Sales Harus Terima Hukuman Dari Kepala Toko Bokepdewasa Com Full Album Cilbo"},{"download_url":"https://lulustream.com/d/d1v0ahkjyj43","single_img":"https://img.lulucdn.com/d1v0ahkjyj43_t.jpg","file_code":"d1v0ahkjyj43","length":"00:10:10","views":"833","vw_fmt":"833","uploaded":"2025-09-20 18:02:54","up_fmt":"20 Sep 2025","up_short":"20 Sep","title":"Bercinta Dengan Adik Iparku Sampai Aku Keluar Di Dalam Link Web Indonesia","t_esc":"Bercinta Dengan Adik Iparku Sampai Aku Keluar Di Dalam Link Web Indonesia"},{"download_url":"https://lulustream.com/d/pdyicilyrwqm","single_img":"https://img.lulucdn.com/pdyicilyrwqm_t.jpg","file_code":"pdyicilyrwqm","length":"00:08:22","views":"2514","vw_fmt":"2.5K","uploaded":"2025-09-20 18:02:54","up_fmt":"20 Sep 2025","up_short":"20 Sep","title":"Skandal Kakak Ngewe Adik Sendiri Sepulang Sekolah Bokepind Videos Simontok Tele Link","t_esc":"Skandal Kakak Ngewe Adik Sendiri Sepulang Sekolah Bokepind Videos Simontok Tele Link"},{"download_url":"https://lulustream.com/d/znojatj2ecqd","single_img":"https://img.lulucdn.com/znojatj2ecqd_t.jpg","file_code":"znojatj2ecqd","length":"00:09:30","views":"2640","vw_fmt":"2.6K","uploaded":"2025-09-20 18:02:54","up_fmt":"20 Sep 2025","up_short":"20 Sep","title":"Aku Melakukannya Dengan Kakak Ku Dikamar Mp Original Video Viral Doodsflix Simontok","t_esc":"Aku Melakukannya Dengan Kakak Ku Dikamar Mp Original Video Viral Doodsflix Simontok"},{"download_url":"https://lulustream.com/d/p6oz47p8dy2h","single_img":"https://img.lulucdn.com/p6oz47p8dy2h_t.jpg","file_code":"p6oz47p8dy2h","length":"00:07:43","views":"4109","vw_fmt":"4.1K","uploaded":"2025-09-20 18:02:54","up_fmt":"20 Sep 2025","up_short":"20 Sep","title":"Di Paksa Ngentot Sama Adik Sendiri Pemersatu Sotwe Poophd Videos Lulustream","t_esc":"Di Paksa Ngentot Sama Adik Sendiri Pemersatu Sotwe Poophd Videos Lulustream"},{"download_url":"https://lulustream.com/d/vakvp3wubbzy","single_img":"https://img.lulucdn.com/vakvp3wubbzy_t.jpg","file_code":"vakvp3wubbzy","length":"00:09:32","views":"95","vw_fmt":"95","uploaded":"2025-09-20 18:02:33","up_fmt":"20 Sep 2025","up_short":"20 Sep","title":"Bokep Bling Remaja Pamer Selangkangan Xbokepfb Org Lagi Viral Dood Terabox Website","t_esc":"Bokep Bling Remaja Pamer Selangkangan Xbokepfb Org Lagi Viral Dood Terabox Website"},{"download_url":"https://lulustream.com/d/gg6dz775rm3g","single_img":"https://img.lulucdn.com/gg6dz775rm3g_t.jpg","file_code":"gg6dz775rm3g","length":"00:06:37","views":"429","vw_fmt":"429","uploaded":"2025-09-20 18:02:30","up_fmt":"20 Sep 2025","up_short":"20 Sep","title":"Ukhty Nakal Pamer Selangkangan Dodstream Doodflix Xpanas Doods Pro Terupdate","t_esc":"Ukhty Nakal Pamer Selangkangan Dodstream Doodflix Xpanas Doods Pro Terupdate"},{"download_url":"https://lulustream.com/d/0y26olzfc114","single_img":"https://img.lulucdn.com/0y26olzfc114_t.jpg","file_code":"0y26olzfc114","length":"00:18:04","views":"205","vw_fmt":"205","uploaded":"2025-09-20 18:02:30","up_fmt":"20 Sep 2025","up_short":"20 Sep","title":"Ukhty Nakal Pamer Selangkangan Lagi Viral Terabox Doods Pro Website Video Colmek","t_esc":"Ukhty Nakal Pamer Selangkangan Lagi Viral Terabox Doods Pro Website Video Colmek"},{"download_url":"https://lulustream.com/d/3pkye9nmcmfu","single_img":"https://img.lulucdn.com/3pkye9nmcmfu_t.jpg","file_code":"3pkye9nmcmfu","length":"00:01:02","views":"13050","vw_fmt":"13.1K","uploaded":"2025-09-20 18:00:51","up_fmt":"20 Sep 2025","up_short":"20 Sep","title":"L Dood Tele Bokepsin Doodstream Simintok Terabox","t_esc":"L Dood Tele Bokepsin Doodstream Simintok Terabox"},{"download_url":"https://lulustream.com/d/kyxl0xzeh27n","single_img":"https://img.lulucdn.com/kyxl0xzeh27n_t.jpg","file_code":"kyxl0xzeh27n","length":"00:01:02","views":"792","vw_fmt":"792","uploaded":"2025-09-20 18:00:48","up_fmt":"20 Sep 2025","up_short":"20 Sep","title":"L Videos Toketbagus Video Bokep Sotwe Dood","t_esc":"L Videos Toketbagus Video Bokep Sotwe Dood"},{"download_url":"https://lulustream.com/d/oa4vn4jmmlf9","single_img":"https://img.lulucdn.com/oa4vn4jmmlf9_t.jpg","file_code":"oa4vn4jmmlf9","length":"00:02:20","views":"950","vw_fmt":"950","uploaded":"2025-09-20 18:00:47","up_fmt":"20 Sep 2025","up_short":"20 Sep","title":"Xpanas Videos Bokep Video Viral Dood","t_esc":"Xpanas Videos Bokep Video Viral Dood"},{"download_url":"https://lulustream.com/d/a81a4vo5mbp0","single_img":"https://img.lulucdn.com/a81a4vo5mbp0_t.jpg","file_code":"a81a4vo5mbp0","length":"00:01:42","views":"8097","vw_fmt":"8.1K","uploaded":"2025-09-20 18:00:47","up_fmt":"20 Sep 2025","up_short":"20 Sep","title":"Tiktok Pekoblive Twitter Video Sma Full Album","t_esc":"Tiktok Pekoblive Twitter Video Sma Full Album"},{"download_url":"https://lulustream.com/d/dsswo89p4b7o","single_img":"https://img.lulucdn.com/dsswo89p4b7o_t.jpg","file_code":"dsswo89p4b7o","length":"00:02:51","views":"18316","vw_fmt":"18.3K","uploaded":"2025-09-20 18:00:47","up_fmt":"20 Sep 2025","up_short":"20 Sep","title":"L Simontok Bokepsin Pejuang Lendir Lulustream Simintok","t_esc":"L Simontok Bokepsin Pejuang Lendir Lulustream Simintok"},{"download_url":"https://lulustream.com/d/lr3emo4l54pe","single_img":"https://img.lulucdn.com/lr3emo4l54pe_t.jpg","file_code":"lr3emo4l54pe","length":"00:01:04","views":"330","vw_fmt":"330","uploaded":"2025-09-20 18:00:46","up_fmt":"20 Sep 2025","up_short":"20 Sep","title":"Vid Full Album Bokep31 Toketbagus Jilbab Live","t_esc":"Vid Full Album Bokep31 Toketbagus Jilbab Live"},{"download_url":"https://lulustream.com/d/951fl1spkbb1","single_img":"https://img.lulucdn.com/951fl1spkbb1_t.jpg","file_code":"951fl1spkbb1","length":"00:05:02","views":"34","vw_fmt":"34","uploaded":"2025-09-20 18:00:44","up_fmt":"20 Sep 2025","up_short":"20 Sep","title":"Ssstwitter Com Terabox Telegram Doods Pro Live Tiktok","t_esc":"Ssstwitter Com Terabox Telegram Doods Pro Live Tiktok"},{"download_url":"https://lulustream.com/d/b82qvvjf5s8c","single_img":"https://img.lulucdn.com/b82qvvjf5s8c_t.jpg","file_code":"b82qvvjf5s8c","length":"00:05:00","views":"3","vw_fmt":"3","uploaded":"2025-09-20 18:00:44","up_fmt":"20 Sep 2025","up_short":"20 Sep","title":"Vid Indonesia Tele Downloader Video Sma Link Web","t_esc":"Vid Indonesia Tele Downloader Video Sma Link Web"},{"download_url":"https://lulustream.com/d/wbswy8g4d5lf","single_img":"https://img.lulucdn.com/wbswy8g4d5lf_t.jpg","file_code":"wbswy8g4d5lf","length":"00:13:54","views":"1257","vw_fmt":"1.3K","uploaded":"2025-09-20 18:00:43","up_fmt":"20 Sep 2025","up_short":"20 Sep","title":"Adek Kakak Ngentot New Tiktok Terabox Folder Cilbo Video Indo","t_esc":"Adek Kakak Ngentot New Tiktok Terabox Folder Cilbo Video Indo"},{"download_url":"https://lulustream.com/d/i3yg8ljr5mhf","single_img":"https://img.lulucdn.com/i3yg8ljr5mhf_t.jpg","file_code":"i3yg8ljr5mhf","length":"00:03:03","views":"3063","vw_fmt":"3.1K","uploaded":"2025-09-20 18:00:43","up_fmt":"20 Sep 2025","up_short":"20 Sep","title":"Skandal Adek Kakak Doodflix Pekoblive Ful Album Lagi Viral Bebasindo","t_esc":"Skandal Adek Kakak Doodflix Pekoblive Ful Album Lagi Viral Bebasindo"},{"download_url":"https://lulustream.com/d/7gufigzfkep6","single_img":"https://img.lulucdn.com/7gufigzfkep6_t.jpg","file_code":"7gufigzfkep6","length":"00:02:13","views":"567","vw_fmt":"567","uploaded":"2025-09-20 18:00:43","up_fmt":"20 Sep 2025","up_short":"20 Sep","title":"Ssstwitter Com Dodstream Indo Twitter Pekoblive Bokepsatset","t_esc":"Ssstwitter Com Dodstream Indo Twitter Pekoblive Bokepsatset"},{"download_url":"https://lulustream.com/d/0muvt9cig8bj","single_img":"https://img.lulucdn.com/0muvt9cig8bj_t.jpg","file_code":"0muvt9cig8bj","length":"00:20:08","views":"849","vw_fmt":"849","uploaded":"2025-09-20 18:00:42","up_fmt":"20 Sep 2025","up_short":"20 Sep","title":"Lagi Belajar Malah Diganggu Kakak Simintok Viral Asupan Bokepin Bokepsin","t_esc":"Lagi Belajar Malah Diganggu Kakak Simintok Viral Asupan Bokepin Bokepsin"},{"download_url":"https://lulustream.com/d/o865bd4chgnx","single_img":"https://img.lulucdn.com/o865bd4chgnx_t.jpg","file_code":"o865bd4chgnx","length":"00:01:04","views":"102","vw_fmt":"102","uploaded":"2025-09-20 18:00:42","up_fmt":"20 Sep 2025","up_short":"20 Sep","title":"Vid Link Web Simontok Telegram Dood Tele Tiktok","t_esc":"Vid Link Web Simontok Telegram Dood Tele Tiktok"},{"download_url":"https://lulustream.com/d/n0w4hl00y6ut","single_img":"https://img.lulucdn.com/n0w4hl00y6ut_t.jpg","file_code":"n0w4hl00y6ut","length":"00:02:20","views":"3394","vw_fmt":"3.4K","uploaded":"2025-09-20 18:00:42","up_fmt":"20 Sep 2025","up_short":"20 Sep","title":"Videos Link Web Doods Pro Xpanas Pejuang Lendir","t_esc":"Videos Link Web Doods Pro Xpanas Pejuang Lendir"},{"download_url":"https://lulustream.com/d/tpbl4ab1fp4h","single_img":"https://img.lulucdn.com/tpbl4ab1fp4h_t.jpg","file_code":"tpbl4ab1fp4h","length":"00:01:42","views":"549","vw_fmt":"549","uploaded":"2025-09-20 18:00:42","up_fmt":"20 Sep 2025","up_short":"20 Sep","title":"Bokepsatset Jilbab Videos Poophd Toketbagus","t_esc":"Bokepsatset Jilbab Videos Poophd Toketbagus"},{"download_url":"https://lulustream.com/d/p4h9jnzga3io","single_img":"https://img.lulucdn.com/p4h9jnzga3io_t.jpg","file_code":"p4h9jnzga3io","length":"00:02:51","views":"1260","vw_fmt":"1.3K","uploaded":"2025-09-20 18:00:42","up_fmt":"20 Sep 2025","up_short":"20 Sep","title":"L Viral Video Memeksiana Popstream Dood Tele","t_esc":"L Viral Video Memeksiana Popstream Dood Tele"},{"download_url":"https://lulustream.com/d/fr7wu76wntco","single_img":"https://img.lulucdn.com/fr7wu76wntco_t.jpg","file_code":"fr7wu76wntco","length":"00:05:02","views":"92","vw_fmt":"92","uploaded":"2025-09-20 18:00:41","up_fmt":"20 Sep 2025","up_short":"20 Sep","title":"Ssstwitter Com Downloader Video Colmek Link Web Bebasindo Live","t_esc":"Ssstwitter Com Downloader Video Colmek Link Web Bebasindo Live"},{"download_url":"https://lulustream.com/d/zdsxwedfy9wy","single_img":"https://img.lulucdn.com/zdsxwedfy9wy_t.jpg","file_code":"zdsxwedfy9wy","length":"00:15:26","views":"447","vw_fmt":"447","uploaded":"2025-09-20 18:00:41","up_fmt":"20 Sep 2025","up_short":"20 Sep","title":"Gangguin Adek Belajar Un New Bokep Video Indo Yakwad Jilbab Terupdate","t_esc":"Gangguin Adek Belajar Un New Bokep Video Indo Yakwad Jilbab Terupdate"},{"download_url":"https://lulustream.com/d/iyi0at9dwtcr","single_img":"https://img.lulucdn.com/iyi0at9dwtcr_t.jpg","file_code":"iyi0at9dwtcr","length":"00:16:26","views":"172","vw_fmt":"172","uploaded":"2025-09-20 18:00:41","up_fmt":"20 Sep 2025","up_short":"20 Sep","title":"Gita Amelia Lagi Belajar Gym Simontok Bokep Video Telegram Viral","t_esc":"Gita Amelia Lagi Belajar Gym Simontok Bokep Video Telegram Viral"},{"download_url":"https://lulustream.com/d/jqe2bv0muq6h","single_img":"https://img.lulucdn.com/jqe2bv0muq6h_t.jpg","file_code":"jqe2bv0muq6h","length":"00:01:05","views":"120","vw_fmt":"120","uploaded":"2025-09-20 18:00:41","up_fmt":"20 Sep 2025","up_short":"20 Sep","title":"Katanya Mau Belajar Bareng Dodstream Links Bokepsin Staklam Asupan Viral","t_esc":"Katanya Mau Belajar Bareng Dodstream Links Bokepsin Staklam Asupan Viral"},{"download_url":"https://lulustream.com/d/6r337cp2op9l","single_img":"https://img.lulucdn.com/6r337cp2op9l_t.jpg","file_code":"6r337cp2op9l","length":"00:01:04","views":"65","vw_fmt":"65","uploaded":"2025-09-20 18:00:40","up_fmt":"20 Sep 2025","up_short":"20 Sep","title":"Vid Popstream Jilbab Asupan Doodflix Pekoblive","t_esc":"Vid Popstream Jilbab Asupan Doodflix Pekoblive"},{"download_url":"https://lulustream.com/d/piokds089lz5","single_img":"https://img.lulucdn.com/piokds089lz5_t.jpg","file_code":"piokds089lz5","length":"00:13:54","views":"150","vw_fmt":"150","uploaded":"2025-09-20 18:00:40","up_fmt":"20 Sep 2025","up_short":"20 Sep","title":"Adek Kakak Ngentot New Cantik Tobrut Lagi Viral Bebasindo Pejuang Lendir Cilbo","t_esc":"Adek Kakak Ngentot New Cantik Tobrut Lagi Viral Bebasindo Pejuang Lendir Cilbo"},{"download_url":"https://lulustream.com/d/m0sdc7pcqg5r","single_img":"https://img.lulucdn.com/m0sdc7pcqg5r_t.jpg","file_code":"m0sdc7pcqg5r","length":"00:03:03","views":"283","vw_fmt":"283","uploaded":"2025-09-20 18:00:40","up_fmt":"20 Sep 2025","up_short":"20 Sep","title":"Skandal Adek Kakak Memeksiana Doodsflix Downloader Tele Asupan Viral","t_esc":"Skandal Adek Kakak Memeksiana Doodsflix Downloader Tele Asupan Viral"},{"download_url":"https://lulustream.com/d/n1x67qvc1evd","single_img":"https://img.lulucdn.com/n1x67qvc1evd_t.jpg","file_code":"n1x67qvc1evd","length":"00:02:13","views":"82","vw_fmt":"82","uploaded":"2025-09-20 18:00:40","up_fmt":"20 Sep 2025","up_short":"20 Sep","title":"Ssstwitter Com Cantik Tobrut Ngentot Simintok Indo Video Colmek","t_esc":"Ssstwitter Com Cantik Tobrut Ngentot Simintok Indo Video Colmek"},{"download_url":"https://lulustream.com/d/0my7bvh2rg3n","single_img":"https://img.lulucdn.com/0my7bvh2rg3n_t.jpg","file_code":"0my7bvh2rg3n","length":"00:15:26","views":"42","vw_fmt":"42","uploaded":"2025-09-20 18:00:30","up_fmt":"20 Sep 2025","up_short":"20 Sep","title":"Gangguin Adek Belajar Un New Doodsflix Dood Tele Pejuang Lendir Viral Jilbab","t_esc":"Gangguin Adek Belajar Un New Doodsflix Dood Tele Pejuang Lendir Viral Jilbab"},{"download_url":"https://lulustream.com/d/xv6xr7p039gs","single_img":"https://img.lulucdn.com/xv6xr7p039gs_t.jpg","file_code":"xv6xr7p039gs","length":"00:16:26","views":"68","vw_fmt":"68","uploaded":"2025-09-20 18:00:30","up_fmt":"20 Sep 2025","up_short":"20 Sep","title":"Gita Amelia Lagi Belajar Gym Xpanas Dood Telegram Downloader Videos","t_esc":"Gita Amelia Lagi Belajar Gym Xpanas Dood Telegram Downloader Videos"},{"download_url":"https://lulustream.com/d/1fdjcr8vz3mw","single_img":"https://img.lulucdn.com/1fdjcr8vz3mw_t.jpg","file_code":"1fdjcr8vz3mw","length":"00:20:08","views":"122","vw_fmt":"122","uploaded":"2025-09-20 18:00:30","up_fmt":"20 Sep 2025","up_short":"20 Sep","title":"Lagi Belajar Malah Diganggu Kakak Dood Tele Videos Viral Bokepind Video","t_esc":"Lagi Belajar Malah Diganggu Kakak Dood Tele Videos Viral Bokepind Video"},{"download_url":"https://lulustream.com/d/adlp6i2ksz7p","single_img":"https://img.lulucdn.com/adlp6i2ksz7p_t.jpg","file_code":"adlp6i2ksz7p","length":"00:08:20","views":"156","vw_fmt":"156","uploaded":"2025-09-20 17:59:54","up_fmt":"20 Sep 2025","up_short":"20 Sep","title":"Adek Kandung Masih Sempit Folder Lulustream Asupan Viral Video Sma","t_esc":"Adek Kandung Masih Sempit Folder Lulustream Asupan Viral Video Sma"},{"download_url":"https://lulustream.com/d/dny4mceenmym","single_img":"https://img.lulucdn.com/dny4mceenmym_t.jpg","file_code":"dny4mceenmym","length":"00:11:17","views":"1062","vw_fmt":"1.1K","uploaded":"2025-09-20 17:59:54","up_fmt":"20 Sep 2025","up_short":"20 Sep","title":"Crot Di Atas Perut Adek Tiri Kingbokep Popstream Indonesia Tele Memeksiana Full","t_esc":"Crot Di Atas Perut Adek Tiri Kingbokep Popstream Indonesia Tele Memeksiana Full"},{"download_url":"https://lulustream.com/d/kcbwdn4z7xmt","single_img":"https://img.lulucdn.com/kcbwdn4z7xmt_t.jpg","file_code":"kcbwdn4z7xmt","length":"00:01:59","views":"438","vw_fmt":"438","uploaded":"2025-09-20 17:59:50","up_fmt":"20 Sep 2025","up_short":"20 Sep","title":"Bokep Sange Twitter Jilbab Colmek Basah Xbokepfb Org Xpanas Lulustream Streaming Terupdate","t_esc":"Bokep Sange Twitter Jilbab Colmek Basah Xbokepfb Org Xpanas Lulustream Streaming Terupdate"},{"download_url":"https://lulustream.com/d/16t6x4zueo3d","single_img":"https://img.lulucdn.com/16t6x4zueo3d_t.jpg","file_code":"16t6x4zueo3d","length":"00:02:45","views":"3767","vw_fmt":"3.8K","uploaded":"2025-09-20 17:59:50","up_fmt":"20 Sep 2025","up_short":"20 Sep","title":"Tante Jilbab Telanjang Lalu Colmek Telegram Poophd Full Album Bokepsatset Links","t_esc":"Tante Jilbab Telanjang Lalu Colmek Telegram Poophd Full Album Bokepsatset Links"},{"download_url":"https://lulustream.com/d/7ekcvlm5xe3d","single_img":"https://img.lulucdn.com/7ekcvlm5xe3d_t.jpg","file_code":"7ekcvlm5xe3d","length":"00:01:07","views":"561","vw_fmt":"561","uploaded":"2025-09-20 17:59:50","up_fmt":"20 Sep 2025","up_short":"20 Sep","title":"Shella Skandal Adek Kakak Tele Pejuang Lendir Simontok Dood Ful Album Yakwad","t_esc":"Shella Skandal Adek Kakak Tele Pejuang Lendir Simontok Dood Ful Album Yakwad"},{"download_url":"https://lulustream.com/d/m5xwjckpg4jv","single_img":"https://img.lulucdn.com/m5xwjckpg4jv_t.jpg","file_code":"m5xwjckpg4jv","length":"00:03:03","views":"208","vw_fmt":"208","uploaded":"2025-09-20 17:59:50","up_fmt":"20 Sep 2025","up_short":"20 Sep","title":"Skandal Adek Kakak Indonesia Xpanas Dood Tobrut Doodstream","t_esc":"Skandal Adek Kakak Indonesia Xpanas Dood Tobrut Doodstream"},{"download_url":"https://lulustream.com/d/6nk6lzjsdf88","single_img":"https://img.lulucdn.com/6nk6lzjsdf88_t.jpg","file_code":"6nk6lzjsdf88","length":"00:02:13","views":"42","vw_fmt":"42","uploaded":"2025-09-20 17:59:50","up_fmt":"20 Sep 2025","up_short":"20 Sep","title":"Ssstwitter Com Bokep Dood Pekoblive Lulustream Tele Ful Album","t_esc":"Ssstwitter Com Bokep Dood Pekoblive Lulustream Tele Ful Album"},{"download_url":"https://lulustream.com/d/58xvhveo44il","single_img":"https://img.lulucdn.com/58xvhveo44il_t.jpg","file_code":"58xvhveo44il","length":"00:02:19","views":"959","vw_fmt":"959","uploaded":"2025-09-20 17:59:49","up_fmt":"20 Sep 2025","up_short":"20 Sep","title":"Bokep Asupan Remaja Sange Dikamarnya Indonesia Simontok Bokepind Poophd Videos","t_esc":"Bokep Asupan Remaja Sange Dikamarnya Indonesia Simontok Bokepind Poophd Videos"},{"download_url":"https://lulustream.com/d/f4s2o59fzjyn","single_img":"https://img.lulucdn.com/f4s2o59fzjyn_t.jpg","file_code":"f4s2o59fzjyn","length":"00:02:20","views":"672","vw_fmt":"672","uploaded":"2025-09-20 17:59:49","up_fmt":"20 Sep 2025","up_short":"20 Sep","title":"Bokep Kacamata Udah Jago Ngewe Mp Lost Lust Life Sotwe Video Colmek","t_esc":"Bokep Kacamata Udah Jago Ngewe Mp Lost Lust Life Sotwe Video Colmek"},{"download_url":"https://lulustream.com/d/fi11ti9y23ji","single_img":"https://img.lulucdn.com/fi11ti9y23ji_t.jpg","file_code":"fi11ti9y23ji","length":"00:02:20","views":"181","vw_fmt":"181","uploaded":"2025-09-20 17:59:17","up_fmt":"20 Sep 2025","up_short":"20 Sep","title":"Bokep Kacamata Udah Jago Ngewe Mp Lost Lust Life Staklam Doods Pro","t_esc":"Bokep Kacamata Udah Jago Ngewe Mp Lost Lust Life Staklam Doods Pro"},{"download_url":"https://lulustream.com/d/vdhb1qlihnpw","single_img":"https://img.lulucdn.com/vdhb1qlihnpw_t.jpg","file_code":"vdhb1qlihnpw","length":"00:01:59","views":"1048","vw_fmt":"1.0K","uploaded":"2025-09-20 17:59:17","up_fmt":"20 Sep 2025","up_short":"20 Sep","title":"Bokep Sange Twitter Jilbab Colmek Basah Xbokepfb Org Popstream Simontok Link Web","t_esc":"Bokep Sange Twitter Jilbab Colmek Basah Xbokepfb Org Popstream Simontok Link Web"},{"download_url":"https://lulustream.com/d/6izj0ky6z9mn","single_img":"https://img.lulucdn.com/6izj0ky6z9mn_t.jpg","file_code":"6izj0ky6z9mn","length":"00:01:59","views":"113","vw_fmt":"113","uploaded":"2025-09-20 17:59:17","up_fmt":"20 Sep 2025","up_short":"20 Sep","title":"Eporner Com Ix Q Oy Hrz Unboxing Memek Dan Toket Berhijab Full","t_esc":"Eporner Com Ix Q Oy Hrz Unboxing Memek Dan Toket Berhijab Full"},{"download_url":"https://lulustream.com/d/axwstql1el4e","single_img":"https://img.lulucdn.com/axwstql1el4e_t.jpg","file_code":"axwstql1el4e","length":"00:03:10","views":"654","vw_fmt":"654","uploaded":"2025-09-20 17:59:16","up_fmt":"20 Sep 2025","up_short":"20 Sep","title":"Bokep Asupan Remaja Smp Pamerin Tubuh Bagus Xbokepfb Org Terupdate Dood Tele","t_esc":"Bokep Asupan Remaja Smp Pamerin Tubuh Bagus Xbokepfb Org Terupdate Dood Tele"},{"download_url":"https://lulustream.com/d/vcdgm31l190z","single_img":"https://img.lulucdn.com/vcdgm31l190z_t.jpg","file_code":"vcdgm31l190z","length":"00:07:55","views":"877","vw_fmt":"877","uploaded":"2025-09-20 17:59:15","up_fmt":"20 Sep 2025","up_short":"20 Sep","title":"Adek Lagi Kumpul Ful Album Xpanas Viral Memeksiana Video Bokep","t_esc":"Adek Lagi Kumpul Ful Album Xpanas Viral Memeksiana Video Bokep"},{"download_url":"https://lulustream.com/d/02vjb6jtpgda","single_img":"https://img.lulucdn.com/02vjb6jtpgda_t.jpg","file_code":"02vjb6jtpgda","length":"00:08:20","views":"114","vw_fmt":"114","uploaded":"2025-09-20 17:59:14","up_fmt":"20 Sep 2025","up_short":"20 Sep","title":"Adek Kandung Masih Sempit Videos Lagi Viral Bokep Video Bokep31 Sma","t_esc":"Adek Kandung Masih Sempit Videos Lagi Viral Bokep Video Bokep31 Sma"},{"download_url":"https://lulustream.com/d/59uom1wav2fu","single_img":"https://img.lulucdn.com/59uom1wav2fu_t.jpg","file_code":"59uom1wav2fu","length":"00:03:27","views":"110","vw_fmt":"110","uploaded":"2025-09-20 17:59:14","up_fmt":"20 Sep 2025","up_short":"20 Sep","title":"Mau Tidur Di Ewe Sama Kakak Sepupunya Dood Tele Bokepind Tiktok Doodflix","t_esc":"Mau Tidur Di Ewe Sama Kakak Sepupunya Dood Tele Bokepind Tiktok Doodflix"},{"download_url":"https://lulustream.com/d/p0p6a5i07qnt","single_img":"https://img.lulucdn.com/p0p6a5i07qnt_t.jpg","file_code":"p0p6a5i07qnt","length":"00:19:38","views":"324","vw_fmt":"324","uploaded":"2025-09-20 17:59:14","up_fmt":"20 Sep 2025","up_short":"20 Sep","title":"Tobrut Bella Missu Di Ewe Waktu Tidur Ngentot Sotwe Bokepind Pekoblive Folder","t_esc":"Tobrut Bella Missu Di Ewe Waktu Tidur Ngentot Sotwe Bokepind Pekoblive Folder"},{"download_url":"https://playmogo.com/d/rr45g43dzh81","single_img":"https://thumbcdn.com/snaps/urfti53ot6db56mi.jpg","file_code":"rr45g43dzh81","length":"00:02:48","views":"707","vw_fmt":"707","uploaded":"2025-09-18 09:06:09","up_fmt":"18 Sep 2025","up_short":"18 Sep","title":"Video Bokep Website Bokepsatset Doodstream Doods Pro","t_esc":"Video Bokep Website Bokepsatset Doodstream Doods Pro"},{"download_url":"https://playmogo.com/d/9pmh9ihtqcuh","single_img":"https://thumbcdn.com/snaps/n0zbbzi1omyrwq16.jpg","file_code":"9pmh9ihtqcuh","length":"00:02:55","views":"1289","vw_fmt":"1.3K","uploaded":"2025-09-18 09:06:09","up_fmt":"18 Sep 2025","up_short":"18 Sep","title":"Akhirnya Ketemu Fullnya Doods Pro Pekoblive Cantik Tobrut Dood Viral","t_esc":"Akhirnya Ketemu Fullnya Doods Pro Pekoblive Cantik Tobrut Dood Viral"},{"download_url":"https://playmogo.com/d/0p14a7i1xfxw","single_img":"https://thumbcdn.com/snaps/p938n2qor30qv259.jpg","file_code":"0p14a7i1xfxw","length":"00:05:50","views":"4128","vw_fmt":"4.1K","uploaded":"2025-09-18 09:06:09","up_fmt":"18 Sep 2025","up_short":"18 Sep","title":"Video Yakwad Tele Pekoblive Update Links","t_esc":"Video Yakwad Tele Pekoblive Update Links"},{"download_url":"https://playmogo.com/d/a6jmmyi1oxoq","single_img":"https://thumbcdn.com/snaps/asqs3g7x1i67hlv7.jpg","file_code":"a6jmmyi1oxoq","length":"00:02:55","views":"59","vw_fmt":"59","uploaded":"2025-09-18 09:06:09","up_fmt":"18 Sep 2025","up_short":"18 Sep","title":"Akhirnya Ketemu Fullnya Dood Indo Simontok Viral Jilbab","t_esc":"Akhirnya Ketemu Fullnya Dood Indo Simontok Viral Jilbab"},{"download_url":"https://playmogo.com/d/cfzy564zt4o1","single_img":"https://thumbcdn.com/snaps/cu5snmz4jlw1bln4.jpg","file_code":"cfzy564zt4o1","length":"00:01:26","views":"616","vw_fmt":"616","uploaded":"2025-09-18 09:06:09","up_fmt":"18 Sep 2025","up_short":"18 Sep","title":"Akhirnya Ketemu Fullnya Apdet Terbaru Update Dodstream Telegram Dood Tele Video Indo","t_esc":"Akhirnya Ketemu Fullnya Apdet Terbaru Update Dodstream Telegram Dood Tele Video Indo"},{"download_url":"https://playmogo.com/d/xwlso40edcvg","single_img":"https://thumbcdn.com/snaps/xo0o86huygo6ovwt.jpg","file_code":"xwlso40edcvg","length":"00:02:04","views":"1857","vw_fmt":"1.9K","uploaded":"2025-09-18 09:06:09","up_fmt":"18 Sep 2025","up_short":"18 Sep","title":"Ayya Zahra Simontok Doodstreem Viral Bochiel Lulustream","t_esc":"Ayya Zahra Simontok Doodstreem Viral Bochiel Lulustream"},{"download_url":"https://playmogo.com/d/ykvk3sm5vta3","single_img":"https://thumbcdn.com/snaps/l238cj8nf9e1ph5s.jpg","file_code":"ykvk3sm5vta3","length":"00:02:06","views":"335","vw_fmt":"335","uploaded":"2025-09-18 09:06:09","up_fmt":"18 Sep 2025","up_short":"18 Sep","title":"Ayaa Zahra Update New Video Viral Downloader Cilbo Doods Pro Colmek","t_esc":"Ayaa Zahra Update New Video Viral Downloader Cilbo Doods Pro Colmek"},{"download_url":"https://playmogo.com/d/qc2l1elc9ncm","single_img":"https://thumbcdn.com/snaps/u05a9so9iul1nchf.jpg","file_code":"qc2l1elc9ncm","length":"00:06:14","views":"1531","vw_fmt":"1.5K","uploaded":"2025-09-18 09:06:09","up_fmt":"18 Sep 2025","up_short":"18 Sep","title":"Ayya Zahra Pekoblive Asupan Viral Doods Pro Video Indo Poophd","t_esc":"Ayya Zahra Pekoblive Asupan Viral Doods Pro Video Indo Poophd"},{"download_url":"https://playmogo.com/d/iztlujf9u436","single_img":"https://thumbcdn.com/snaps/b1l08ufmu3m1hmj0.jpg","file_code":"iztlujf9u436","length":"00:07:14","views":"874","vw_fmt":"874","uploaded":"2025-09-18 09:06:09","up_fmt":"18 Sep 2025","up_short":"18 Sep","title":"Ayya Zahra Versi Longdur Video Indo Links Cilbo Doostream Colmek","t_esc":"Ayya Zahra Versi Longdur Video Indo Links Cilbo Doostream Colmek"},{"download_url":"https://playmogo.com/d/h7kfhafvpcge","single_img":"https://thumbcdn.com/snaps/t7y5wi56hmlq1x2q.jpg","file_code":"h7kfhafvpcge","length":"00:01:04","views":"2155","vw_fmt":"2.2K","uploaded":"2025-09-18 09:06:09","up_fmt":"18 Sep 2025","up_short":"18 Sep","title":"Ayaa Zahra Update New Yakwad Doods Pro Full Album Asupan Viral Pemersatu","t_esc":"Ayaa Zahra Update New Yakwad Doods Pro Full Album Asupan Viral Pemersatu"},{"download_url":"https://playmogo.com/d/u0ehy6y0b9zc","single_img":"https://thumbcdn.com/snaps/3oqex33ykso1bnaz.jpg","file_code":"u0ehy6y0b9zc","length":"00:10:12","views":"804","vw_fmt":"804","uploaded":"2025-09-18 09:06:09","up_fmt":"18 Sep 2025","up_short":"18 Sep","title":"Hijab Hitam Sange Berat Poophd Video Viral Bokepin Cilbo Bokepsatset","t_esc":"Hijab Hitam Sange Berat Poophd Video Viral Bokepin Cilbo Bokepsatset"},{"download_url":"https://playmogo.com/d/pl0mxma581yw","single_img":"https://thumbcdn.com/snaps/66li357a0mttq1jw.jpg","file_code":"pl0mxma581yw","length":"00:09:56","views":"286","vw_fmt":"286","uploaded":"2025-09-18 09:06:09","up_fmt":"18 Sep 2025","up_short":"18 Sep","title":"Seleb Cacargh Tobrut Doggy Pantat Mulus Xpanas Jilbab Videos Bokepsin Pemersatu","t_esc":"Seleb Cacargh Tobrut Doggy Pantat Mulus Xpanas Jilbab Videos Bokepsin Pemersatu"},{"download_url":"https://playmogo.com/d/covljl6hjhhr","single_img":"https://thumbcdn.com/snaps/veznwwn85j8gqy9k.jpg","file_code":"covljl6hjhhr","length":"00:02:15","views":"450","vw_fmt":"450","uploaded":"2025-09-18 09:06:09","up_fmt":"18 Sep 2025","up_short":"18 Sep","title":"Vcs Seleb Cacargh Tobrut Video Bokep Toketbagus Indo Doodstreem","t_esc":"Vcs Seleb Cacargh Tobrut Video Bokep Toketbagus Indo Doodstreem"},{"download_url":"https://playmogo.com/d/snoavz4urobp","single_img":"https://thumbcdn.com/snaps/vg7u25kv3ezsevs5.jpg","file_code":"snoavz4urobp","length":"00:06:11","views":"418","vw_fmt":"418","uploaded":"2025-09-18 09:06:09","up_fmt":"18 Sep 2025","up_short":"18 Sep","title":"Vcs Caca Lagi Viral Bochiel Terabox Doodstream Bokepin","t_esc":"Vcs Caca Lagi Viral Bochiel Terabox Doodstream Bokepin"},{"download_url":"https://playmogo.com/d/zz1r1mwg1sf5","single_img":"https://thumbcdn.com/snaps/r2jww3vw9xwz0fqq.jpg","file_code":"zz1r1mwg1sf5","length":"00:17:50","views":"2724","vw_fmt":"2.7K","uploaded":"2025-09-18 09:06:09","up_fmt":"18 Sep 2025","up_short":"18 Sep","title":"Cacaarrgrgrgrhrhr Live Blunder Update Telegram Twitter Simontok Doodstreem Doodstream","t_esc":"Cacaarrgrgrgrhrhr Live Blunder Update Telegram Twitter Simontok Doodstreem Doodstream"},{"download_url":"https://playmogo.com/d/bqwyo14n2mg5","single_img":"https://thumbcdn.com/snaps/aozpdpipbbl6sjvt.jpg","file_code":"bqwyo14n2mg5","length":"00:03:19","views":"1395","vw_fmt":"1.4K","uploaded":"2025-09-18 09:06:09","up_fmt":"18 Sep 2025","up_short":"18 Sep","title":"Vidcloudtv Netea Ish Lqsglv Doodlix Org Streaming Videos Doodsflix Live Pemersatu","t_esc":"Vidcloudtv Netea Ish Lqsglv Doodlix Org Streaming Videos Doodsflix Live Pemersatu"},{"download_url":"https://playmogo.com/d/5b1c5i44e2rk","single_img":"https://thumbcdn.com/snaps/bckoxp59t647cphv.jpg","file_code":"5b1c5i44e2rk","length":"00:03:14","views":"508","vw_fmt":"508","uploaded":"2025-09-18 09:06:09","up_fmt":"18 Sep 2025","up_short":"18 Sep","title":"Caca Janda Muda Streaming Jilbab Bebasindo Doodsflix Doostream","t_esc":"Caca Janda Muda Streaming Jilbab Bebasindo Doodsflix Doostream"},{"download_url":"https://playmogo.com/d/f7j3r71pa1vy","single_img":"https://thumbcdn.com/snaps/8l1rz41mlhg1h9mr.jpg","file_code":"f7j3r71pa1vy","length":"00:05:11","views":"738","vw_fmt":"738","uploaded":"2025-09-18 09:06:09","up_fmt":"18 Sep 2025","up_short":"18 Sep","title":"Caca Janda Muda Indo Doodstream Bokepind Asupan Viral","t_esc":"Caca Janda Muda Indo Doodstream Bokepind Asupan Viral"},{"download_url":"https://playmogo.com/d/zgr7bkt9do99","single_img":"https://thumbcdn.com/snaps/degyqqof184wp6eg.jpg","file_code":"zgr7bkt9do99","length":"00:03:19","views":"36","vw_fmt":"36","uploaded":"2025-09-18 09:06:09","up_fmt":"18 Sep 2025","up_short":"18 Sep","title":"Vidcloudtv Netea Ish Lqsglv Doodlix Org Pejuang Lendir Pekoblive Simontok Video Viral","t_esc":"Vidcloudtv Netea Ish Lqsglv Doodlix Org Pejuang Lendir Pekoblive Simontok Video Viral"},{"download_url":"https://playmogo.com/d/hlpp2melx9vz","single_img":"https://thumbcdn.com/snaps/aukyreokfmzuizza.jpg","file_code":"hlpp2melx9vz","length":"00:03:14","views":"68","vw_fmt":"68","uploaded":"2025-09-18 09:06:09","up_fmt":"18 Sep 2025","up_short":"18 Sep","title":"Caca Janda Muda Tiktok Terabox Asupan Viral Links Indonesia","t_esc":"Caca Janda Muda Tiktok Terabox Asupan Viral Links Indonesia"},{"download_url":"https://playmogo.com/d/37o2dzhjqu38","single_img":"https://thumbcdn.com/snaps/ugt71t8bfnm2mxyb.jpg","file_code":"37o2dzhjqu38","length":"00:05:11","views":"168","vw_fmt":"168","uploaded":"2025-09-18 09:06:09","up_fmt":"18 Sep 2025","up_short":"18 Sep","title":"Caca Janda Muda Downloader Terupdate Lulustream Telegram Video Sma","t_esc":"Caca Janda Muda Downloader Terupdate Lulustream Telegram Video Sma"},{"download_url":"https://playmogo.com/d/e1wd1xfq5913","single_img":"https://thumbcdn.com/snaps/8pjusv5bspu6eldj.jpg","file_code":"e1wd1xfq5913","length":"00:18:19","views":"7968","vw_fmt":"8.0K","uploaded":"2025-09-18 09:05:14","up_fmt":"18 Sep 2025","up_short":"18 Sep","title":"Monic Full Percakapan Asupan Bokep Video Ngentot Popstream Pekoblive","t_esc":"Monic Full Percakapan Asupan Bokep Video Ngentot Popstream Pekoblive"},{"download_url":"https://playmogo.com/d/cyiyqa1hj2q0","single_img":"https://thumbcdn.com/snaps/fa3woqs0r4jv9eti.jpg","file_code":"cyiyqa1hj2q0","length":"00:51:39","views":"1593","vw_fmt":"1.6K","uploaded":"2025-09-18 09:05:14","up_fmt":"18 Sep 2025","up_short":"18 Sep","title":"Monic Live Bling Terbaru Jilbab Viral Xpanas Lulustream","t_esc":"Monic Live Bling Terbaru Jilbab Viral Xpanas Lulustream"},{"download_url":"https://playmogo.com/d/og4zzfjm1e38","single_img":"https://thumbcdn.com/snaps/wlzwwjztzvf1k5td.jpg","file_code":"og4zzfjm1e38","length":"00:47:08","views":"1793","vw_fmt":"1.8K","uploaded":"2025-09-18 09:05:14","up_fmt":"18 Sep 2025","up_short":"18 Sep","title":"Live Orgasme Monic Poophd Popstream Lulustream Terabox Toketbagus","t_esc":"Live Orgasme Monic Poophd Popstream Lulustream Terabox Toketbagus"},{"download_url":"https://playmogo.com/d/64q2kgwwh2ie","single_img":"https://thumbcdn.com/snaps/0oa5iumql9y4gc5r.jpg","file_code":"64q2kgwwh2ie","length":"00:23:11","views":"301","vw_fmt":"301","uploaded":"2025-09-18 09:05:14","up_fmt":"18 Sep 2025","up_short":"18 Sep","title":"Monic Ngewe Dood Tele Bokep31 Xpanas Pemersatu Live","t_esc":"Monic Ngewe Dood Tele Bokep31 Xpanas Pemersatu Live"},{"download_url":"https://playmogo.com/d/4hyooc861u5w","single_img":"https://thumbcdn.com/snaps/dscv40556fber2rf.jpg","file_code":"4hyooc861u5w","length":"00:46:32","views":"654","vw_fmt":"654","uploaded":"2025-09-18 09:05:14","up_fmt":"18 Sep 2025","up_short":"18 Sep","title":"Dedekk Monic Siii Biduan Racing Wajah Cantik Bodi Bahrnulnya Buat Piala Bergilir","t_esc":"Dedekk Monic Siii Biduan Racing Wajah Cantik Bodi Bahrnulnya Buat Piala Bergilir"},{"download_url":"https://playmogo.com/d/31b57d1hfc8u","single_img":"https://thumbcdn.com/snaps/hlbr0fjr7d14wpw9.jpg","file_code":"31b57d1hfc8u","length":"00:09:16","views":"1897","vw_fmt":"1.9K","uploaded":"2025-09-18 09:05:14","up_fmt":"18 Sep 2025","up_short":"18 Sep","title":"Bokep Indo Laura Toge Update Skin Perawat Bokepindoh Popstream Simontok Doodsflix Video","t_esc":"Bokep Indo Laura Toge Update Skin Perawat Bokepindoh Popstream Simontok Doodsflix Video"},{"download_url":"https://playmogo.com/d/8c767kvt5pyb","single_img":"https://thumbcdn.com/snaps/46vw53hfmcq1wzmg.jpg","file_code":"8c767kvt5pyb","length":"00:16:56","views":"953","vw_fmt":"953","uploaded":"2025-09-18 09:05:14","up_fmt":"18 Sep 2025","up_short":"18 Sep","title":"Laura Buka Jilbab Si Kalem Ternyata Beringas Kingbokep Bokep31 Doostream Live Pejuang","t_esc":"Laura Buka Jilbab Si Kalem Ternyata Beringas Kingbokep Bokep31 Doostream Live Pejuang"},{"download_url":"https://playmogo.com/d/5jiv43hiwy58","single_img":"https://thumbcdn.com/snaps/6z02c6ucfg1qes26.jpg","file_code":"5jiv43hiwy58","length":"00:04:49","views":"354","vw_fmt":"354","uploaded":"2025-09-18 09:05:14","up_fmt":"18 Sep 2025","up_short":"18 Sep","title":"Semua Tentang Laura Gak Ada Yang Pernah Gagal Kingbokep Streaming Video Indo","t_esc":"Semua Tentang Laura Gak Ada Yang Pernah Gagal Kingbokep Streaming Video Indo"},{"download_url":"https://lulustream.com/d/qjxlj4pxkm5b","single_img":"https://img.lulucdn.com/qjxlj4pxkm5b_t.jpg","file_code":"qjxlj4pxkm5b","length":"00:06:58","views":"26779","vw_fmt":"26.8K","uploaded":"2025-09-17 23:35:57","up_fmt":"17 Sep 2025","up_short":"17 Sep","title":"Yona Tante Obrut Tele Thelulu Simontok Doostream Bokepsin Doodsflix Indo","t_esc":"Yona Tante Obrut Tele Thelulu Simontok Doostream Bokepsin Doodsflix Indo"},{"download_url":"https://lulustream.com/d/b66bj2c301c0","single_img":"https://img.lulucdn.com/b66bj2c301c0_t.jpg","file_code":"b66bj2c301c0","length":"00:03:52","views":"6658","vw_fmt":"6.7K","uploaded":"2025-09-17 23:35:57","up_fmt":"17 Sep 2025","up_short":"17 Sep","title":"Yona Tante Obrut Tele Thelulu Cantik Tobrut Memeksiana Poophd Live Doods Pro","t_esc":"Yona Tante Obrut Tele Thelulu Cantik Tobrut Memeksiana Poophd Live Doods Pro"},{"download_url":"https://lulustream.com/d/7tsin3dued9s","single_img":"https://img.lulucdn.com/7tsin3dued9s_t.jpg","file_code":"7tsin3dued9s","length":"00:02:37","views":"13063","vw_fmt":"13.1K","uploaded":"2025-09-17 23:35:57","up_fmt":"17 Sep 2025","up_short":"17 Sep","title":"Yona Tante Obrut Tele Thelulu Lokal Simintok Bokepsin Links Terupdate","t_esc":"Yona Tante Obrut Tele Thelulu Lokal Simintok Bokepsin Links Terupdate"},{"download_url":"https://lulustream.com/d/s5bzhyx9td2l","single_img":"https://img.lulucdn.com/s5bzhyx9td2l_t.jpg","file_code":"s5bzhyx9td2l","length":"00:03:25","views":"14913","vw_fmt":"14.9K","uploaded":"2025-09-17 23:35:57","up_fmt":"17 Sep 2025","up_short":"17 Sep","title":"Yona Tante Obrut Tele Thelulu Doodsflix Twitter Staklam Lokal Tiktok","t_esc":"Yona Tante Obrut Tele Thelulu Doodsflix Twitter Staklam Lokal Tiktok"},{"download_url":"https://lulustream.com/d/t2pn27ce1nm1","single_img":"https://img.lulucdn.com/t2pn27ce1nm1_t.jpg","file_code":"t2pn27ce1nm1","length":"00:08:00","views":"11781","vw_fmt":"11.8K","uploaded":"2025-09-17 23:35:56","up_fmt":"17 Sep 2025","up_short":"17 Sep","title":"Yona Tante Obrut Tele Thelulu Cantik Tobrut Live Ngentot Video Viral Doods","t_esc":"Yona Tante Obrut Tele Thelulu Cantik Tobrut Live Ngentot Video Viral Doods"},{"download_url":"https://lulustream.com/d/xarme42j6tvq","single_img":"https://img.lulucdn.com/xarme42j6tvq_t.jpg","file_code":"xarme42j6tvq","length":"00:05:49","views":"7594","vw_fmt":"7.6K","uploaded":"2025-09-17 23:35:56","up_fmt":"17 Sep 2025","up_short":"17 Sep","title":"Yona Tante Obrut Tele Thelulu Telegram Videos Indonesia Bokep Video Bokepsatset","t_esc":"Yona Tante Obrut Tele Thelulu Telegram Videos Indonesia Bokep Video Bokepsatset"},{"download_url":"https://lulustream.com/d/yjmg6pxkvvwf","single_img":"https://img.lulucdn.com/yjmg6pxkvvwf_t.jpg","file_code":"yjmg6pxkvvwf","length":"00:03:45","views":"3878","vw_fmt":"3.9K","uploaded":"2025-09-17 23:35:56","up_fmt":"17 Sep 2025","up_short":"17 Sep","title":"Yona Tante Obrut Tele Thelulu Bokep31 Poophd Pekoblive Cilbo Video Colmek","t_esc":"Yona Tante Obrut Tele Thelulu Bokep31 Poophd Pekoblive Cilbo Video Colmek"},{"download_url":"https://lulustream.com/d/snh6p0edh2ma","single_img":"https://img.lulucdn.com/snh6p0edh2ma_t.jpg","file_code":"snh6p0edh2ma","length":"00:03:24","views":"6527","vw_fmt":"6.5K","uploaded":"2025-09-17 23:35:56","up_fmt":"17 Sep 2025","up_short":"17 Sep","title":"Yona Tante Obrut Tele Thelulu Xpanas Lokal Asupan Viral Terupdate Dood","t_esc":"Yona Tante Obrut Tele Thelulu Xpanas Lokal Asupan Viral Terupdate Dood"},{"download_url":"https://lulustream.com/d/72apcwn39juk","single_img":"https://img.lulucdn.com/72apcwn39juk_t.jpg","file_code":"72apcwn39juk","length":"00:02:06","views":"4144","vw_fmt":"4.1K","uploaded":"2025-09-17 23:35:55","up_fmt":"17 Sep 2025","up_short":"17 Sep","title":"Yona Tante Obrut Tele Thelulu Downloader Terabox Live Simintok Bokepind","t_esc":"Yona Tante Obrut Tele Thelulu Downloader Terabox Live Simintok Bokepind"},{"download_url":"https://lulustream.com/d/2ru4f0bv32tt","single_img":"https://img.lulucdn.com/2ru4f0bv32tt_t.jpg","file_code":"2ru4f0bv32tt","length":"00:48:43","views":"4072","vw_fmt":"4.1K","uploaded":"2025-09-17 14:32:38","up_fmt":"17 Sep 2025","up_short":"17 Sep","title":"Film Semi Rumput Tetangga Kelas Bintang Zafira Sun Full Album Lagi Viral","t_esc":"Film Semi Rumput Tetangga Kelas Bintang Zafira Sun Full Album Lagi Viral"},{"download_url":"https://lulustream.com/d/hj5kfmtu4spr","single_img":"https://img.lulucdn.com/hj5kfmtu4spr_t.jpg","file_code":"hj5kfmtu4spr","length":"00:32:24","views":"10659","vw_fmt":"10.7K","uploaded":"2025-09-17 14:32:38","up_fmt":"17 Sep 2025","up_short":"17 Sep","title":"Kelas Bintang Mimi Cucu Part Tobrut Videos Cantik Doodflix Dodstream","t_esc":"Kelas Bintang Mimi Cucu Part Tobrut Videos Cantik Doodflix Dodstream"},{"download_url":"https://lulustream.com/d/c0yrkc7vl0td","single_img":"https://img.lulucdn.com/c0yrkc7vl0td_t.jpg","file_code":"c0yrkc7vl0td","length":"00:03:25","views":"439","vw_fmt":"439","uploaded":"2025-09-17 14:32:37","up_fmt":"17 Sep 2025","up_short":"17 Sep","title":"Bokep Indo Bts Film Porno Virly Virginia Mp Terupdate Bebasindo Bokepsatset Lulustream","t_esc":"Bokep Indo Bts Film Porno Virly Virginia Mp Terupdate Bebasindo Bokepsatset Lulustream"},{"download_url":"https://lulustream.com/d/k3eari7tqhkh","single_img":"https://img.lulucdn.com/k3eari7tqhkh_t.jpg","file_code":"k3eari7tqhkh","length":"00:12:38","views":"4738","vw_fmt":"4.7K","uploaded":"2025-09-17 14:32:01","up_fmt":"17 Sep 2025","up_short":"17 Sep","title":"Bokep Indo Di Ajak Ngamar Sama Supir Truk Jalan Links Asupan Twitter","t_esc":"Bokep Indo Di Ajak Ngamar Sama Supir Truk Jalan Links Asupan Twitter"},{"download_url":"https://lulustream.com/d/ik15cpoe5khn","single_img":"https://img.lulucdn.com/ik15cpoe5khn_t.jpg","file_code":"ik15cpoe5khn","length":"00:05:48","views":"24238","vw_fmt":"24.2K","uploaded":"2025-09-17 14:32:01","up_fmt":"17 Sep 2025","up_short":"17 Sep","title":"Bokep Indo Istri Tetangga Terlalu Menggoda Di Jalan Indonesia Video Colmek Website","t_esc":"Bokep Indo Istri Tetangga Terlalu Menggoda Di Jalan Indonesia Video Colmek Website"},{"download_url":"https://lulustream.com/d/gs1ven45tugb","single_img":"https://img.lulucdn.com/gs1ven45tugb_t.jpg","file_code":"gs1ven45tugb","length":"00:06:33","views":"3507","vw_fmt":"3.5K","uploaded":"2025-09-17 14:32:01","up_fmt":"17 Sep 2025","up_short":"17 Sep","title":"Tante Yona Hijab B Sewa Brondong Bokepviralterbaru Indo Toketbagus Doodstreem Bebasindo Lulustream","t_esc":"Tante Yona Hijab B Sewa Brondong Bokepviralterbaru Indo Toketbagus Doodstreem Bebasindo Lulustream"},{"download_url":"https://lulustream.com/d/adtexr0m8nq8","single_img":"https://img.lulucdn.com/adtexr0m8nq8_t.jpg","file_code":"adtexr0m8nq8","length":"00:01:06","views":"2174","vw_fmt":"2.2K","uploaded":"2025-09-17 14:32:01","up_fmt":"17 Sep 2025","up_short":"17 Sep","title":"Tante Yona Doostream Bokepsin Doodstreem Toketbagus Link Web","t_esc":"Tante Yona Doostream Bokepsin Doodstreem Toketbagus Link Web"},{"download_url":"https://lulustream.com/d/ygno3uqshzyx","single_img":"https://img.lulucdn.com/ygno3uqshzyx_t.jpg","file_code":"ygno3uqshzyx","length":"00:11:51","views":"8167","vw_fmt":"8.2K","uploaded":"2025-09-17 14:32:00","up_fmt":"17 Sep 2025","up_short":"17 Sep","title":"Bokep Indo Malam Jumataan Bersama Bunda Tercinta Pejuang Lendir Xpanas Dood Doodsflix","t_esc":"Bokep Indo Malam Jumataan Bersama Bunda Tercinta Pejuang Lendir Xpanas Dood Doodsflix"},{"download_url":"https://lulustream.com/d/huvux5xp2mf1","single_img":"https://img.lulucdn.com/huvux5xp2mf1_t.jpg","file_code":"huvux5xp2mf1","length":"00:01:32","views":"2243","vw_fmt":"2.2K","uploaded":"2025-09-17 14:32:00","up_fmt":"17 Sep 2025","up_short":"17 Sep","title":"Gaya Muda Mudi Bercinta Memeksiana Doostream Bebasindo Simontok Twitter","t_esc":"Gaya Muda Mudi Bercinta Memeksiana Doostream Bebasindo Simontok Twitter"},{"download_url":"https://lulustream.com/d/aws7tji5rnjy","single_img":"https://img.lulucdn.com/aws7tji5rnjy_t.jpg","file_code":"aws7tji5rnjy","length":"00:11:02","views":"4865","vw_fmt":"4.9K","uploaded":"2025-09-17 14:32:00","up_fmt":"17 Sep 2025","up_short":"17 Sep","title":"Aku Tak Bisa Beritahu Istriku Sekalipun Muluu Robek Percaya Ibu Mertuaku Hamil","t_esc":"Aku Tak Bisa Beritahu Istriku Sekalipun Muluu Robek Percaya Ibu Mertuaku Hamil"},{"download_url":"https://lulustream.com/d/jtg3u9ovkbvb","single_img":"https://img.lulucdn.com/jtg3u9ovkbvb_t.jpg","file_code":"jtg3u9ovkbvb","length":"00:28:47","views":"2337","vw_fmt":"2.3K","uploaded":"2025-09-17 14:31:59","up_fmt":"17 Sep 2025","up_short":"17 Sep","title":"Dea Ometv Sicantik Mp Cilbo Video Indo Xpanas Dodstream Telegram","t_esc":"Dea Ometv Sicantik Mp Cilbo Video Indo Xpanas Dodstream Telegram"},{"download_url":"https://lulustream.com/d/jepq89v4ma4p","single_img":"https://img.lulucdn.com/jepq89v4ma4p_t.jpg","file_code":"jepq89v4ma4p","length":"00:10:50","views":"6703","vw_fmt":"6.7K","uploaded":"2025-09-17 14:31:59","up_fmt":"17 Sep 2025","up_short":"17 Sep","title":"Bercinta Dengan Seorang Pelayan Kamar Telegram Bochiel Cilbo Bokepsin Full Album","t_esc":"Bercinta Dengan Seorang Pelayan Kamar Telegram Bochiel Cilbo Bokepsin Full Album"},{"download_url":"https://lulustream.com/d/v3e6qdd84qzt","single_img":"https://img.lulucdn.com/v3e6qdd84qzt_t.jpg","file_code":"v3e6qdd84qzt","length":"00:07:00","views":"3629","vw_fmt":"3.6K","uploaded":"2025-09-17 14:31:59","up_fmt":"17 Sep 2025","up_short":"17 Sep","title":"Bokep Cinta Antara Tante Dan Keponakan Cilbo Terabox Videos Full Album Downloader","t_esc":"Bokep Cinta Antara Tante Dan Keponakan Cilbo Terabox Videos Full Album Downloader"},{"download_url":"https://lulustream.com/d/cjje8q6hjxh7","single_img":"https://img.lulucdn.com/cjje8q6hjxh7_t.jpg","file_code":"cjje8q6hjxh7","length":"00:04:58","views":"8145","vw_fmt":"8.1K","uploaded":"2025-09-17 14:31:58","up_fmt":"17 Sep 2025","up_short":"17 Sep","title":"Ome Tv Hijabers Paker Tetek Mancungnya Live Indo Bochiel Simontok Video Viral","t_esc":"Ome Tv Hijabers Paker Tetek Mancungnya Live Indo Bochiel Simontok Video Viral"},{"download_url":"https://lulustream.com/d/8ecetbjs7smp","single_img":"https://img.lulucdn.com/8ecetbjs7smp_t.jpg","file_code":"8ecetbjs7smp","length":"00:06:28","views":"4188","vw_fmt":"4.2K","uploaded":"2025-09-17 14:31:58","up_fmt":"17 Sep 2025","up_short":"17 Sep","title":"Ometv Sma Pengen Jadi Simpanan Bokep31 Jilbab Dood Tele Video Indo Link","t_esc":"Ometv Sma Pengen Jadi Simpanan Bokep31 Jilbab Dood Tele Video Indo Link"},{"download_url":"https://lulustream.com/d/4zfkk8l31q44","single_img":"https://img.lulucdn.com/4zfkk8l31q44_t.jpg","file_code":"4zfkk8l31q44","length":"00:06:49","views":"4960","vw_fmt":"5.0K","uploaded":"2025-09-17 14:31:57","up_fmt":"17 Sep 2025","up_short":"17 Sep","title":"Pelan Sayang Pekoblive Dood Videos Bokep Video Tiktok","t_esc":"Pelan Sayang Pekoblive Dood Videos Bokep Video Tiktok"},{"download_url":"https://lulustream.com/d/siz1o24k24j1","single_img":"https://img.lulucdn.com/siz1o24k24j1_t.jpg","file_code":"siz1o24k24j1","length":"00:01:24","views":"1297","vw_fmt":"1.3K","uploaded":"2025-09-17 14:31:29","up_fmt":"17 Sep 2025","up_short":"17 Sep","title":"Ayash Dodstream Video Bokep Doods Pro Update Website","t_esc":"Ayash Dodstream Video Bokep Doods Pro Update Website"},{"download_url":"https://lulustream.com/d/pilr9bqcd0c7","single_img":"https://img.lulucdn.com/pilr9bqcd0c7_t.jpg","file_code":"pilr9bqcd0c7","length":"00:06:47","views":"4348","vw_fmt":"4.3K","uploaded":"2025-09-17 14:31:28","up_fmt":"17 Sep 2025","up_short":"17 Sep","title":"Andini Cosplay Waifu Maid Lagi Viral Downloader Poophd Jilbab Live","t_esc":"Andini Cosplay Waifu Maid Lagi Viral Downloader Poophd Jilbab Live"},{"download_url":"https://lulustream.com/d/9dffofzee3i4","single_img":"https://img.lulucdn.com/9dffofzee3i4_t.jpg","file_code":"9dffofzee3i4","length":"00:03:24","views":"1991","vw_fmt":"2.0K","uploaded":"2025-09-17 14:31:28","up_fmt":"17 Sep 2025","up_short":"17 Sep","title":"Andini Mainin Meki Dan Anal Pake Pulpen Lulustream Cilbo Popstream Downloader Jilbab","t_esc":"Andini Mainin Meki Dan Anal Pake Pulpen Lulustream Cilbo Popstream Downloader Jilbab"},{"download_url":"https://lulustream.com/d/c1ydiht5u2pn","single_img":"https://img.lulucdn.com/c1ydiht5u2pn_t.jpg","file_code":"c1ydiht5u2pn","length":"00:02:58","views":"1222","vw_fmt":"1.2K","uploaded":"2025-09-17 14:31:28","up_fmt":"17 Sep 2025","up_short":"17 Sep","title":"Andini Pake Daster Kancut Ijo Mainin Meki Poophd Full Album Links Cantik","t_esc":"Andini Pake Daster Kancut Ijo Mainin Meki Poophd Full Album Links Cantik"},{"download_url":"https://lulustream.com/d/zopmfks8ymt6","single_img":"https://img.lulucdn.com/zopmfks8ymt6_t.jpg","file_code":"zopmfks8ymt6","length":"00:05:06","views":"1168","vw_fmt":"1.2K","uploaded":"2025-09-17 14:31:28","up_fmt":"17 Sep 2025","up_short":"17 Sep","title":"Andini Kaos Imut Kutang Kuning Mainin Meki Ngewe Sama Guling Telegram Downloader","t_esc":"Andini Kaos Imut Kutang Kuning Mainin Meki Ngewe Sama Guling Telegram Downloader"},{"download_url":"https://lulustream.com/d/os6y3o0sqh6p","single_img":"https://img.lulucdn.com/os6y3o0sqh6p_t.jpg","file_code":"os6y3o0sqh6p","length":"00:14:13","views":"7212","vw_fmt":"7.2K","uploaded":"2025-09-17 14:31:27","up_fmt":"17 Sep 2025","up_short":"17 Sep","title":"Udah Belajar Ngewe Bokepsatset Bochiel Asupan Viral Video Indo Tiktok","t_esc":"Udah Belajar Ngewe Bokepsatset Bochiel Asupan Viral Video Indo Tiktok"},{"download_url":"https://lulustream.com/d/8qabwnthvwb0","single_img":"https://img.lulucdn.com/8qabwnthvwb0_t.jpg","file_code":"8qabwnthvwb0","length":"00:16:26","views":"1917","vw_fmt":"1.9K","uploaded":"2025-09-17 14:31:27","up_fmt":"17 Sep 2025","up_short":"17 Sep","title":"Gita Amelia Lagi Belajar Gym Downloader Viral Yakwad Video Colmek Bokep31","t_esc":"Gita Amelia Lagi Belajar Gym Downloader Viral Yakwad Video Colmek Bokep31"},{"download_url":"https://lulustream.com/d/s5htv38jlolm","single_img":"https://img.lulucdn.com/s5htv38jlolm_t.jpg","file_code":"s5htv38jlolm","length":"00:06:16","views":"280","vw_fmt":"280","uploaded":"2025-09-17 14:31:27","up_fmt":"17 Sep 2025","up_short":"17 Sep","title":"Tugas Kuliahbc Alasan Belajarif Kelompokbh Indo Dood Tele Twitter Pekoblive","t_esc":"Tugas Kuliahbc Alasan Belajarif Kelompokbh Indo Dood Tele Twitter Pekoblive"},{"download_url":"https://lulustream.com/d/stgqra291sqd","single_img":"https://img.lulucdn.com/stgqra291sqd_t.jpg","file_code":"stgqra291sqd","length":"00:05:08","views":"2072","vw_fmt":"2.1K","uploaded":"2025-09-17 14:31:27","up_fmt":"17 Sep 2025","up_short":"17 Sep","title":"Santriwati Jilbab Polos Belajar C Lmek Video Viral Bokepsatset Toketbagus Terupdate Doods","t_esc":"Santriwati Jilbab Polos Belajar C Lmek Video Viral Bokepsatset Toketbagus Terupdate Doods"},{"download_url":"https://lulustream.com/d/tlopmr2svzco","single_img":"https://img.lulucdn.com/tlopmr2svzco_t.jpg","file_code":"tlopmr2svzco","length":"00:08:20","views":"3467","vw_fmt":"3.5K","uploaded":"2025-09-17 14:31:03","up_fmt":"17 Sep 2025","up_short":"17 Sep","title":"Adek Kandung Masih Sempit Link Web Doodflix Indo Downloader Dodstream","t_esc":"Adek Kandung Masih Sempit Link Web Doodflix Indo Downloader Dodstream"},{"download_url":"https://lulustream.com/d/1zhdwiwe59bl","single_img":"https://img.lulucdn.com/1zhdwiwe59bl_t.jpg","file_code":"1zhdwiwe59bl","length":"00:01:05","views":"2500","vw_fmt":"2.5K","uploaded":"2025-09-17 14:31:03","up_fmt":"17 Sep 2025","up_short":"17 Sep","title":"Bokep Adik Ipar Sudah Minta Ampun Bokepind Ngentot Memeksiana Bochiel Simontok","t_esc":"Bokep Adik Ipar Sudah Minta Ampun Bokepind Ngentot Memeksiana Bochiel Simontok"},{"download_url":"https://lulustream.com/d/gyb27jnbfi2v","single_img":"https://img.lulucdn.com/gyb27jnbfi2v_t.jpg","file_code":"gyb27jnbfi2v","length":"00:03:27","views":"873","vw_fmt":"873","uploaded":"2025-09-17 14:31:03","up_fmt":"17 Sep 2025","up_short":"17 Sep","title":"Mau Tidur Di Ewe Sama Kakak Sepupunya Yakwad Downloader Twitter Video Indo","t_esc":"Mau Tidur Di Ewe Sama Kakak Sepupunya Yakwad Downloader Twitter Video Indo"},{"download_url":"https://lulustream.com/d/zckaw41jo1u5","single_img":"https://img.lulucdn.com/zckaw41jo1u5_t.jpg","file_code":"zckaw41jo1u5","length":"00:19:38","views":"3426","vw_fmt":"3.4K","uploaded":"2025-09-17 14:31:03","up_fmt":"17 Sep 2025","up_short":"17 Sep","title":"Tobrut Bella Missu Di Ewe Waktu Tidur Cantik Videos Bokepin Lagi Viral","t_esc":"Tobrut Bella Missu Di Ewe Waktu Tidur Cantik Videos Bokepin Lagi Viral"},{"download_url":"https://lulustream.com/d/oxkxa5p4bl6k","single_img":"https://img.lulucdn.com/oxkxa5p4bl6k_t.jpg","file_code":"oxkxa5p4bl6k","length":"00:01:20","views":"1372","vw_fmt":"1.4K","uploaded":"2025-09-17 14:30:57","up_fmt":"17 Sep 2025","up_short":"17 Sep","title":"Abg Smp Cuantik Bugil Membelah Dan Membuka Tempiknya Yang Wangi Staklam Dood","t_esc":"Abg Smp Cuantik Bugil Membelah Dan Membuka Tempiknya Yang Wangi Staklam Dood"},{"download_url":"https://lulustream.com/d/2tbmsb0vkxyq","single_img":"https://img.lulucdn.com/2tbmsb0vkxyq_t.jpg","file_code":"2tbmsb0vkxyq","length":"00:03:22","views":"14883","vw_fmt":"14.9K","uploaded":"2025-09-17 14:30:57","up_fmt":"17 Sep 2025","up_short":"17 Sep","title":"Smp Ngentot Perdana Doods Pro Ful Album Memeksiana Bokepsin","t_esc":"Smp Ngentot Perdana Doods Pro Ful Album Memeksiana Bokepsin"},{"download_url":"https://lulustream.com/d/4qe94rhwftka","single_img":"https://img.lulucdn.com/4qe94rhwftka_t.jpg","file_code":"4qe94rhwftka","length":"00:01:39","views":"508","vw_fmt":"508","uploaded":"2025-09-17 14:30:57","up_fmt":"17 Sep 2025","up_short":"17 Sep","title":"Ldplayeryoraa Pelajar Smp Tobrut Mp Cilbo Doostream Links Bebasindo Video Bokep","t_esc":"Ldplayeryoraa Pelajar Smp Tobrut Mp Cilbo Doostream Links Bebasindo Video Bokep"},{"download_url":"https://lulustream.com/d/zzkhv9kqznjw","single_img":"https://img.lulucdn.com/zzkhv9kqznjw_t.jpg","file_code":"zzkhv9kqznjw","length":"00:01:01","views":"8530","vw_fmt":"8.5K","uploaded":"2025-09-17 14:30:57","up_fmt":"17 Sep 2025","up_short":"17 Sep","title":"Kakak Bejat Adik Berhijab Masih Smp Disuruh Nyepongin Kontol Asupan Cantik Tobrut","t_esc":"Kakak Bejat Adik Berhijab Masih Smp Disuruh Nyepongin Kontol Asupan Cantik Tobrut"},{"download_url":"https://lulustream.com/d/bigwpjwvv2ys","single_img":"https://img.lulucdn.com/bigwpjwvv2ys_t.jpg","file_code":"bigwpjwvv2ys","length":"00:01:04","views":"1695","vw_fmt":"1.7K","uploaded":"2025-09-17 14:30:56","up_fmt":"17 Sep 2025","up_short":"17 Sep","title":"Vid Lagi Viral Bokepin Tele Links Xpanas","t_esc":"Vid Lagi Viral Bokepin Tele Links Xpanas"},{"download_url":"https://lulustream.com/d/dlkplf7lbz8q","single_img":"https://img.lulucdn.com/dlkplf7lbz8q_t.jpg","file_code":"dlkplf7lbz8q","length":"00:23:41","views":"432","vw_fmt":"432","uploaded":"2025-09-17 14:30:56","up_fmt":"17 Sep 2025","up_short":"17 Sep","title":"Vid Bokepin Links Poophd Link Web Memeksiana","t_esc":"Vid Bokepin Links Poophd Link Web Memeksiana"},{"download_url":"https://lulustream.com/d/83tv6e7vfz7s","single_img":"https://img.lulucdn.com/83tv6e7vfz7s_t.jpg","file_code":"83tv6e7vfz7s","length":"00:07:55","views":"4873","vw_fmt":"4.9K","uploaded":"2025-09-17 14:30:56","up_fmt":"17 Sep 2025","up_short":"17 Sep","title":"Adek Lagi Kumpul Lokal Viral Links Bokepin Live","t_esc":"Adek Lagi Kumpul Lokal Viral Links Bokepin Live"},{"download_url":"https://playmogo.com/d/w43ul8o2o73n","single_img":"https://thumbcdn.com/snaps/rbf9dmwaldwgekg8.jpg","file_code":"w43ul8o2o73n","length":"00:01:24","views":"448","vw_fmt":"448","uploaded":"2025-09-17 14:29:40","up_fmt":"17 Sep 2025","up_short":"17 Sep","title":"Ayank Kk Qjhhhh Indo Dood Tele Doodsflix Doodflix Ngentot","t_esc":"Ayank Kk Qjhhhh Indo Dood Tele Doodsflix Doodflix Ngentot"},{"download_url":"https://playmogo.com/d/1kvyjsop8bhx","single_img":"https://thumbcdn.com/snaps/9g01tqhpe1wb94xa.jpg","file_code":"1kvyjsop8bhx","length":"00:09:31","views":"590","vw_fmt":"590","uploaded":"2025-09-17 14:29:40","up_fmt":"17 Sep 2025","up_short":"17 Sep","title":"Di Paksa Pacar Doostream Videos Downloader Video Bokep Sotwe","t_esc":"Di Paksa Pacar Doostream Videos Downloader Video Bokep Sotwe"},{"download_url":"https://playmogo.com/d/bgt8wze7q28j","single_img":"https://thumbcdn.com/snaps/5iwk9wugz6ckn6jb.jpg","file_code":"bgt8wze7q28j","length":"00:01:12","views":"74","vw_fmt":"74","uploaded":"2025-09-17 14:29:40","up_fmt":"17 Sep 2025","up_short":"17 Sep","title":"Desah Nikmat Twitter Indonesia Video Viral Yakwad Memeksiana","t_esc":"Desah Nikmat Twitter Indonesia Video Viral Yakwad Memeksiana"},{"download_url":"https://playmogo.com/d/3dqqxe1o6np1","single_img":"https://thumbcdn.com/snaps/5yvtwatrlwoih4hj.jpg","file_code":"3dqqxe1o6np1","length":"00:01:32","views":"283","vw_fmt":"283","uploaded":"2025-09-17 14:29:40","up_fmt":"17 Sep 2025","up_short":"17 Sep","title":"Pacar Mulus Tele Jilbab Bebasindo Downloader Simintok","t_esc":"Pacar Mulus Tele Jilbab Bebasindo Downloader Simintok"},{"download_url":"https://playmogo.com/d/cpqos70j3wsf","single_img":"https://thumbcdn.com/snaps/y10vu0i61h4htkfg.jpg","file_code":"cpqos70j3wsf","length":"00:01:00","views":"198","vw_fmt":"198","uploaded":"2025-09-17 14:29:40","up_fmt":"17 Sep 2025","up_short":"17 Sep","title":"Ketagihan Bokep Video Bokepind Toketbagus Simontok Dood","t_esc":"Ketagihan Bokep Video Bokepind Toketbagus Simontok Dood"},{"download_url":"https://playmogo.com/d/82rup3kyygva","single_img":"https://thumbcdn.com/snaps/d19klquu1qdh3rxc.jpg","file_code":"82rup3kyygva","length":"00:49:23","views":"506","vw_fmt":"506","uploaded":"2025-09-17 14:29:40","up_fmt":"17 Sep 2025","up_short":"17 Sep","title":"Chindo Colmek Sampe Banjir Memeksiana Downloader Viral Doods Pro Website","t_esc":"Chindo Colmek Sampe Banjir Memeksiana Downloader Viral Doods Pro Website"},{"download_url":"https://playmogo.com/d/zjvgoxdky491","single_img":"https://thumbcdn.com/snaps/hpoj9k0skbur2g5i.jpg","file_code":"zjvgoxdky491","length":"00:02:48","views":"2766","vw_fmt":"2.8K","uploaded":"2025-09-14 14:15:27","up_fmt":"14 Sep 2025","up_short":"14 Sep","title":"Andini Permata Tele Full Album Staklam Website Videos","t_esc":"Andini Permata Tele Full Album Staklam Website Videos"},{"download_url":"https://playmogo.com/d/1j9cfevas2ol","single_img":"https://thumbcdn.com/snaps/nq56tvqydszjregz.jpg","file_code":"1j9cfevas2ol","length":"00:05:14","views":"2284","vw_fmt":"2.3K","uploaded":"2025-09-14 14:15:27","up_fmt":"14 Sep 2025","up_short":"14 Sep","title":"Andini Permata Indonesia Bokepsin Jilbab Bokep31 Videos","t_esc":"Andini Permata Indonesia Bokepsin Jilbab Bokep31 Videos"},{"download_url":"https://playmogo.com/d/0o1ljpzp78w6","single_img":"https://thumbcdn.com/snaps/prxispb173znwbkf.jpg","file_code":"0o1ljpzp78w6","length":"00:02:02","views":"1758","vw_fmt":"1.8K","uploaded":"2025-09-14 14:15:27","up_fmt":"14 Sep 2025","up_short":"14 Sep","title":"Andini Terabox Indo Full Album Toketbagus Live","t_esc":"Andini Terabox Indo Full Album Toketbagus Live"},{"download_url":"https://playmogo.com/d/6zgqyl0afmzt","single_img":"https://thumbcdn.com/snaps/opnhzmjwvur1ego3.jpg","file_code":"6zgqyl0afmzt","length":"00:01:38","views":"1125","vw_fmt":"1.1K","uploaded":"2025-09-14 14:15:27","up_fmt":"14 Sep 2025","up_short":"14 Sep","title":"Andini Permata Part Viral Video Sma Bokepin Colmek Poophd Website","t_esc":"Andini Permata Part Viral Video Sma Bokepin Colmek Poophd Website"},{"download_url":"https://playmogo.com/d/8hh1z9winq6i","single_img":"https://thumbcdn.com/snaps/ada8vap1relqfy6p.jpg","file_code":"8hh1z9winq6i","length":"00:07:02","views":"1341","vw_fmt":"1.3K","uploaded":"2025-09-14 14:15:27","up_fmt":"14 Sep 2025","up_short":"14 Sep","title":"Andini Hijab Viral Pamer Dada T Lanjng Bulat Depan Kamera Doostream Bokepind","t_esc":"Andini Hijab Viral Pamer Dada T Lanjng Bulat Depan Kamera Doostream Bokepind"},{"download_url":"https://playmogo.com/d/9py0ut3rppvi","single_img":"https://thumbcdn.com/snaps/2ncxhakjk75op4rr.jpg","file_code":"9py0ut3rppvi","length":"00:04:55","views":"2517","vw_fmt":"2.5K","uploaded":"2025-09-14 14:15:27","up_fmt":"14 Sep 2025","up_short":"14 Sep","title":"Viral Andini Permata P Full Album Twitter Folder Memeksiana Dood","t_esc":"Viral Andini Permata P Full Album Twitter Folder Memeksiana Dood"},{"download_url":"https://playmogo.com/d/ycyayk165r07","single_img":"https://thumbcdn.com/snaps/4onw9em34dm5zo1t.jpg","file_code":"ycyayk165r07","length":"00:05:00","views":"382","vw_fmt":"382","uploaded":"2025-09-14 14:15:00","up_fmt":"14 Sep 2025","up_short":"14 Sep","title":"Urfavgirlshit Lagi Viral Tele Twitter Website Link Web","t_esc":"Urfavgirlshit Lagi Viral Tele Twitter Website Link Web"},{"download_url":"https://playmogo.com/d/sh9bf2am952l","single_img":"https://thumbcdn.com/snaps/zmh8idsrk91zmq9c.jpg","file_code":"sh9bf2am952l","length":"00:08:41","views":"301","vw_fmt":"301","uploaded":"2025-09-14 14:15:00","up_fmt":"14 Sep 2025","up_short":"14 Sep","title":"Urfavgirlshit Simintok Tiktok Doodstreem Video Viral Bebasindo","t_esc":"Urfavgirlshit Simintok Tiktok Doodstreem Video Viral Bebasindo"},{"download_url":"https://playmogo.com/d/b8nmynhlmxsa","single_img":"https://thumbcdn.com/snaps/bejqzzx9gsrqzr0k.jpg","file_code":"b8nmynhlmxsa","length":"00:02:25","views":"172","vw_fmt":"172","uploaded":"2025-09-14 14:15:00","up_fmt":"14 Sep 2025","up_short":"14 Sep","title":"Urfavgirlshit Terabox Dood Telegram Doodsflix Lokal","t_esc":"Urfavgirlshit Terabox Dood Telegram Doodsflix Lokal"},{"download_url":"https://playmogo.com/d/se9a9h48pnu3","single_img":"https://thumbcdn.com/snaps/v38fyzgmc1tef3b4.jpg","file_code":"se9a9h48pnu3","length":"00:02:59","views":"372","vw_fmt":"372","uploaded":"2025-09-14 14:15:00","up_fmt":"14 Sep 2025","up_short":"14 Sep","title":"Urfavgirlshit Bokepind Website Videos Simintok Doodsflix","t_esc":"Urfavgirlshit Bokepind Website Videos Simintok Doodsflix"},{"download_url":"https://playmogo.com/d/hswv3mv6583f","single_img":"https://thumbcdn.com/snaps/exrnhfjkvcut1y88.jpg","file_code":"hswv3mv6583f","length":"00:01:51","views":"328","vw_fmt":"328","uploaded":"2025-09-14 14:15:00","up_fmt":"14 Sep 2025","up_short":"14 Sep","title":"Urfavgirlshit Asupan Viral Telegram Video Colmek Streaming Toketbagus","t_esc":"Urfavgirlshit Asupan Viral Telegram Video Colmek Streaming Toketbagus"},{"download_url":"https://playmogo.com/d/hlltnp6y90p8","single_img":"https://thumbcdn.com/snaps/xnzwmcu8xm4soud1.jpg","file_code":"hlltnp6y90p8","length":"00:09:13","views":"343","vw_fmt":"343","uploaded":"2025-09-14 14:14:45","up_fmt":"14 Sep 2025","up_short":"14 Sep","title":"Ms Breewc Ful Album Dood Tele Bebasindo Video Viral Streaming","t_esc":"Ms Breewc Ful Album Dood Tele Bebasindo Video Viral Streaming"},{"download_url":"https://playmogo.com/d/qnq2a1ber6q3","single_img":"https://thumbcdn.com/snaps/eqx7lndbdi6xhx52.jpg","file_code":"qnq2a1ber6q3","length":"00:05:42","views":"439","vw_fmt":"439","uploaded":"2025-09-14 14:14:45","up_fmt":"14 Sep 2025","up_short":"14 Sep","title":"Bokep Indo Msbreewc Cindo Cantik Ml Wot Bokepsin Bokepsatset Link Web Lagi","t_esc":"Bokep Indo Msbreewc Cindo Cantik Ml Wot Bokepsin Bokepsatset Link Web Lagi"},{"download_url":"https://playmogo.com/d/9tvftzvpa7lh","single_img":"https://thumbcdn.com/snaps/v60p4tno3xcczyjw.jpg","file_code":"9tvftzvpa7lh","length":"00:18:01","views":"564","vw_fmt":"564","uploaded":"2025-09-14 14:14:45","up_fmt":"14 Sep 2025","up_short":"14 Sep","title":"Msbreewc Update Eksklusif Bokepin Pemersatu Full Album Bokep","t_esc":"Msbreewc Update Eksklusif Bokepin Pemersatu Full Album Bokep"},{"download_url":"https://playmogo.com/d/t9eb37x4df5o","single_img":"https://thumbcdn.com/snaps/4mqv5eizd2t2xmqj.jpg","file_code":"t9eb37x4df5o","length":"00:05:45","views":"137","vw_fmt":"137","uploaded":"2025-09-14 14:14:45","up_fmt":"14 Sep 2025","up_short":"14 Sep","title":"Msbreewc Update Doodstream Simontok Bokep31 Tele","t_esc":"Msbreewc Update Doodstream Simontok Bokep31 Tele"},{"download_url":"https://playmogo.com/d/dzmxkirlp5qg","single_img":"https://thumbcdn.com/snaps/fw39upjpsw1h4fp8.jpg","file_code":"dzmxkirlp5qg","length":"00:19:31","views":"234","vw_fmt":"234","uploaded":"2025-09-14 14:14:45","up_fmt":"14 Sep 2025","up_short":"14 Sep","title":"Bokep Indo Ms Breewc Cosplay Chindo Full Memek Becek Dood Stream Videos","t_esc":"Bokep Indo Ms Breewc Cosplay Chindo Full Memek Becek Dood Stream Videos"},{"download_url":"https://playmogo.com/d/cne0j0egihvs","single_img":"https://thumbcdn.com/snaps/pe9hjuoco3hy9mao.jpg","file_code":"cne0j0egihvs","length":"00:19:41","views":"233","vw_fmt":"233","uploaded":"2025-09-14 14:14:45","up_fmt":"14 Sep 2025","up_short":"14 Sep","title":"Fake Agent Msbreewwc Amateur Porn Feat Msbreewc Doods Pro Yakwad Viral Telegram","t_esc":"Fake Agent Msbreewwc Amateur Porn Feat Msbreewc Doods Pro Yakwad Viral Telegram"},{"download_url":"https://playmogo.com/d/6u6c0urvsgty","single_img":"https://thumbcdn.com/snaps/ihorqwen4in1kuji.jpg","file_code":"6u6c0urvsgty","length":"00:10:07","views":"357","vw_fmt":"357","uploaded":"2025-09-14 14:14:45","up_fmt":"14 Sep 2025","up_short":"14 Sep","title":"Msbreewc Vcs Free Ke Fllowers Part Update Terupdate Video Indo Folder Asupan","t_esc":"Msbreewc Vcs Free Ke Fllowers Part Update Terupdate Video Indo Folder Asupan"},{"download_url":"https://playmogo.com/d/3h8z2hiucm8d","single_img":"https://thumbcdn.com/snaps/b7hczbajp16sfw9p.jpg","file_code":"3h8z2hiucm8d","length":"00:09:43","views":"225","vw_fmt":"225","uploaded":"2025-09-14 14:13:59","up_fmt":"14 Sep 2025","up_short":"14 Sep","title":"Onlyfans Princesisi Eksklusif Terbaru Cilbo Folder Website Pejuang Lendir Bokep Dood","t_esc":"Onlyfans Princesisi Eksklusif Terbaru Cilbo Folder Website Pejuang Lendir Bokep Dood"},{"download_url":"https://playmogo.com/d/6di4l8o7tryf","single_img":"https://thumbcdn.com/snaps/xjq3qfg7zyy6mm8w.jpg","file_code":"6di4l8o7tryf","length":"00:11:42","views":"101","vw_fmt":"101","uploaded":"2025-09-14 14:13:59","up_fmt":"14 Sep 2025","up_short":"14 Sep","title":"B Ae Dcf Ec C Full Album Doodstream Lulustream Ful Bochiel","t_esc":"B Ae Dcf Ec C Full Album Doodstream Lulustream Ful Bochiel"},{"download_url":"https://playmogo.com/d/pnduhg1m9l2u","single_img":"https://thumbcdn.com/snaps/ene204hljikkznf8.jpg","file_code":"pnduhg1m9l2u","length":"00:09:56","views":"368","vw_fmt":"368","uploaded":"2025-09-14 14:13:59","up_fmt":"14 Sep 2025","up_short":"14 Sep","title":"Doggy Pantat Mulus Ukhti Shalula Lagi Viral Dood Cantik Tobrut Terupdate Simintok","t_esc":"Doggy Pantat Mulus Ukhti Shalula Lagi Viral Dood Cantik Tobrut Terupdate Simintok"},{"download_url":"https://playmogo.com/d/thuw2sz87zc6","single_img":"https://thumbcdn.com/snaps/pr51phta2da7ahl0.jpg","file_code":"thuw2sz87zc6","length":"00:04:02","views":"250","vw_fmt":"250","uploaded":"2025-09-14 14:13:59","up_fmt":"14 Sep 2025","up_short":"14 Sep","title":"Ngewe Cewek Tepi Jalan Tetek Besar Dan Cantik Dood Stream","t_esc":"Ngewe Cewek Tepi Jalan Tetek Besar Dan Cantik Dood Stream"},{"download_url":"https://playmogo.com/d/3n7vrze74s58","single_img":"https://thumbcdn.com/snaps/2w0zyy71njmnj4ue.jpg","file_code":"3n7vrze74s58","length":"00:03:50","views":"336","vw_fmt":"336","uploaded":"2025-09-14 14:13:59","up_fmt":"14 Sep 2025","up_short":"14 Sep","title":"Doggy Abg Hijabers Montok Pantad Gede Mulus Banget Poop Hd Lokal Bokep","t_esc":"Doggy Abg Hijabers Montok Pantad Gede Mulus Banget Poop Hd Lokal Bokep"},{"download_url":"https://playmogo.com/d/5cx5nmvasuee","single_img":"https://thumbcdn.com/snaps/tdi9u62bdzdoxgvp.jpg","file_code":"5cx5nmvasuee","length":"00:07:29","views":"457","vw_fmt":"457","uploaded":"2025-08-17 14:27:17","up_fmt":"17 Agu 2025","up_short":"17 Agu","title":"Delightful Hug Boy Girl Cowgirl Creampie Pqlzv Sbp Celeb Jared Net Telegram","t_esc":"Delightful Hug Boy Girl Cowgirl Creampie Pqlzv Sbp Celeb Jared Net Telegram"},{"download_url":"https://playmogo.com/d/nb3x760w6bwo","single_img":"https://thumbcdn.com/snaps/fc97zbifbyw46y3d.jpg","file_code":"nb3x760w6bwo","length":"00:11:24","views":"266","vw_fmt":"266","uploaded":"2025-08-17 14:27:17","up_fmt":"17 Agu 2025","up_short":"17 Agu","title":"Delightful Hug Boy Girl Maid Ride K Otfjq Jg Celeb Jared Net","t_esc":"Delightful Hug Boy Girl Maid Ride K Otfjq Jg Celeb Jared Net"},{"download_url":"https://playmogo.com/d/4dfyxndi9pta","single_img":"https://thumbcdn.com/snaps/rzmil6nxj1uuer9d.jpg","file_code":"4dfyxndi9pta","length":"00:09:26","views":"399","vw_fmt":"399","uploaded":"2025-08-17 14:27:17","up_fmt":"17 Agu 2025","up_short":"17 Agu","title":"Delightfulhug Hj Dood Tele Indo Doods Pro Simontok Video Sma","t_esc":"Delightfulhug Hj Dood Tele Indo Doods Pro Simontok Video Sma"},{"download_url":"https://playmogo.com/d/i4hul966hhi3","single_img":"https://thumbcdn.com/snaps/g3e9f1psespljdlg.jpg","file_code":"i4hul966hhi3","length":"00:07:07","views":"140","vw_fmt":"140","uploaded":"2025-08-17 14:27:17","up_fmt":"17 Agu 2025","up_short":"17 Agu","title":"Delightfulhug Cantik Tobrut Asupan Doods Pro Update Video Colmek","t_esc":"Delightfulhug Cantik Tobrut Asupan Doods Pro Update Video Colmek"},{"download_url":"https://playmogo.com/d/4vf5crwj7hsg","single_img":"https://thumbcdn.com/snaps/kg4bkot9d1qgiap8.jpg","file_code":"4vf5crwj7hsg","length":"00:11:24","views":"27","vw_fmt":"27","uploaded":"2025-08-17 14:27:17","up_fmt":"17 Agu 2025","up_short":"17 Agu","title":"Delightful Hug Boy Girl Maid Ride K Otfjq Jg Celeb Jared Net","t_esc":"Delightful Hug Boy Girl Maid Ride K Otfjq Jg Celeb Jared Net"},{"download_url":"https://playmogo.com/d/wk94g3uohgya","single_img":"https://thumbcdn.com/snaps/yfzmpf44y3cdgiru.jpg","file_code":"wk94g3uohgya","length":"00:09:26","views":"91","vw_fmt":"91","uploaded":"2025-08-17 14:27:17","up_fmt":"17 Agu 2025","up_short":"17 Agu","title":"Delightfulhug Hj Dodstream Memeksiana Live Simontok Pemersatu","t_esc":"Delightfulhug Hj Dodstream Memeksiana Live Simontok Pemersatu"},{"download_url":"https://playmogo.com/d/7by0hv49mmne","single_img":"https://thumbcdn.com/snaps/v11311dx6y0lallt.jpg","file_code":"7by0hv49mmne","length":"00:09:26","views":"76","vw_fmt":"76","uploaded":"2025-08-17 14:27:17","up_fmt":"17 Agu 2025","up_short":"17 Agu","title":"Delightfulhug Hj Asupan Video Viral Doostream Doodflix Bokepind","t_esc":"Delightfulhug Hj Asupan Video Viral Doostream Doodflix Bokepind"},{"download_url":"https://lulustream.com/d/ltidfo5wfo8y","single_img":"https://img.lulucdn.com/ltidfo5wfo8y_t.jpg","file_code":"ltidfo5wfo8y","length":"00:02:18","views":"11162","vw_fmt":"11.2K","uploaded":"2025-08-16 19:56:50","up_fmt":"16 Agu 2025","up_short":"16 Agu","title":"Bokep Indo Viral Pecah Perawan Nangis Full Album Video Twitter Ful","t_esc":"Bokep Indo Viral Pecah Perawan Nangis Full Album Video Twitter Ful"},{"download_url":"https://lulustream.com/d/rb51opuuw6k0","single_img":"https://img.lulucdn.com/rb51opuuw6k0_t.jpg","file_code":"rb51opuuw6k0","length":"00:02:43","views":"25486","vw_fmt":"25.5K","uploaded":"2025-08-16 19:56:50","up_fmt":"16 Agu 2025","up_short":"16 Agu","title":"Sepang Bljr Ngntot Mp Bokep Twitter Doodstream Dood Memeksiana","t_esc":"Sepang Bljr Ngntot Mp Bokep Twitter Doodstream Dood Memeksiana"},{"download_url":"https://lulustream.com/d/p1g3g5f4a1wc","single_img":"https://img.lulucdn.com/p1g3g5f4a1wc_t.jpg","file_code":"p1g3g5f4a1wc","length":"00:14:01","views":"20614","vw_fmt":"20.6K","uploaded":"2025-08-16 19:56:50","up_fmt":"16 Agu 2025","up_short":"16 Agu","title":"Tante Vs Cilbo Part Simintok Dood Tele Video Bokep Doods Pro Asupan","t_esc":"Tante Vs Cilbo Part Simintok Dood Tele Video Bokep Doods Pro Asupan"},{"download_url":"https://lulustream.com/d/wm7g6cnjscpo","single_img":"https://img.lulucdn.com/wm7g6cnjscpo_t.jpg","file_code":"wm7g6cnjscpo","length":"00:02:43","views":"2759","vw_fmt":"2.8K","uploaded":"2025-08-16 19:55:56","up_fmt":"16 Agu 2025","up_short":"16 Agu","title":"Sepang Bljr Ngntot Mp Lokal Bokep31 Tiktok Yakwad Bochiel","t_esc":"Sepang Bljr Ngntot Mp Lokal Bokep31 Tiktok Yakwad Bochiel"},{"download_url":"https://lulustream.com/d/3dwn47pyjqer","single_img":"https://img.lulucdn.com/3dwn47pyjqer_t.jpg","file_code":"3dwn47pyjqer","length":"00:06:22","views":"684","vw_fmt":"684","uploaded":"2025-08-16 19:55:56","up_fmt":"16 Agu 2025","up_short":"16 Agu","title":"Ssstwitter Com Video Colmek Toketbagus Doodstreem Tiktok Simintok","t_esc":"Ssstwitter Com Video Colmek Toketbagus Doodstreem Tiktok Simintok"},{"download_url":"https://lulustream.com/d/gw92i369f0fs","single_img":"https://img.lulucdn.com/gw92i369f0fs_t.jpg","file_code":"gw92i369f0fs","length":"00:05:08","views":"858","vw_fmt":"858","uploaded":"2025-08-16 19:55:56","up_fmt":"16 Agu 2025","up_short":"16 Agu","title":"Ssstwitter Com Video Indo Xpanas Doostream Poophd Bokepsin","t_esc":"Ssstwitter Com Video Indo Xpanas Doostream Poophd Bokepsin"},{"download_url":"https://lulustream.com/d/ofdxs3ae07cf","single_img":"https://img.lulucdn.com/ofdxs3ae07cf_t.jpg","file_code":"ofdxs3ae07cf","length":"00:01:24","views":"333","vw_fmt":"333","uploaded":"2025-08-16 19:55:56","up_fmt":"16 Agu 2025","up_short":"16 Agu","title":"Ssstwitter Com Tiktok Videos Indo Bokepsatset Bokep","t_esc":"Ssstwitter Com Tiktok Videos Indo Bokepsatset Bokep"},{"download_url":"https://lulustream.com/d/b7myx7skx7zo","single_img":"https://img.lulucdn.com/b7myx7skx7zo_t.jpg","file_code":"b7myx7skx7zo","length":"00:02:15","views":"1054","vw_fmt":"1.1K","uploaded":"2025-08-16 19:55:56","up_fmt":"16 Agu 2025","up_short":"16 Agu","title":"Ssstwitter Com Bokep Video Cantik Tobrut Bokepin Bokep31 Terabox","t_esc":"Ssstwitter Com Bokep Video Cantik Tobrut Bokepin Bokep31 Terabox"},{"download_url":"https://lulustream.com/d/r0mcsmhnlleh","single_img":"https://img.lulucdn.com/r0mcsmhnlleh_t.jpg","file_code":"r0mcsmhnlleh","length":"00:02:07","views":"7388","vw_fmt":"7.4K","uploaded":"2025-08-16 19:55:55","up_fmt":"16 Agu 2025","up_short":"16 Agu","title":"Polos Lagi Birahi Cilbo Pekoblive Pejuang Lendir Live Lokal","t_esc":"Polos Lagi Birahi Cilbo Pekoblive Pejuang Lendir Live Lokal"},{"download_url":"https://lulustream.com/d/pcbe4o6yq5og","single_img":"https://img.lulucdn.com/pcbe4o6yq5og_t.jpg","file_code":"pcbe4o6yq5og","length":"00:01:54","views":"3705","vw_fmt":"3.7K","uploaded":"2025-08-16 19:55:55","up_fmt":"16 Agu 2025","up_short":"16 Agu","title":"L Smp Indo Doodflix Terabox Bokepin Yakwad","t_esc":"L Smp Indo Doodflix Terabox Bokepin Yakwad"},{"download_url":"https://lulustream.com/d/k3wagsxa3jf8","single_img":"https://img.lulucdn.com/k3wagsxa3jf8_t.jpg","file_code":"k3wagsxa3jf8","length":"00:01:59","views":"2534","vw_fmt":"2.5K","uploaded":"2025-08-16 19:55:55","up_fmt":"16 Agu 2025","up_short":"16 Agu","title":"Eporner Com Ix Q Oy Hrz Unboxing Memek Dan Toket Berhijab Full","t_esc":"Eporner Com Ix Q Oy Hrz Unboxing Memek Dan Toket Berhijab Full"},{"download_url":"https://playmogo.com/d/1h8zsf5f9n9x","single_img":"https://thumbcdn.com/snaps/wbhmlve72kufl25x.jpg","file_code":"1h8zsf5f9n9x","length":"00:07:23","views":"399","vw_fmt":"399","uploaded":"2025-08-15 10:01:38","up_fmt":"15 Agu 2025","up_short":"15 Agu","title":"Cela Dini Update Terbaru Video Viral Full Album Toketbagus Cantik Tobrut","t_esc":"Cela Dini Update Terbaru Video Viral Full Album Toketbagus Cantik Tobrut"},{"download_url":"https://playmogo.com/d/bvdy9qvsnlwo","single_img":"https://thumbcdn.com/snaps/onyd6ox0umftdyk6.jpg","file_code":"bvdy9qvsnlwo","length":"00:01:09","views":"379","vw_fmt":"379","uploaded":"2025-08-15 10:01:38","up_fmt":"15 Agu 2025","up_short":"15 Agu","title":"U Enak Banget Pliss Telegram Cilbo Staklam Viral Tele","t_esc":"U Enak Banget Pliss Telegram Cilbo Staklam Viral Tele"},{"download_url":"https://playmogo.com/d/brc237ebu6gc","single_img":"https://thumbcdn.com/snaps/3dfnyi0nq15br247.jpg","file_code":"brc237ebu6gc","length":"00:01:51","views":"169","vw_fmt":"169","uploaded":"2025-08-15 10:01:38","up_fmt":"15 Agu 2025","up_short":"15 Agu","title":"Tocil Cantik Terupdate Cilbo Doostream Doodstreem Asupan Viral","t_esc":"Tocil Cantik Terupdate Cilbo Doostream Doodstreem Asupan Viral"},{"download_url":"https://playmogo.com/d/omk7pszxdzas","single_img":"https://thumbcdn.com/snaps/smeeks9rcn3m4cav.jpg","file_code":"omk7pszxdzas","length":"00:01:12","views":"611","vw_fmt":"611","uploaded":"2025-08-15 10:01:38","up_fmt":"15 Agu 2025","up_short":"15 Agu","title":"Adik Ipar Mantap Tisu Magic Viral Simintok Twitter Folder Video Colmek","t_esc":"Adik Ipar Mantap Tisu Magic Viral Simintok Twitter Folder Video Colmek"},{"download_url":"https://playmogo.com/d/ll2jdic6cum6","single_img":"https://thumbcdn.com/snaps/3bkykbgkpxn14avy.jpg","file_code":"ll2jdic6cum6","length":"00:02:32","views":"302","vw_fmt":"302","uploaded":"2025-08-15 10:01:38","up_fmt":"15 Agu 2025","up_short":"15 Agu","title":"Abg Tobrut Mulus Video Bokep Videos Bokepsin Indo Staklam","t_esc":"Abg Tobrut Mulus Video Bokep Videos Bokepsin Indo Staklam"},{"download_url":"https://playmogo.com/d/zx3v3d4xwktg","single_img":"https://thumbcdn.com/snaps/wcyvdir7ju7vdc3k.jpg","file_code":"zx3v3d4xwktg","length":"00:02:37","views":"562","vw_fmt":"562","uploaded":"2025-08-15 10:01:38","up_fmt":"15 Agu 2025","up_short":"15 Agu","title":"Toge Ngentot Indonesia Bokepsatset Pemersatu Tiktok Bokepsin","t_esc":"Toge Ngentot Indonesia Bokepsatset Pemersatu Tiktok Bokepsin"},{"download_url":"https://playmogo.com/d/f3bm6j87wkx2","single_img":"https://thumbcdn.com/snaps/ce1o8jz9l17mt33t.jpg","file_code":"f3bm6j87wkx2","length":"00:07:23","views":"166","vw_fmt":"166","uploaded":"2025-08-15 10:01:38","up_fmt":"15 Agu 2025","up_short":"15 Agu","title":"Cela Dini Update Terbaru Popstream Doostream Indo Full Album Bokepind","t_esc":"Cela Dini Update Terbaru Popstream Doostream Indo Full Album Bokepind"},{"download_url":"https://playmogo.com/d/eaq5uebdlreu","single_img":"https://thumbcdn.com/snaps/q0w8jptfsw6ezsmf.jpg","file_code":"eaq5uebdlreu","length":"00:10:54","views":"682","vw_fmt":"682","uploaded":"2025-08-15 10:01:38","up_fmt":"15 Agu 2025","up_short":"15 Agu","title":"Vid Dood Doodflix Lokal Twitter Cantik Tobrut","t_esc":"Vid Dood Doodflix Lokal Twitter Cantik Tobrut"},{"download_url":"https://playmogo.com/d/284r1ra0yuqb","single_img":"https://thumbcdn.com/snaps/crpv0s6v4522e0ep.jpg","file_code":"284r1ra0yuqb","length":"00:01:06","views":"205","vw_fmt":"205","uploaded":"2025-08-15 10:01:38","up_fmt":"15 Agu 2025","up_short":"15 Agu","title":"Kebaya Putih Poop Hd Doodsflix Update Lulustream Bokepin Bokepind","t_esc":"Kebaya Putih Poop Hd Doodsflix Update Lulustream Bokepin Bokepind"},{"download_url":"https://playmogo.com/d/vv4p7jgd10ff","single_img":"https://thumbcdn.com/snaps/f16ibnu114n7wg97.jpg","file_code":"vv4p7jgd10ff","length":"00:06:35","views":"572","vw_fmt":"572","uploaded":"2025-08-15 10:01:38","up_fmt":"15 Agu 2025","up_short":"15 Agu","title":"Homemade Cute Wife In Batik Wants Sex Full Uncen Fansly Bbw Thaixxx","t_esc":"Homemade Cute Wife In Batik Wants Sex Full Uncen Fansly Bbw Thaixxx"},{"download_url":"https://playmogo.com/d/eqhjrrqlqtak","single_img":"https://thumbcdn.com/snaps/c0dqf0ok1o79i151.jpg","file_code":"eqhjrrqlqtak","length":"00:10:41","views":"439","vw_fmt":"439","uploaded":"2025-08-15 10:01:38","up_fmt":"15 Agu 2025","up_short":"15 Agu","title":"Pake Batik Lebih Nikmat Popstream Asupan Viral Memeksiana Update Lokal","t_esc":"Pake Batik Lebih Nikmat Popstream Asupan Viral Memeksiana Update Lokal"},{"download_url":"https://playmogo.com/d/w8kke9sdt9b7","single_img":"https://thumbcdn.com/snaps/fm9mfum73d7bktw6.jpg","file_code":"w8kke9sdt9b7","length":"00:18:04","views":"6985","vw_fmt":"7.0K","uploaded":"2025-08-15 08:21:21","up_fmt":"15 Agu 2025","up_short":"15 Agu","title":"Pijat Plus Ngentot Tante Toge Bokepsin Asupan Viral Xpanas Simontok","t_esc":"Pijat Plus Ngentot Tante Toge Bokepsin Asupan Viral Xpanas Simontok"},{"download_url":"https://playmogo.com/d/6juqx54c87hb","single_img":"https://thumbcdn.com/snaps/2tdtwo7j8wdx5cih.jpg","file_code":"6juqx54c87hb","length":"00:01:06","views":"449","vw_fmt":"449","uploaded":"2025-08-15 08:21:21","up_fmt":"15 Agu 2025","up_short":"15 Agu","title":"Istri Ku Yang Bersih Dan Mulus Video Viral Dodstream Staklam Bokep Jilbab","t_esc":"Istri Ku Yang Bersih Dan Mulus Video Viral Dodstream Staklam Bokep Jilbab"},{"download_url":"https://playmogo.com/d/5kjjj5ypbsfs","single_img":"https://thumbcdn.com/snaps/zl6pfal7tkvix99k.jpg","file_code":"5kjjj5ypbsfs","length":"00:01:56","views":"362","vw_fmt":"362","uploaded":"2025-08-15 08:21:21","up_fmt":"15 Agu 2025","up_short":"15 Agu","title":"Viral Jilbab Coklat Kacamata Link Web Doodsflix Video Sma Lagi Lulustream","t_esc":"Viral Jilbab Coklat Kacamata Link Web Doodsflix Video Sma Lagi Lulustream"},{"download_url":"https://playmogo.com/d/x8i0tk8y9em9","single_img":"https://thumbcdn.com/snaps/9ojtzeh7ygnmprdp.jpg","file_code":"x8i0tk8y9em9","length":"00:10:30","views":"410","vw_fmt":"410","uploaded":"2025-08-15 08:21:21","up_fmt":"15 Agu 2025","up_short":"15 Agu","title":"Ngewe Janda Montok Bokepsin Full Album Twitter Cilbo Doodstreem","t_esc":"Ngewe Janda Montok Bokepsin Full Album Twitter Cilbo Doodstreem"},{"download_url":"https://playmogo.com/d/kznqf02pc6jx","single_img":"https://thumbcdn.com/snaps/et3dj33dec2g9hxc.jpg","file_code":"kznqf02pc6jx","length":"00:04:29","views":"502","vw_fmt":"502","uploaded":"2025-08-15 08:21:21","up_fmt":"15 Agu 2025","up_short":"15 Agu","title":"Doyan Wot Narsis Kak Anggita Downloader Dood Doostream Video Sma Cilbo","t_esc":"Doyan Wot Narsis Kak Anggita Downloader Dood Doostream Video Sma Cilbo"},{"download_url":"https://playmogo.com/d/zzvu8vjgi6zr","single_img":"https://thumbcdn.com/snaps/uepfkgj9wi7jgzql.jpg","file_code":"zzvu8vjgi6zr","length":"00:24:28","views":"353","vw_fmt":"353","uploaded":"2025-08-15 08:21:21","up_fmt":"15 Agu 2025","up_short":"15 Agu","title":"Staycation Bareng Temen Ngentot Video Sma Cilbo Bokepin Tiktok Dood","t_esc":"Staycation Bareng Temen Ngentot Video Sma Cilbo Bokepin Tiktok Dood"}],"results_total":"26424","results":200}}