{"msg":"OK","server_time":"2026-05-06 05:52:38","status":200,"result":{"total_pages":134,"files":[{"download_url":"https://playmogo.com/d/jf220vj5108r","single_img":"https://ticdn.net/snaps/8cnq1gan9bupfsam.jpg","file_code":"jf220vj5108r","length":"00:01:07","views":"2360","vw_fmt":"2.4K","uploaded":"2023-10-10 04:02:07","up_fmt":"10 Okt 2023","up_short":"10 Okt","title":"Sepongan Nikmat Dari Pacar Hijab Cantik Bokep Indo Viral Jilbab Website Video","t_esc":"Sepongan Nikmat Dari Pacar Hijab Cantik Bokep Indo Viral Jilbab Website Video"},{"download_url":"https://playmogo.com/d/t8yvj2j74tau","single_img":"https://ticdn.net/snaps/0kg9mjh32tcgvmyb.jpg","file_code":"t8yvj2j74tau","length":"00:08:32","views":"2433","vw_fmt":"2.4K","uploaded":"2023-10-10 03:59:50","up_fmt":"10 Okt 2023","up_short":"10 Okt","title":"Main Dikost Ukthy Minta Dipuasin Doodsflix Video Viral Bokepsatset Lokal Streaming","t_esc":"Main Dikost Ukthy Minta Dipuasin Doodsflix Video Viral Bokepsatset Lokal Streaming"},{"download_url":"https://playmogo.com/d/as31fjb2l2gy","single_img":"https://ticdn.net/snaps/h21h3l9fyzt368p1.jpg","file_code":"as31fjb2l2gy","length":"00:03:21","views":"7618","vw_fmt":"7.6K","uploaded":"2023-10-10 03:59:50","up_fmt":"10 Okt 2023","up_short":"10 Okt","title":"Dikost Dikasih Jatah Mantan Tog Sebelum Nikahannya Dood Stream Live Folder Bokepsatset","t_esc":"Dikost Dikasih Jatah Mantan Tog Sebelum Nikahannya Dood Stream Live Folder Bokepsatset"},{"download_url":"https://playmogo.com/d/t8nbv4bz777v","single_img":"https://ticdn.net/snaps/hnxt0tyfpqayitr7.jpg","file_code":"t8nbv4bz777v","length":"00:07:30","views":"3377","vw_fmt":"3.4K","uploaded":"2023-10-10 03:59:50","up_fmt":"10 Okt 2023","up_short":"10 Okt","title":"Abg Bokep Sma Tobrut Jago Goyang Diatas Video Indo Tiktok Streaming","t_esc":"Abg Bokep Sma Tobrut Jago Goyang Diatas Video Indo Tiktok Streaming"},{"download_url":"https://playmogo.com/d/x1ubu9vqst16","single_img":"https://ticdn.net/snaps/coe11l67cct5aqbr.jpg","file_code":"x1ubu9vqst16","length":"00:01:00","views":"2590","vw_fmt":"2.6K","uploaded":"2023-10-10 02:22:38","up_fmt":"10 Okt 2023","up_short":"10 Okt","title":"Cewek Sange Colmek Susu Montok Gedepokoknya Viral Video Sma Full Album Bokepsin","t_esc":"Cewek Sange Colmek Susu Montok Gedepokoknya Viral Video Sma Full Album Bokepsin"},{"download_url":"https://playmogo.com/d/7e2fnkjubuu4","single_img":"https://ticdn.net/snaps/daes975zy0yjrb0u.jpg","file_code":"7e2fnkjubuu4","length":"00:03:02","views":"3535","vw_fmt":"3.5K","uploaded":"2023-10-10 02:22:38","up_fmt":"10 Okt 2023","up_short":"10 Okt","title":"Skandal Tobrut Baju Biru Gedepokoknya Bokep Video Doodstreem Bokep31 Downloader Pejuang Lendir","t_esc":"Skandal Tobrut Baju Biru Gedepokoknya Bokep Video Doodstreem Bokep31 Downloader Pejuang Lendir"},{"download_url":"https://playmogo.com/d/dc1xthprrzea","single_img":"https://ticdn.net/snaps/awvqv29h28j2iayc.jpg","file_code":"dc1xthprrzea","length":"00:03:00","views":"6349","vw_fmt":"6.3K","uploaded":"2023-10-10 02:22:38","up_fmt":"10 Okt 2023","up_short":"10 Okt","title":"Bacol Pascol Merapat Gedepokoknya Jilbab Bebasindo Cantik Tobrut Doodflix Pemersatu","t_esc":"Bacol Pascol Merapat Gedepokoknya Jilbab Bebasindo Cantik Tobrut Doodflix Pemersatu"},{"download_url":"https://playmogo.com/d/bsmz32gs4v6h","single_img":"https://ticdn.net/snaps/6fozaw9sb440bipy.jpg","file_code":"bsmz32gs4v6h","length":"00:03:01","views":"2485","vw_fmt":"2.5K","uploaded":"2023-10-10 02:22:38","up_fmt":"10 Okt 2023","up_short":"10 Okt","title":"Cewek Sangeanm Gedepokoknya Doodflix Video Viral Simintok Folder Live","t_esc":"Cewek Sangeanm Gedepokoknya Doodflix Video Viral Simintok Folder Live"},{"download_url":"https://playmogo.com/d/kemsw4ios4gq","single_img":"https://ticdn.net/snaps/1i5jl8yq9mjcsavv.jpg","file_code":"kemsw4ios4gq","length":"00:05:25","views":"2797","vw_fmt":"2.8K","uploaded":"2023-10-10 00:59:05","up_fmt":"10 Okt 2023","up_short":"10 Okt","title":"Istri Lagi Hamil Duburnya Dimasukin Kontol Yakwad Doodstreem Links Bokepsatset Streaming","t_esc":"Istri Lagi Hamil Duburnya Dimasukin Kontol Yakwad Doodstreem Links Bokepsatset Streaming"},{"download_url":"https://playmogo.com/d/s6eiprarsnrb","single_img":"https://ticdn.net/snaps/2lh499qy02ebiz6h.jpg","file_code":"s6eiprarsnrb","length":"00:02:13","views":"8788","vw_fmt":"8.8K","uploaded":"2023-10-10 00:58:53","up_fmt":"10 Okt 2023","up_short":"10 Okt","title":"Ngew Sama Str Yg Sdng Hamil Dood Stream Bochiel Terabox Doods Pro","t_esc":"Ngew Sama Str Yg Sdng Hamil Dood Stream Bochiel Terabox Doods Pro"},{"download_url":"https://playmogo.com/d/z1o4io2y0n5z","single_img":"https://ticdn.net/snaps/4kjdtgrk6frcr8t5.jpg","file_code":"z1o4io2y0n5z","length":"00:01:27","views":"3484","vw_fmt":"3.5K","uploaded":"2023-10-10 00:58:43","up_fmt":"10 Okt 2023","up_short":"10 Okt","title":"Kangen Desahan Onlyfans Hukihoe Ngewe Ketika Hamil Muda Doodstreamapaaja Telegram Popstream Live","t_esc":"Kangen Desahan Onlyfans Hukihoe Ngewe Ketika Hamil Muda Doodstreamapaaja Telegram Popstream Live"},{"download_url":"https://playmogo.com/d/sit3b4vvz9d7","single_img":"https://ticdn.net/snaps/u2ycxxxag18g6d9y.jpg","file_code":"sit3b4vvz9d7","length":"00:00:41","views":"11237","vw_fmt":"11.2K","uploaded":"2023-10-10 00:58:39","up_fmt":"10 Okt 2023","up_short":"10 Okt","title":"Main Bareng Kk Ipar Yg Lagi Hamil Muda Di Tinggal Keluar Kota","t_esc":"Main Bareng Kk Ipar Yg Lagi Hamil Muda Di Tinggal Keluar Kota"},{"download_url":"https://playmogo.com/d/8ff73elivcdp","single_img":"https://ticdn.net/snaps/4pil1yy8u49s0zhq.jpg","file_code":"8ff73elivcdp","length":"00:16:57","views":"2995","vw_fmt":"3.0K","uploaded":"2023-10-10 00:58:37","up_fmt":"10 Okt 2023","up_short":"10 Okt","title":"Hijab Big Tits Violet Di Paksa Hamil Oleh Ibu Mertua Colipedia Com","t_esc":"Hijab Big Tits Violet Di Paksa Hamil Oleh Ibu Mertua Colipedia Com"},{"download_url":"https://playmogo.com/d/svzl0844e5pm","single_img":"https://ticdn.net/snaps/yrc03tlyu5dpb7r4.jpg","file_code":"svzl0844e5pm","length":"00:09:08","views":"7364","vw_fmt":"7.4K","uploaded":"2023-10-10 00:58:26","up_fmt":"10 Okt 2023","up_short":"10 Okt","title":"Ngentot Binor Tetangga Hamil Bulan Dood Stream Telegram Video Colmek Indonesia Viral","t_esc":"Ngentot Binor Tetangga Hamil Bulan Dood Stream Telegram Video Colmek Indonesia Viral"},{"download_url":"https://playmogo.com/d/5zy6ijac343g","single_img":"https://ticdn.net/snaps/mi3gzxd8uazync8j.jpg","file_code":"5zy6ijac343g","length":"00:09:55","views":"4985","vw_fmt":"5.0K","uploaded":"2023-10-10 00:58:22","up_fmt":"10 Okt 2023","up_short":"10 Okt","title":"Istri Lagi Hamil Duburnya Dimasukin Kontol Dood Stream Viral Terupdate Ngentot Lulustream","t_esc":"Istri Lagi Hamil Duburnya Dimasukin Kontol Dood Stream Viral Terupdate Ngentot Lulustream"},{"download_url":"https://playmogo.com/d/1pr3owpabfgo","single_img":"https://ticdn.net/snaps/ge64dwvgtkh5bju8.jpg","file_code":"1pr3owpabfgo","length":"00:04:04","views":"4893","vw_fmt":"4.9K","uploaded":"2023-10-10 00:58:18","up_fmt":"10 Okt 2023","up_short":"10 Okt","title":"Fransiska Hamil Bulan Nyepong Crot Di Mulut Sampe Muntah X Hamster Dood","t_esc":"Fransiska Hamil Bulan Nyepong Crot Di Mulut Sampe Muntah X Hamster Dood"},{"download_url":"https://playmogo.com/d/yctolyjmiw3o","single_img":"https://ticdn.net/snaps/288v7z76ifcesoye.jpg","file_code":"yctolyjmiw3o","length":"00:02:19","views":"5061","vw_fmt":"5.1K","uploaded":"2023-10-10 00:52:34","up_fmt":"10 Okt 2023","up_short":"10 Okt","title":"Video Tante Ernie Pemersatu Bangsa Link Web Bochiel Xpanas Indo","t_esc":"Video Tante Ernie Pemersatu Bangsa Link Web Bochiel Xpanas Indo"},{"download_url":"https://playmogo.com/d/l2te5xlca8r7","single_img":"https://ticdn.net/snaps/bp87w31eta8afnlp.jpg","file_code":"l2te5xlca8r7","length":"00:10:16","views":"1184","vw_fmt":"1.2K","uploaded":"2023-10-10 00:52:31","up_fmt":"10 Okt 2023","up_short":"10 Okt","title":"Video Bokep Viral Tisya Erni Sudah Liat Blm Cantik Tobrut Full Album","t_esc":"Video Bokep Viral Tisya Erni Sudah Liat Blm Cantik Tobrut Full Album"},{"download_url":"https://playmogo.com/d/sm0b5zkmjjxl","single_img":"https://ticdn.net/snaps/4f4t5d9mesbd46za.jpg","file_code":"sm0b5zkmjjxl","length":"00:04:45","views":"52902","vw_fmt":"52.9K","uploaded":"2023-10-10 00:41:28","up_fmt":"10 Okt 2023","up_short":"10 Okt","title":"Tante Yona Main Sama Om Dood Stream Twitter Video Colmek Bokepsin Bokep","t_esc":"Tante Yona Main Sama Om Dood Stream Twitter Video Colmek Bokepsin Bokep"},{"download_url":"https://playmogo.com/d/fnk87v39z42j","single_img":"https://ticdn.net/snaps/9l0s7ab4ddppu6xe.jpg","file_code":"fnk87v39z42j","length":"00:08:40","views":"127161","vw_fmt":"127.2K","uploaded":"2023-10-10 00:40:09","up_fmt":"10 Okt 2023","up_short":"10 Okt","title":"Dogy Binor Hijab Tante Yona Terbaru Viral Twitter Dood Stream Bochiel Bokepsin","t_esc":"Dogy Binor Hijab Tante Yona Terbaru Viral Twitter Dood Stream Bochiel Bokepsin"},{"download_url":"https://playmogo.com/d/m0xwift38ld4","single_img":"https://ticdn.net/snaps/a8g16zs5tlqr2e30.jpg","file_code":"m0xwift38ld4","length":"00:07:26","views":"3856","vw_fmt":"3.9K","uploaded":"2023-10-08 23:37:45","up_fmt":"8 Okt 2023","up_short":"8 Okt","title":"Mahasiswi Colmek Di Ruang Tamu Saat Rumah Sepi Dood Stream Cilbo Sotwe","t_esc":"Mahasiswi Colmek Di Ruang Tamu Saat Rumah Sepi Dood Stream Cilbo Sotwe"},{"download_url":"https://playmogo.com/d/kwmqh1ryu2hh","single_img":"https://ticdn.net/snaps/siy22ecefqt3iy83.jpg","file_code":"kwmqh1ryu2hh","length":"00:01:21","views":"3311","vw_fmt":"3.3K","uploaded":"2023-10-08 23:37:23","up_fmt":"8 Okt 2023","up_short":"8 Okt","title":"Pacaran Bareng Jande Di Ruang Tamu Dood Stream Link Web Indonesia Ngentot","t_esc":"Pacaran Bareng Jande Di Ruang Tamu Dood Stream Link Web Indonesia Ngentot"},{"download_url":"https://playmogo.com/d/l95p8ycgy5dw","single_img":"https://ticdn.net/snaps/a1ha4qcbqwfswfd0.jpg","file_code":"l95p8ycgy5dw","length":"00:02:19","views":"990","vw_fmt":"990","uploaded":"2023-10-08 23:37:13","up_fmt":"8 Okt 2023","up_short":"8 Okt","title":"Ngewe Hijab Sma Di Ruang Tamu Lagi Viral Doods Pro Memeksiana Bokepsin","t_esc":"Ngewe Hijab Sma Di Ruang Tamu Lagi Viral Doods Pro Memeksiana Bokepsin"},{"download_url":"https://playmogo.com/d/clmj6rhs1trh","single_img":"https://ticdn.net/snaps/p5uw3aegq5q17sbu.jpg","file_code":"clmj6rhs1trh","length":"00:03:26","views":"8036","vw_fmt":"8.0K","uploaded":"2023-10-08 23:37:11","up_fmt":"8 Okt 2023","up_short":"8 Okt","title":"Pembantu Nyepong Majikannya Di Ruang Tamu Pintu Luar Terbuka Folder Telegram Pekoblive","t_esc":"Pembantu Nyepong Majikannya Di Ruang Tamu Pintu Luar Terbuka Folder Telegram Pekoblive"},{"download_url":"https://playmogo.com/d/0u5277gq009s","single_img":"https://ticdn.net/snaps/ditpycw7b4rmcj60.jpg","file_code":"0u5277gq009s","length":"00:01:56","views":"2513","vw_fmt":"2.5K","uploaded":"2023-10-08 23:37:09","up_fmt":"8 Okt 2023","up_short":"8 Okt","title":"Abg Cosplay Maen Emek Di Ruang Tamu Asupan Viral Bokep Video Downloader","t_esc":"Abg Cosplay Maen Emek Di Ruang Tamu Asupan Viral Bokep Video Downloader"},{"download_url":"https://playmogo.com/d/z7blo2buu9ld","single_img":"https://ticdn.net/snaps/2fbocdmmhachzew2.jpg","file_code":"z7blo2buu9ld","length":"00:00:10","views":"22561","vw_fmt":"22.6K","uploaded":"2023-10-08 23:36:54","up_fmt":"8 Okt 2023","up_short":"8 Okt","title":"Muslim Udah Stw Ngentot Di Ruang Tamu Folder Pekoblive Twitter Tele Video","t_esc":"Muslim Udah Stw Ngentot Di Ruang Tamu Folder Pekoblive Twitter Tele Video"},{"download_url":"https://playmogo.com/d/96hprjvfy6f0","single_img":"https://ticdn.net/snaps/wy6zz22f00jr9xkc.jpg","file_code":"96hprjvfy6f0","length":"00:01:29","views":"2228","vw_fmt":"2.2K","uploaded":"2023-10-08 23:36:46","up_fmt":"8 Okt 2023","up_short":"8 Okt","title":"Sampe Muncrat Di Ruang Tamu Dood Stream Lulustream Bokepsin Folder Video Viral","t_esc":"Sampe Muncrat Di Ruang Tamu Dood Stream Lulustream Bokepsin Folder Video Viral"},{"download_url":"https://playmogo.com/d/9k033p969yiz","single_img":"https://ticdn.net/snaps/inxtf9kzg3gnbcro.jpg","file_code":"9k033p969yiz","length":"00:09:46","views":"2275","vw_fmt":"2.3K","uploaded":"2023-10-08 23:36:45","up_fmt":"8 Okt 2023","up_short":"8 Okt","title":"Ngewe Binor Di Ruang Tamu Dood Stream Downloader Video Sma Memeksiana Yakwad","t_esc":"Ngewe Binor Di Ruang Tamu Dood Stream Downloader Video Sma Memeksiana Yakwad"},{"download_url":"https://playmogo.com/d/80h7vqanrbms","single_img":"https://ticdn.net/snaps/h1mu4mljwq6llvjj.jpg","file_code":"80h7vqanrbms","length":"00:04:29","views":"4668","vw_fmt":"4.7K","uploaded":"2023-10-08 23:36:42","up_fmt":"8 Okt 2023","up_short":"8 Okt","title":"Genjot Ayang Hijab Di Ruang Tamu Dood Tele Video Viral Ful Album","t_esc":"Genjot Ayang Hijab Di Ruang Tamu Dood Tele Video Viral Ful Album"},{"download_url":"https://playmogo.com/d/d6m3nfr17esl","single_img":"https://ticdn.net/snaps/nsbk1murzwsvqdtr.jpg","file_code":"d6m3nfr17esl","length":"00:00:41","views":"6008","vw_fmt":"6.0K","uploaded":"2023-10-08 23:36:40","up_fmt":"8 Okt 2023","up_short":"8 Okt","title":"Wot Di Ruang Tamu Links Doodflix Video Viral Doodstreem Bokepsatset","t_esc":"Wot Di Ruang Tamu Links Doodflix Video Viral Doodstreem Bokepsatset"},{"download_url":"https://playmogo.com/d/2hy4wy7pprij","single_img":"https://ticdn.net/snaps/lq14pmiwodu84aav.jpg","file_code":"2hy4wy7pprij","length":"00:01:14","views":"9397","vw_fmt":"9.4K","uploaded":"2023-10-08 23:36:24","up_fmt":"8 Okt 2023","up_short":"8 Okt","title":"Ngewe Tante Bude Nungging Di Ruang Tamu Toketbagus Bokepin Cilbo Bochiel Terabox","t_esc":"Ngewe Tante Bude Nungging Di Ruang Tamu Toketbagus Bokepin Cilbo Bochiel Terabox"},{"download_url":"https://playmogo.com/d/gl0i67aa6sxf","single_img":"https://ticdn.net/snaps/otzenpsvwxzoti1f.jpg","file_code":"gl0i67aa6sxf","length":"00:07:26","views":"1474","vw_fmt":"1.5K","uploaded":"2023-10-08 23:36:20","up_fmt":"8 Okt 2023","up_short":"8 Okt","title":"Tante Bandung Kulum Penis Gede Brondong Di Ruang Tamu Dood Stream Doodstream","t_esc":"Tante Bandung Kulum Penis Gede Brondong Di Ruang Tamu Dood Stream Doodstream"},{"download_url":"https://playmogo.com/d/6xz4ycaeyd5w","single_img":"https://ticdn.net/snaps/wcly4z52z3daabzt.jpg","file_code":"6xz4ycaeyd5w","length":"00:01:50","views":"5462","vw_fmt":"5.5K","uploaded":"2023-10-08 23:36:19","up_fmt":"8 Okt 2023","up_short":"8 Okt","title":"Skandal Jilbab Dientot Saat Rumah Sepi Indo Dood Toketbagus Doostream Bokep31","t_esc":"Skandal Jilbab Dientot Saat Rumah Sepi Indo Dood Toketbagus Doostream Bokep31"},{"download_url":"https://playmogo.com/d/x39nxwr2cfd1","single_img":"https://ticdn.net/snaps/m041tqob80nxxqx2.jpg","file_code":"x39nxwr2cfd1","length":"00:04:16","views":"1251","vw_fmt":"1.3K","uploaded":"2023-10-08 23:35:51","up_fmt":"8 Okt 2023","up_short":"8 Okt","title":"Cewek Cantik Di Ruang Tamu Dood Stream Tele Simontok Lulustream Bokepsatset Bokep31","t_esc":"Cewek Cantik Di Ruang Tamu Dood Stream Tele Simontok Lulustream Bokepsatset Bokep31"},{"download_url":"https://playmogo.com/d/eu2961rfk4t8","single_img":"https://ticdn.net/snaps/1huhnjhuy99ygujm.jpg","file_code":"eu2961rfk4t8","length":"00:02:20","views":"13231","vw_fmt":"13.2K","uploaded":"2023-10-08 23:34:12","up_fmt":"8 Okt 2023","up_short":"8 Okt","title":"Ruang Tamu Sepi Langsung Gas Entot Pacar Di Sofa Dood Stream","t_esc":"Ruang Tamu Sepi Langsung Gas Entot Pacar Di Sofa Dood Stream"},{"download_url":"https://playmogo.com/d/wvsyflg49h0s","single_img":"https://ticdn.net/snaps/mmhrwektrn52rwp8.jpg","file_code":"wvsyflg49h0s","length":"00:12:49","views":"35339","vw_fmt":"35.3K","uploaded":"2023-10-08 23:34:07","up_fmt":"8 Okt 2023","up_short":"8 Okt","title":"Adek Tiri Dipaksa Ngewe Awalnya Malu Akhirnya Mau Doodflix Bokepind Ful Album","t_esc":"Adek Tiri Dipaksa Ngewe Awalnya Malu Akhirnya Mau Doodflix Bokepind Ful Album"},{"download_url":"https://playmogo.com/d/ozpz1co2hseg","single_img":"https://ticdn.net/snaps/ydugi1rjq355pl3v.jpg","file_code":"ozpz1co2hseg","length":"00:05:13","views":"2452","vw_fmt":"2.5K","uploaded":"2023-10-08 23:33:57","up_fmt":"8 Okt 2023","up_short":"8 Okt","title":"Ml Di Sofa Ruang Tamu Memeksiana Dood Bochiel Staklam Bokepsin","t_esc":"Ml Di Sofa Ruang Tamu Memeksiana Dood Bochiel Staklam Bokepsin"},{"download_url":"https://playmogo.com/d/zkrjmlkpzqvi","single_img":"https://ticdn.net/snaps/yrtw778t1h9p4175.jpg","file_code":"zkrjmlkpzqvi","length":"00:07:41","views":"1765","vw_fmt":"1.8K","uploaded":"2023-10-08 23:33:53","up_fmt":"8 Okt 2023","up_short":"8 Okt","title":"Sama Pacar Di Ruang Tamu Folder Video Viral Pemersatu Asupan","t_esc":"Sama Pacar Di Ruang Tamu Folder Video Viral Pemersatu Asupan"},{"download_url":"https://playmogo.com/d/3c05wfwgkb72","single_img":"https://ticdn.net/snaps/6xjwsvhfmubwuq84.jpg","file_code":"3c05wfwgkb72","length":"00:05:06","views":"2358","vw_fmt":"2.4K","uploaded":"2023-10-08 21:13:58","up_fmt":"8 Okt 2023","up_short":"8 Okt","title":"Hot Mom Sensasi Bercinta Kelas Bintang Com Pekoblive Telegram Doodsflix Pejuang Lendir","t_esc":"Hot Mom Sensasi Bercinta Kelas Bintang Com Pekoblive Telegram Doodsflix Pejuang Lendir"},{"download_url":"https://playmogo.com/d/ihb2lyjggma9","single_img":"https://ticdn.net/snaps/2if9j98sp03h5kpo.jpg","file_code":"ihb2lyjggma9","length":"00:54:09","views":"11941","vw_fmt":"11.9K","uploaded":"2023-10-08 21:13:52","up_fmt":"8 Okt 2023","up_short":"8 Okt","title":"Pepaya Gantung Full Movies Kelas Bintang Dood Stream Video Sma Bokepind Bokep","t_esc":"Pepaya Gantung Full Movies Kelas Bintang Dood Stream Video Sma Bokepind Bokep"},{"download_url":"https://playmogo.com/d/hfr6cakyarag","single_img":"https://ticdn.net/snaps/b91375tw4hseeuna.jpg","file_code":"hfr6cakyarag","length":"00:30:38","views":"12886","vw_fmt":"12.9K","uploaded":"2023-10-08 21:13:49","up_fmt":"8 Okt 2023","up_short":"8 Okt","title":"Threesome Film Series Kelas Bintang Video Bokep Links Bokep31 Tiktok Lokal","t_esc":"Threesome Film Series Kelas Bintang Video Bokep Links Bokep31 Tiktok Lokal"},{"download_url":"https://playmogo.com/d/c4damkx1ihon","single_img":"https://ticdn.net/snaps/4deps1t8uc1tkrby.jpg","file_code":"c4damkx1ihon","length":"00:23:14","views":"8381","vw_fmt":"8.4K","uploaded":"2023-10-08 21:13:35","up_fmt":"8 Okt 2023","up_short":"8 Okt","title":"Stw Part Film Series Kelas Bintang Com Bokep Dood Cilbo Bebasindo Asupan","t_esc":"Stw Part Film Series Kelas Bintang Com Bokep Dood Cilbo Bebasindo Asupan"},{"download_url":"https://playmogo.com/d/971bz2mjj4t8","single_img":"https://ticdn.net/snaps/grt1ixrutlm87rc8.jpg","file_code":"971bz2mjj4t8","length":"00:23:14","views":"71","vw_fmt":"71","uploaded":"2023-10-08 21:13:33","up_fmt":"8 Okt 2023","up_short":"8 Okt","title":"Stw Part Film Series Kelas Bintang Com Videos Yakwad Bebasindo Bokep Video","t_esc":"Stw Part Film Series Kelas Bintang Com Videos Yakwad Bebasindo Bokep Video"},{"download_url":"https://playmogo.com/d/vy8brve551w0","single_img":"https://ticdn.net/snaps/qz2e9ic2id8jb021.jpg","file_code":"vy8brve551w0","length":"00:05:06","views":"3288","vw_fmt":"3.3K","uploaded":"2023-10-08 21:13:30","up_fmt":"8 Okt 2023","up_short":"8 Okt","title":"Hot Mom Sensasi Bercinta Kelas Bintang Com Viral Bokep Video Doodsflix Bokepsin","t_esc":"Hot Mom Sensasi Bercinta Kelas Bintang Com Viral Bokep Video Doodsflix Bokepsin"},{"download_url":"https://playmogo.com/d/ykluiqr19fpv","single_img":"https://ticdn.net/snaps/4fu740el95sxdyj5.jpg","file_code":"ykluiqr19fpv","length":"00:46:22","views":"8657","vw_fmt":"8.7K","uploaded":"2023-10-08 21:13:28","up_fmt":"8 Okt 2023","up_short":"8 Okt","title":"Melly Artis Jepang Hadir Di Kelasbintang Com Tobrut Bokep Simontok Lagi Viral","t_esc":"Melly Artis Jepang Hadir Di Kelasbintang Com Tobrut Bokep Simontok Lagi Viral"},{"download_url":"https://playmogo.com/d/hdmnbelcc3gm","single_img":"https://ticdn.net/snaps/9dobtgms13fokxmt.jpg","file_code":"hdmnbelcc3gm","length":"01:03:33","views":"4472","vw_fmt":"4.5K","uploaded":"2023-10-08 21:13:26","up_fmt":"8 Okt 2023","up_short":"8 Okt","title":"Layangan Sange Ajarin Ponakan Anu Kelas Bintang Simontok Full Album Bokepin Doodflix","t_esc":"Layangan Sange Ajarin Ponakan Anu Kelas Bintang Simontok Full Album Bokepin Doodflix"},{"download_url":"https://playmogo.com/d/xn55azfxna1c","single_img":"https://ticdn.net/snaps/y62mnrh6r64ufgaa.jpg","file_code":"xn55azfxna1c","length":"00:33:48","views":"2297","vw_fmt":"2.3K","uploaded":"2023-10-08 21:13:24","up_fmt":"8 Okt 2023","up_short":"8 Okt","title":"Tanteku Emang Ajib Film Semi Kelas Bintang Terabox Doodstreem Bokep Video Full","t_esc":"Tanteku Emang Ajib Film Semi Kelas Bintang Terabox Doodstreem Bokep Video Full"},{"download_url":"https://playmogo.com/d/pl0dlwdzgr8g","single_img":"https://ticdn.net/snaps/up3kbxnj0kxel9a0.jpg","file_code":"pl0dlwdzgr8g","length":"02:32:51","views":"270","vw_fmt":"270","uploaded":"2023-10-08 20:31:29","up_fmt":"8 Okt 2023","up_short":"8 Okt","title":"Film Semi Jepang Semua Pria Tergoda Rara Anzai Jilbab Bokepind Video Bokep","t_esc":"Film Semi Jepang Semua Pria Tergoda Rara Anzai Jilbab Bokepind Video Bokep"},{"download_url":"https://playmogo.com/d/qq9nwtkrgckt","single_img":"https://ticdn.net/snaps/3a30dnytkwhcm45j.jpg","file_code":"qq9nwtkrgckt","length":"00:05:59","views":"8947","vw_fmt":"8.9K","uploaded":"2023-10-08 16:51:20","up_fmt":"8 Okt 2023","up_short":"8 Okt","title":"Rara Nadifa Pamer Body Pejuang Lendir Lokal Toketbagus Bokep Doodflix","t_esc":"Rara Nadifa Pamer Body Pejuang Lendir Lokal Toketbagus Bokep Doodflix"},{"download_url":"https://playmogo.com/d/k42hhahv8s74","single_img":"https://ticdn.net/snaps/c8by3jaypeaqi6xs.jpg","file_code":"k42hhahv8s74","length":"00:06:31","views":"20962","vw_fmt":"21.0K","uploaded":"2023-10-08 16:51:20","up_fmt":"8 Okt 2023","up_short":"8 Okt","title":"Rara Nadifa Cosplay Maid Telegram Folder Bokepsatset Bokep Dood Popstream","t_esc":"Rara Nadifa Cosplay Maid Telegram Folder Bokepsatset Bokep Dood Popstream"},{"download_url":"https://playmogo.com/d/cl1u2l4tcigv","single_img":"https://ticdn.net/snaps/ym8eel2sqwgaj2hj.jpg","file_code":"cl1u2l4tcigv","length":"00:12:23","views":"10452","vw_fmt":"10.5K","uploaded":"2023-10-08 16:51:20","up_fmt":"8 Okt 2023","up_short":"8 Okt","title":"Rara Nadifa Sm Putih Abu Bokepsin Asupan Folder Tele Tiktok","t_esc":"Rara Nadifa Sm Putih Abu Bokepsin Asupan Folder Tele Tiktok"},{"download_url":"https://playmogo.com/d/cjrm43nsvwwa","single_img":"https://ticdn.net/snaps/3ycklv5g1v9db2m5.jpg","file_code":"cjrm43nsvwwa","length":"00:39:24","views":"8023","vw_fmt":"8.0K","uploaded":"2023-10-08 13:05:54","up_fmt":"8 Okt 2023","up_short":"8 Okt","title":"Film Semi Korea Beauty Salon Special Services Part Dood Stream Doodsflix Doostream","t_esc":"Film Semi Korea Beauty Salon Special Services Part Dood Stream Doodsflix Doostream"},{"download_url":"https://playmogo.com/d/c89417i50fq0","single_img":"https://ticdn.net/snaps/e79rjz32j2tr00kf.jpg","file_code":"c89417i50fq0","length":"00:18:58","views":"3443","vw_fmt":"3.4K","uploaded":"2023-10-08 13:05:49","up_fmt":"8 Okt 2023","up_short":"8 Okt","title":"Burung Titipan Film Semi Lokal Kelas Bintang Sangetube Bokepind Bokep31 Simontok Ful","t_esc":"Burung Titipan Film Semi Lokal Kelas Bintang Sangetube Bokepind Bokep31 Simontok Ful"},{"download_url":"https://playmogo.com/d/bd5r9cmy2mdn","single_img":"https://ticdn.net/snaps/gpuluj4bl9ytfcuh.jpg","file_code":"bd5r9cmy2mdn","length":"00:03:03","views":"1719","vw_fmt":"1.7K","uploaded":"2023-10-08 13:05:46","up_fmt":"8 Okt 2023","up_short":"8 Okt","title":"Bokep Film Semi Korea Gemoy Bokep31 Doodstream Doods Pro Indo Indonesia","t_esc":"Bokep Film Semi Korea Gemoy Bokep31 Doodstream Doods Pro Indo Indonesia"},{"download_url":"https://playmogo.com/d/a3g43bsoac9i","single_img":"https://ticdn.net/snaps/6pwwdoyep917xaop.jpg","file_code":"a3g43bsoac9i","length":"00:14:26","views":"1594","vw_fmt":"1.6K","uploaded":"2023-10-08 13:05:45","up_fmt":"8 Okt 2023","up_short":"8 Okt","title":"Bokep Film Semi Jepang Gemoy Tele Staklam Doodstreem Memeksiana Video Viral","t_esc":"Bokep Film Semi Jepang Gemoy Tele Staklam Doodstreem Memeksiana Video Viral"},{"download_url":"https://playmogo.com/d/u0tturzjjbkq","single_img":"https://ticdn.net/snaps/yrfz7ydh0laxsrou.jpg","file_code":"u0tturzjjbkq","length":"00:03:15","views":"538","vw_fmt":"538","uploaded":"2023-10-08 13:05:43","up_fmt":"8 Okt 2023","up_short":"8 Okt","title":"Film Bokep Semi Korea Gemoy Popstream Terupdate Tiktok Ful Album Simontok","t_esc":"Film Bokep Semi Korea Gemoy Popstream Terupdate Tiktok Ful Album Simontok"},{"download_url":"https://playmogo.com/d/b4v1ybfmknle","single_img":"https://ticdn.net/snaps/hzofouda0raj2pz8.jpg","file_code":"b4v1ybfmknle","length":"00:03:05","views":"2173","vw_fmt":"2.2K","uploaded":"2023-10-08 13:05:33","up_fmt":"8 Okt 2023","up_short":"8 Okt","title":"Film Semi Korea Bokep Gemoy Video Doods Pro Simontok Streaming","t_esc":"Film Semi Korea Bokep Gemoy Video Doods Pro Simontok Streaming"},{"download_url":"https://playmogo.com/d/52c704c316n5","single_img":"https://ticdn.net/snaps/tv8y3ytq4ip3lm0n.jpg","file_code":"52c704c316n5","length":"00:33:48","views":"1162","vw_fmt":"1.2K","uploaded":"2023-10-08 13:05:24","up_fmt":"8 Okt 2023","up_short":"8 Okt","title":"Tanteku Emang Ajib Film Semi Kelas Bintang Bokep Terbaru Viral Bokepsatset Doostream","t_esc":"Tanteku Emang Ajib Film Semi Kelas Bintang Bokep Terbaru Viral Bokepsatset Doostream"},{"download_url":"https://playmogo.com/d/tfa1419afjyx","single_img":"https://ticdn.net/snaps/xfffpj9wfrhak8g8.jpg","file_code":"tfa1419afjyx","length":"00:33:48","views":"3097","vw_fmt":"3.1K","uploaded":"2023-10-08 13:05:23","up_fmt":"8 Okt 2023","up_short":"8 Okt","title":"Tanteku Emang Ajib Film Semi Kelas Bintang Bokep Terbaru Bebasindo Pemersatu Twitter","t_esc":"Tanteku Emang Ajib Film Semi Kelas Bintang Bokep Terbaru Bebasindo Pemersatu Twitter"},{"download_url":"https://playmogo.com/d/rsn2860lsxmv","single_img":"https://ticdn.net/snaps/ug61xo3lqlzcethb.jpg","file_code":"rsn2860lsxmv","length":"00:57:35","views":"13454","vw_fmt":"13.5K","uploaded":"2023-10-08 13:05:16","up_fmt":"8 Okt 2023","up_short":"8 Okt","title":"Bokep Indo Virly Virginia Sugar Daddy Film Kelas Bintang Semi Tante","t_esc":"Bokep Indo Virly Virginia Sugar Daddy Film Kelas Bintang Semi Tante"},{"download_url":"https://playmogo.com/d/zdo26jfm7lvz","single_img":"https://ticdn.net/snaps/we7x7oj4z5truh0g.jpg","file_code":"zdo26jfm7lvz","length":"01:28:16","views":"10946","vw_fmt":"10.9K","uploaded":"2023-10-08 13:05:16","up_fmt":"8 Okt 2023","up_short":"8 Okt","title":"Bokep Indo Siskaeee Kramat Tunggak Kelas Bintang Kelasbintang Virly Virginia Ofc Film","t_esc":"Bokep Indo Siskaeee Kramat Tunggak Kelas Bintang Kelasbintang Virly Virginia Ofc Film"},{"download_url":"https://playmogo.com/d/nbeyaw1p85kg","single_img":"https://ticdn.net/snaps/yui708vvnfgqo81z.jpg","file_code":"nbeyaw1p85kg","length":"00:58:22","views":"6412","vw_fmt":"6.4K","uploaded":"2023-10-08 13:05:14","up_fmt":"8 Okt 2023","up_short":"8 Okt","title":"Bokep Indo Mangga Muda Film Kelas Bintang Kelasbintang Semi Tante","t_esc":"Bokep Indo Mangga Muda Film Kelas Bintang Kelasbintang Semi Tante"},{"download_url":"https://playmogo.com/d/mgsr50b9vr4v","single_img":"https://ticdn.net/snaps/jnuco4h1i4xsrky7.jpg","file_code":"mgsr50b9vr4v","length":"01:27:55","views":"995","vw_fmt":"995","uploaded":"2023-10-08 13:05:11","up_fmt":"8 Okt 2023","up_short":"8 Okt","title":"Bokep Paupahan Film Semi Sub Indo Doostream Cilbo Ngentot Popstream Bokep31","t_esc":"Bokep Paupahan Film Semi Sub Indo Doostream Cilbo Ngentot Popstream Bokep31"},{"download_url":"https://playmogo.com/d/o93qqt0le9tk","single_img":"https://ticdn.net/snaps/589toaq49pifv6qw.jpg","file_code":"o93qqt0le9tk","length":"01:31:24","views":"2068","vw_fmt":"2.1K","uploaded":"2023-10-08 13:05:09","up_fmt":"8 Okt 2023","up_short":"8 Okt","title":"Bokep Sex Games Film Semi Sub Indo Telegram Bokepsin Dood Video","t_esc":"Bokep Sex Games Film Semi Sub Indo Telegram Bokepsin Dood Video"},{"download_url":"https://playmogo.com/d/gg00yrnikg9m","single_img":"https://ticdn.net/snaps/dsmgvjmjze3rqbog.jpg","file_code":"gg00yrnikg9m","length":"01:51:32","views":"1840","vw_fmt":"1.8K","uploaded":"2023-10-08 13:05:09","up_fmt":"8 Okt 2023","up_short":"8 Okt","title":"Afam Sub Indo Bokep Film Semi Subtitle Indonesia Ngentot Twitter Bokepin Poophd","t_esc":"Afam Sub Indo Bokep Film Semi Subtitle Indonesia Ngentot Twitter Bokepin Poophd"},{"download_url":"https://playmogo.com/d/f3t9ui3rmra2","single_img":"https://ticdn.net/snaps/1r8nadeoenku0hg9.jpg","file_code":"f3t9ui3rmra2","length":"01:37:00","views":"1689","vw_fmt":"1.7K","uploaded":"2023-10-08 13:05:08","up_fmt":"8 Okt 2023","up_short":"8 Okt","title":"Crush Kong Curly Sub Indo Bokep Film Semi Subtitle Indonesia Memeksiana Simintok","t_esc":"Crush Kong Curly Sub Indo Bokep Film Semi Subtitle Indonesia Memeksiana Simintok"},{"download_url":"https://playmogo.com/d/pk13yvwz3lfd","single_img":"https://ticdn.net/snaps/2sc31by9raaeu8rn.jpg","file_code":"pk13yvwz3lfd","length":"01:48:37","views":"579","vw_fmt":"579","uploaded":"2023-10-08 13:05:05","up_fmt":"8 Okt 2023","up_short":"8 Okt","title":"Domme Sub Indo Bokep Film Semi Subtitle Indonesia Website Terupdate Viral Doods","t_esc":"Domme Sub Indo Bokep Film Semi Subtitle Indonesia Website Terupdate Viral Doods"},{"download_url":"https://playmogo.com/d/stfwgv772iau","single_img":"https://ticdn.net/snaps/86skw4xa4eq05cgq.jpg","file_code":"stfwgv772iau","length":"01:34:36","views":"2566","vw_fmt":"2.6K","uploaded":"2023-10-08 13:05:02","up_fmt":"8 Okt 2023","up_short":"8 Okt","title":"Bokep Balik Taya Film Semi Sub Indo Angeli Khang Dood Stream Video","t_esc":"Bokep Balik Taya Film Semi Sub Indo Angeli Khang Dood Stream Video"},{"download_url":"https://playmogo.com/d/s6vwxib6xoli","single_img":"https://ticdn.net/snaps/5fuczqrrijrwleiy.jpg","file_code":"s6vwxib6xoli","length":"01:47:50","views":"679","vw_fmt":"679","uploaded":"2023-10-08 13:04:59","up_fmt":"8 Okt 2023","up_short":"8 Okt","title":"Kaliwaan Sub Indo Bokep Film Semi Subtitle Indonesia Telegram Bokepind Doods Pro","t_esc":"Kaliwaan Sub Indo Bokep Film Semi Subtitle Indonesia Telegram Bokepind Doods Pro"},{"download_url":"https://playmogo.com/d/o081p3jv7hpg","single_img":"https://ticdn.net/snaps/0gkya0ewdpra12gm.jpg","file_code":"o081p3jv7hpg","length":"00:20:09","views":"13015","vw_fmt":"13.0K","uploaded":"2023-10-08 13:04:59","up_fmt":"8 Okt 2023","up_short":"8 Okt","title":"Bokep Indo Artis Ayu Azhari Adegan Bugil Ngentot Film Semi Bochiel Indonesia","t_esc":"Bokep Indo Artis Ayu Azhari Adegan Bugil Ngentot Film Semi Bochiel Indonesia"},{"download_url":"https://playmogo.com/d/bz0j0i8bh4sz","single_img":"https://ticdn.net/snaps/am5o3y9sg3uw01iz.jpg","file_code":"bz0j0i8bh4sz","length":"01:42:56","views":"1353","vw_fmt":"1.4K","uploaded":"2023-10-08 13:04:50","up_fmt":"8 Okt 2023","up_short":"8 Okt","title":"Boso Dos Sub Indo Bokep Film Semi Subtitle Indonesia Dood Stream Lulustream","t_esc":"Boso Dos Sub Indo Bokep Film Semi Subtitle Indonesia Dood Stream Lulustream"},{"download_url":"https://playmogo.com/d/qber7p7zs2zo","single_img":"https://ticdn.net/snaps/oitzp8leseuenyuy.jpg","file_code":"qber7p7zs2zo","length":"01:31:40","views":"1620","vw_fmt":"1.6K","uploaded":"2023-10-08 13:04:50","up_fmt":"8 Okt 2023","up_short":"8 Okt","title":"Film Semi Sex Erotic Movie Sweet Pejuang Lendir Simontok Doodflix Bokep31 Cantik","t_esc":"Film Semi Sex Erotic Movie Sweet Pejuang Lendir Simontok Doodflix Bokep31 Cantik"},{"download_url":"https://playmogo.com/d/2nzir1y4dziv","single_img":"https://ticdn.net/snaps/106yyqx3asg5popp.jpg","file_code":"2nzir1y4dziv","length":"00:35:07","views":"3447","vw_fmt":"3.4K","uploaded":"2023-10-08 13:04:49","up_fmt":"8 Okt 2023","up_short":"8 Okt","title":"Dukun Cabul Film Semi Kelas Bintang Memeksiana Indo Terabox Video Viral Cantik","t_esc":"Dukun Cabul Film Semi Kelas Bintang Memeksiana Indo Terabox Video Viral Cantik"},{"download_url":"https://playmogo.com/d/6u9ss6un6750","single_img":"https://ticdn.net/snaps/fulk53qbdnni9p9c.jpg","file_code":"6u9ss6un6750","length":"00:57:35","views":"11402","vw_fmt":"11.4K","uploaded":"2023-10-08 13:04:47","up_fmt":"8 Okt 2023","up_short":"8 Okt","title":"Bokep Indo Virly Virginia Sugar Daddy Film Kelas Bintang Semi Tante Dood","t_esc":"Bokep Indo Virly Virginia Sugar Daddy Film Kelas Bintang Semi Tante Dood"},{"download_url":"https://playmogo.com/d/0vpdt2p7viep","single_img":"https://ticdn.net/snaps/oss0cqzg9zfg1ye7.jpg","file_code":"0vpdt2p7viep","length":"00:03:25","views":"92263","vw_fmt":"92.3K","uploaded":"2023-10-08 13:04:46","up_fmt":"8 Okt 2023","up_short":"8 Okt","title":"Di Balik Layar Kelas Bintang Cantik Tobrut Bochiel Doodflix Doostream Simontok","t_esc":"Di Balik Layar Kelas Bintang Cantik Tobrut Bochiel Doodflix Doostream Simontok"},{"download_url":"https://playmogo.com/d/4en0aejfxdyp","single_img":"https://ticdn.net/snaps/wu2mgsfg7lcvhwpd.jpg","file_code":"4en0aejfxdyp","length":"00:53:40","views":"21925","vw_fmt":"21.9K","uploaded":"2023-10-08 13:04:45","up_fmt":"8 Okt 2023","up_short":"8 Okt","title":"Artis Cantik Dibalik Layar Kelas Bintang Dood Stream Lulustream Doostream Tele Update","t_esc":"Artis Cantik Dibalik Layar Kelas Bintang Dood Stream Lulustream Doostream Tele Update"},{"download_url":"https://playmogo.com/d/6tdux2hmjgym","single_img":"https://ticdn.net/snaps/a47azd0djk7c5547.jpg","file_code":"6tdux2hmjgym","length":"00:41:20","views":"50463","vw_fmt":"50.5K","uploaded":"2023-10-08 13:04:44","up_fmt":"8 Okt 2023","up_short":"8 Okt","title":"Kelas Bintang Birahi Muda Meli Gp Biasa Popstream Lokal Doods Pro Indo","t_esc":"Kelas Bintang Birahi Muda Meli Gp Biasa Popstream Lokal Doods Pro Indo"},{"download_url":"https://playmogo.com/d/oes3mjk1ho0m","single_img":"https://ticdn.net/snaps/e3dxhsvhhnzfd5me.jpg","file_code":"oes3mjk1ho0m","length":"00:57:35","views":"11605","vw_fmt":"11.6K","uploaded":"2023-10-08 13:04:41","up_fmt":"8 Okt 2023","up_short":"8 Okt","title":"Virly Virginia Sugar Daddy Film Kelas Bintang Semi Tante Dood Strea","t_esc":"Virly Virginia Sugar Daddy Film Kelas Bintang Semi Tante Dood Strea"},{"download_url":"https://playmogo.com/d/pmz2caa5eizb","single_img":"https://ticdn.net/snaps/e4br87ninow73js7.jpg","file_code":"pmz2caa5eizb","length":"00:02:41","views":"14549","vw_fmt":"14.5K","uploaded":"2023-10-08 13:04:39","up_fmt":"8 Okt 2023","up_short":"8 Okt","title":"Bts Film Semi Indo Kelas Bintang Premium Content Dood Stream Link Web","t_esc":"Bts Film Semi Indo Kelas Bintang Premium Content Dood Stream Link Web"},{"download_url":"https://playmogo.com/d/cqy26582f1wf","single_img":"https://ticdn.net/snaps/6lp9qumvibakpc3o.jpg","file_code":"cqy26582f1wf","length":"00:10:09","views":"2778","vw_fmt":"2.8K","uploaded":"2023-10-08 12:25:47","up_fmt":"8 Okt 2023","up_short":"8 Okt","title":"Layani Pria Sampai Bergetar Muncrat Video Viral Bokep Lokal Pejuang Lendir Links","t_esc":"Layani Pria Sampai Bergetar Muncrat Video Viral Bokep Lokal Pejuang Lendir Links"},{"download_url":"https://playmogo.com/d/drv9uigesan4","single_img":"https://ticdn.net/snaps/wawxb39oz70t1y6e.jpg","file_code":"drv9uigesan4","length":"00:31:04","views":"1302","vw_fmt":"1.3K","uploaded":"2023-10-08 12:25:46","up_fmt":"8 Okt 2023","up_short":"8 Okt","title":"Nabil Squirt Muncrat Live Show Dood Stream Bokepin Video Bokep Staklam Indo","t_esc":"Nabil Squirt Muncrat Live Show Dood Stream Bokepin Video Bokep Staklam Indo"},{"download_url":"https://playmogo.com/d/cqmhb34iudxy","single_img":"https://ticdn.net/snaps/8toyhfwu7imidbju.jpg","file_code":"cqmhb34iudxy","length":"00:02:19","views":"38857","vw_fmt":"38.9K","uploaded":"2023-10-08 12:25:45","up_fmt":"8 Okt 2023","up_short":"8 Okt","title":"Penjaga Warung Muncrat Dood Stream Tiktok Staklam Video Sma Downloader Full Album","t_esc":"Penjaga Warung Muncrat Dood Stream Tiktok Staklam Video Sma Downloader Full Album"},{"download_url":"https://playmogo.com/d/1y0t7f2idaak","single_img":"https://ticdn.net/snaps/21zycbcx4pxz8di1.jpg","file_code":"1y0t7f2idaak","length":"00:07:41","views":"5551","vw_fmt":"5.6K","uploaded":"2023-10-08 12:25:42","up_fmt":"8 Okt 2023","up_short":"8 Okt","title":"Puasin Dildo Sampe Muncrat Serrrr Dood Stream Doostream Bokepsatset Memeksiana Video Viral","t_esc":"Puasin Dildo Sampe Muncrat Serrrr Dood Stream Doostream Bokepsatset Memeksiana Video Viral"},{"download_url":"https://playmogo.com/d/qi86v900jrux","single_img":"https://ticdn.net/snaps/ijxsgqgmqg9a7112.jpg","file_code":"qi86v900jrux","length":"00:03:00","views":"3823","vw_fmt":"3.8K","uploaded":"2023-10-08 12:25:41","up_fmt":"8 Okt 2023","up_short":"8 Okt","title":"Momoy Gemoy Colok Sampe Muncrat Dood Stream Telegram Indo Tele Viral Asupan","t_esc":"Momoy Gemoy Colok Sampe Muncrat Dood Stream Telegram Indo Tele Viral Asupan"},{"download_url":"https://playmogo.com/d/s50vpl2cfr8s","single_img":"https://ticdn.net/snaps/ha8joizxzd0evok7.jpg","file_code":"s50vpl2cfr8s","length":"00:02:20","views":"3748","vw_fmt":"3.7K","uploaded":"2023-10-08 12:25:36","up_fmt":"8 Okt 2023","up_short":"8 Okt","title":"Nggak Tahan Sama Desahan Cewe Ini Doodstreamapaaja Telegram Dood Stream Bokep Video","t_esc":"Nggak Tahan Sama Desahan Cewe Ini Doodstreamapaaja Telegram Dood Stream Bokep Video"},{"download_url":"https://playmogo.com/d/ziuwy4ybjs20","single_img":"https://ticdn.net/snaps/i947tknsmfemc1ve.jpg","file_code":"ziuwy4ybjs20","length":"00:02:07","views":"2773","vw_fmt":"2.8K","uploaded":"2023-10-08 12:25:32","up_fmt":"8 Okt 2023","up_short":"8 Okt","title":"Abg Omek Desahan Nya Enak Banget Bokep Bebasindo Folder Tobrut Lulustream","t_esc":"Abg Omek Desahan Nya Enak Banget Bokep Bebasindo Folder Tobrut Lulustream"},{"download_url":"https://playmogo.com/d/21a9zh8s9fpq","single_img":"https://ticdn.net/snaps/01o9bv9oqgzctumh.jpg","file_code":"21a9zh8s9fpq","length":"00:02:20","views":"1338","vw_fmt":"1.3K","uploaded":"2023-10-08 12:25:29","up_fmt":"8 Okt 2023","up_short":"8 Okt","title":"Desahan Cewe Hijab Xnxx Com Lulustream Tobrut Tiktok Doodsflix Video Indo","t_esc":"Desahan Cewe Hijab Xnxx Com Lulustream Tobrut Tiktok Doodsflix Video Indo"},{"download_url":"https://playmogo.com/d/guruebo20bw9","single_img":"https://ticdn.net/snaps/e34one9l087c4udf.jpg","file_code":"guruebo20bw9","length":"00:01:59","views":"2815","vw_fmt":"2.8K","uploaded":"2023-10-08 12:25:28","up_fmt":"8 Okt 2023","up_short":"8 Okt","title":"Desahan Disaat Colmek Downloader Dood Popstream Terabox Streaming","t_esc":"Desahan Disaat Colmek Downloader Dood Popstream Terabox Streaming"},{"download_url":"https://playmogo.com/d/9h7ewan5gpoj","single_img":"https://ticdn.net/snaps/adcgpkfmqd170sv5.jpg","file_code":"9h7ewan5gpoj","length":"00:07:51","views":"6756","vw_fmt":"6.8K","uploaded":"2023-10-08 12:25:24","up_fmt":"8 Okt 2023","up_short":"8 Okt","title":"Kuli Sawit Ganteng Muscle Ngocokk Kntl Dibayarin Mas Iffal Desahan Nya Bikin","t_esc":"Kuli Sawit Ganteng Muscle Ngocokk Kntl Dibayarin Mas Iffal Desahan Nya Bikin"},{"download_url":"https://playmogo.com/d/5zuis7k8irq9","single_img":"https://ticdn.net/snaps/cohqe9zzy6s08jm1.jpg","file_code":"5zuis7k8irq9","length":"00:01:12","views":"10202","vw_fmt":"10.2K","uploaded":"2023-10-08 12:25:23","up_fmt":"8 Okt 2023","up_short":"8 Okt","title":"Desahan Cici Di Entot Otong Besar Meki Sempit No Bulu Dood Stream","t_esc":"Desahan Cici Di Entot Otong Besar Meki Sempit No Bulu Dood Stream"},{"download_url":"https://playmogo.com/d/y4ta0np0wjvn","single_img":"https://ticdn.net/snaps/qvzenws88w88bf7w.jpg","file_code":"y4ta0np0wjvn","length":"00:27:03","views":"1325","vw_fmt":"1.3K","uploaded":"2023-10-08 12:25:22","up_fmt":"8 Okt 2023","up_short":"8 Okt","title":"Onlyfans Manyvids Valerica Steele Red Squirt P Bokepsin Bokepin Doodsflix Bokep Dood","t_esc":"Onlyfans Manyvids Valerica Steele Red Squirt P Bokepsin Bokepin Doodsflix Bokep Dood"},{"download_url":"https://playmogo.com/d/vx5oy3zmi9cy","single_img":"https://ticdn.net/snaps/fgkcknzfnmodytvt.jpg","file_code":"vx5oy3zmi9cy","length":"00:00:54","views":"28249","vw_fmt":"28.2K","uploaded":"2023-10-08 12:25:21","up_fmt":"8 Okt 2023","up_short":"8 Okt","title":"Desahan Nya Enak Beut Cui Bokep Bokepin Bebasindo Dood Tele Bochiel","t_esc":"Desahan Nya Enak Beut Cui Bokep Bokepin Bebasindo Dood Tele Bochiel"},{"download_url":"https://playmogo.com/d/3azzen9pst2q","single_img":"https://ticdn.net/snaps/yr55q6vctbhugndd.jpg","file_code":"3azzen9pst2q","length":"00:12:18","views":"1052","vw_fmt":"1.1K","uploaded":"2023-10-08 12:25:19","up_fmt":"8 Okt 2023","up_short":"8 Okt","title":"Desahan Lisa Abg Hot Bj G Asupan Toketbagus Lokal Simintok Yakwad","t_esc":"Desahan Lisa Abg Hot Bj G Asupan Toketbagus Lokal Simintok Yakwad"},{"download_url":"https://playmogo.com/d/9tcbjdm3zfnt","single_img":"https://ticdn.net/snaps/dk56xqa8xm03vurs.jpg","file_code":"9tcbjdm3zfnt","length":"00:01:39","views":"3337","vw_fmt":"3.3K","uploaded":"2023-10-08 12:25:18","up_fmt":"8 Okt 2023","up_short":"8 Okt","title":"Desahan Mantan Low Mp Popstream Doodstream Simintok Terupdate Simontok","t_esc":"Desahan Mantan Low Mp Popstream Doodstream Simintok Terupdate Simontok"},{"download_url":"https://playmogo.com/d/hcu1v7jhuxoi","single_img":"https://ticdn.net/snaps/qttnsz8f7etnn1tp.jpg","file_code":"hcu1v7jhuxoi","length":"00:59:24","views":"489","vw_fmt":"489","uploaded":"2023-10-08 12:25:08","up_fmt":"8 Okt 2023","up_short":"8 Okt","title":"Kembang Desa Bahenol By Marlboroqueensex Live Simintok Bochiel Doodflix Jilbab","t_esc":"Kembang Desa Bahenol By Marlboroqueensex Live Simintok Bochiel Doodflix Jilbab"},{"download_url":"https://playmogo.com/d/q7ubiphyx0aa","single_img":"https://ticdn.net/snaps/vm2xtswn65d35ftb.jpg","file_code":"q7ubiphyx0aa","length":"00:05:27","views":"1906","vw_fmt":"1.9K","uploaded":"2023-10-08 12:25:03","up_fmt":"8 Okt 2023","up_short":"8 Okt","title":"Ayue Taniya Wot Mendesah Keenakan Folder Asupan Viral Popstream Doods Pro Link","t_esc":"Ayue Taniya Wot Mendesah Keenakan Folder Asupan Viral Popstream Doods Pro Link"},{"download_url":"https://playmogo.com/d/e98a89so5jmg","single_img":"https://ticdn.net/snaps/jpt3u1yyrds0ylek.jpg","file_code":"e98a89so5jmg","length":"00:00:28","views":"3449","vw_fmt":"3.4K","uploaded":"2023-10-08 12:25:02","up_fmt":"8 Okt 2023","up_short":"8 Okt","title":"Toket Gede Mendesah Dood Stream Indo Cilbo Telegram Simontok","t_esc":"Toket Gede Mendesah Dood Stream Indo Cilbo Telegram Simontok"},{"download_url":"https://playmogo.com/d/rxell8yrscrw","single_img":"https://ticdn.net/snaps/wzwzblgwelnry6pu.jpg","file_code":"rxell8yrscrw","length":"00:00:31","views":"1628","vw_fmt":"1.6K","uploaded":"2023-10-08 12:25:01","up_fmt":"8 Okt 2023","up_short":"8 Okt","title":"Mendesah Tipis Doodsflix Asupan Full Album Terabox Simontok","t_esc":"Mendesah Tipis Doodsflix Asupan Full Album Terabox Simontok"},{"download_url":"https://playmogo.com/d/fwe8b4kpahll","single_img":"https://ticdn.net/snaps/t4jl04c8yhyc2qs3.jpg","file_code":"fwe8b4kpahll","length":"01:59:56","views":"953","vw_fmt":"953","uploaded":"2023-10-08 12:25:00","up_fmt":"8 Okt 2023","up_short":"8 Okt","title":"Tutorial Bikin Cewek Organisme Sampai Mendesah Mirai Asumi Bebasindo Video Sma Bokep","t_esc":"Tutorial Bikin Cewek Organisme Sampai Mendesah Mirai Asumi Bebasindo Video Sma Bokep"},{"download_url":"https://playmogo.com/d/85whmctv42ut","single_img":"https://ticdn.net/snaps/5wwto9ifxx0667pw.jpg","file_code":"85whmctv42ut","length":"00:17:33","views":"12064","vw_fmt":"12.1K","uploaded":"2023-10-08 12:24:58","up_fmt":"8 Okt 2023","up_short":"8 Okt","title":"Sampe Mendesah Desah Dood Stream Bokepind Bokep Video Update Tele","t_esc":"Sampe Mendesah Desah Dood Stream Bokepind Bokep Video Update Tele"},{"download_url":"https://playmogo.com/d/zedxk4z3fuhm","single_img":"https://ticdn.net/snaps/3ana07hgzgabcou5.jpg","file_code":"zedxk4z3fuhm","length":"00:19:01","views":"978","vw_fmt":"978","uploaded":"2023-10-08 12:24:58","up_fmt":"8 Okt 2023","up_short":"8 Okt","title":"Bokep Indo Cantik Tobrut Remas Tt Mendesah Live Bochiel Lulustream Bokepind Viral","t_esc":"Bokep Indo Cantik Tobrut Remas Tt Mendesah Live Bochiel Lulustream Bokepind Viral"},{"download_url":"https://playmogo.com/d/v9etfkr0sich","single_img":"https://ticdn.net/snaps/ktft1jasbwlxktos.jpg","file_code":"v9etfkr0sich","length":"00:07:56","views":"10352","vw_fmt":"10.4K","uploaded":"2023-10-08 12:24:57","up_fmt":"8 Okt 2023","up_short":"8 Okt","title":"Grepe Totek Ayang Lagi Tiduran Malah Mendesah Lulustream Indo Streaming Pekoblive Bokepsatset","t_esc":"Grepe Totek Ayang Lagi Tiduran Malah Mendesah Lulustream Indo Streaming Pekoblive Bokepsatset"},{"download_url":"https://playmogo.com/d/6ilnsf389z19","single_img":"https://ticdn.net/snaps/5nuusigic42tyiz9.jpg","file_code":"6ilnsf389z19","length":"00:04:27","views":"4003","vw_fmt":"4.0K","uploaded":"2023-10-08 12:24:56","up_fmt":"8 Okt 2023","up_short":"8 Okt","title":"Entot Bumil Sampe Mendesah Keenakan Crot Muka Asupan Viral Terupdate Simontok Video","t_esc":"Entot Bumil Sampe Mendesah Keenakan Crot Muka Asupan Viral Terupdate Simontok Video"},{"download_url":"https://playmogo.com/d/1lgbqdy3zcyw","single_img":"https://ticdn.net/snaps/2hkkmory4ypq6ygf.jpg","file_code":"1lgbqdy3zcyw","length":"00:02:59","views":"5477","vw_fmt":"5.5K","uploaded":"2023-10-08 12:24:37","up_fmt":"8 Okt 2023","up_short":"8 Okt","title":"Nekat Maen Di Wc Mall Sama Tante Hijab Dood Tele Simontok Doodstreem","t_esc":"Nekat Maen Di Wc Mall Sama Tante Hijab Dood Tele Simontok Doodstreem"},{"download_url":"https://playmogo.com/d/g4nk3v32galv","single_img":"https://ticdn.net/snaps/nvklymuho4fa63op.jpg","file_code":"g4nk3v32galv","length":"00:12:40","views":"1632","vw_fmt":"1.6K","uploaded":"2023-10-08 12:24:36","up_fmt":"8 Okt 2023","up_short":"8 Okt","title":"Tante Montok Prank Pengantar Makanan Dood Stream Lagi Viral Website Ful Album","t_esc":"Tante Montok Prank Pengantar Makanan Dood Stream Lagi Viral Website Ful Album"},{"download_url":"https://playmogo.com/d/6o83x6438mt2","single_img":"https://ticdn.net/snaps/8nxmaqjauttpog2i.jpg","file_code":"6o83x6438mt2","length":"00:08:02","views":"1761","vw_fmt":"1.8K","uploaded":"2023-10-08 12:24:34","up_fmt":"8 Okt 2023","up_short":"8 Okt","title":"Niat Hati Cuma Ngintip Eh Khilaf Jga Sama Tante Dood Stream","t_esc":"Niat Hati Cuma Ngintip Eh Khilaf Jga Sama Tante Dood Stream"},{"download_url":"https://playmogo.com/d/nt43nag9em6g","single_img":"https://ticdn.net/snaps/r9f7cemb40nk96ir.jpg","file_code":"nt43nag9em6g","length":"00:02:47","views":"1195","vw_fmt":"1.2K","uploaded":"2023-10-08 12:24:29","up_fmt":"8 Okt 2023","up_short":"8 Okt","title":"Tante Udah Pasrah Dood Stream Tele Bokepsin Simontok Bebasindo Videos","t_esc":"Tante Udah Pasrah Dood Stream Tele Bokepsin Simontok Bebasindo Videos"},{"download_url":"https://playmogo.com/d/832pu1if3dkf","single_img":"https://ticdn.net/snaps/v6gp9d462w5yz3s3.jpg","file_code":"832pu1if3dkf","length":"00:02:15","views":"21586","vw_fmt":"21.6K","uploaded":"2023-10-08 12:24:25","up_fmt":"8 Okt 2023","up_short":"8 Okt","title":"Tante Dibungkus Sama Ponakan Sendiri Modus Anterin Pulang Dood Stre Video Bokep","t_esc":"Tante Dibungkus Sama Ponakan Sendiri Modus Anterin Pulang Dood Stre Video Bokep"},{"download_url":"https://playmogo.com/d/v4n9l5756c03","single_img":"https://ticdn.net/snaps/hjzn2zdtv7cxuy5s.jpg","file_code":"v4n9l5756c03","length":"00:07:18","views":"554","vw_fmt":"554","uploaded":"2023-10-08 12:24:16","up_fmt":"8 Okt 2023","up_short":"8 Okt","title":"Tante Cinta Pepaya Gantungnya Ga Ada Obet Dood Stream Doodstreem Indonesia Bokep31","t_esc":"Tante Cinta Pepaya Gantungnya Ga Ada Obet Dood Stream Doodstreem Indonesia Bokep31"},{"download_url":"https://playmogo.com/d/7ma4v7uktjue","single_img":"https://ticdn.net/snaps/orw18fmp42fcwlvq.jpg","file_code":"7ma4v7uktjue","length":"00:02:19","views":"1471","vw_fmt":"1.5K","uploaded":"2023-10-08 12:23:57","up_fmt":"8 Okt 2023","up_short":"8 Okt","title":"Jav Ibu Menuruti Sang Anak Staklam Tobrut Bokep Video Asupan","t_esc":"Jav Ibu Menuruti Sang Anak Staklam Tobrut Bokep Video Asupan"},{"download_url":"https://playmogo.com/d/uz60y3wghha1","single_img":"https://ticdn.net/snaps/wxsn9vw8pyuasklw.jpg","file_code":"uz60y3wghha1","length":"00:39:03","views":"15416","vw_fmt":"15.4K","uploaded":"2023-10-08 12:23:56","up_fmt":"8 Okt 2023","up_short":"8 Okt","title":"Tubuh Ibu Mertuaku Yg Bikin Aku Bernafsu Setiap Hari Lulustream Popstream Telegram","t_esc":"Tubuh Ibu Mertuaku Yg Bikin Aku Bernafsu Setiap Hari Lulustream Popstream Telegram"},{"download_url":"https://playmogo.com/d/wk5fw5ruvc6s","single_img":"https://ticdn.net/snaps/81y4utabzrs8bikz.jpg","file_code":"wk5fw5ruvc6s","length":"00:46:34","views":"3796","vw_fmt":"3.8K","uploaded":"2023-10-08 12:23:55","up_fmt":"8 Okt 2023","up_short":"8 Okt","title":"Tubuh Ibu Mertuaku Yg Bikin Aku Bernafsu Setiap Hari Part Cantik Tobrut","t_esc":"Tubuh Ibu Mertuaku Yg Bikin Aku Bernafsu Setiap Hari Part Cantik Tobrut"},{"download_url":"https://playmogo.com/d/jbelqdxv4w5n","single_img":"https://ticdn.net/snaps/3ynlmxgz2sqctjk9.jpg","file_code":"jbelqdxv4w5n","length":"00:00:42","views":"11859","vw_fmt":"11.9K","uploaded":"2023-10-08 12:23:54","up_fmt":"8 Okt 2023","up_short":"8 Okt","title":"Setubuhi Ibu Tiri Saat Ayah Pergi Dood Stream Doodstream Video Sma Videos","t_esc":"Setubuhi Ibu Tiri Saat Ayah Pergi Dood Stream Doodstream Video Sma Videos"},{"download_url":"https://playmogo.com/d/zz1hvzv9v1wm","single_img":"https://ticdn.net/snaps/phnv2coxgrw6igln.jpg","file_code":"zz1hvzv9v1wm","length":"00:20:01","views":"18646","vw_fmt":"18.6K","uploaded":"2023-10-08 12:23:39","up_fmt":"8 Okt 2023","up_short":"8 Okt","title":"Remaja Binal Yo Minta Di Colmekin Kimcilonly Ratu Bokepsin Bokepind Videos Bokep","t_esc":"Remaja Binal Yo Minta Di Colmekin Kimcilonly Ratu Bokepsin Bokepind Videos Bokep"},{"download_url":"https://playmogo.com/d/dszepi80bq0x","single_img":"https://ticdn.net/snaps/ia112bekzevtlfds.jpg","file_code":"dszepi80bq0x","length":"00:16:43","views":"3343","vw_fmt":"3.3K","uploaded":"2023-10-08 12:23:38","up_fmt":"8 Okt 2023","up_short":"8 Okt","title":"Pasangan Remaja Ml Di Hotel Dood Stream Asupan Viral Dodstream Video Colmek","t_esc":"Pasangan Remaja Ml Di Hotel Dood Stream Asupan Viral Dodstream Video Colmek"},{"download_url":"https://playmogo.com/d/ixd0pqb3ot8q","single_img":"https://ticdn.net/snaps/4s4wofge0bxsmbcu.jpg","file_code":"ixd0pqb3ot8q","length":"00:47:29","views":"1754","vw_fmt":"1.8K","uploaded":"2023-10-08 11:16:38","up_fmt":"8 Okt 2023","up_short":"8 Okt","title":"Tante Live Prank Ojol Ngentot Threesome New Dood Doods Pro Pejuang Lendir","t_esc":"Tante Live Prank Ojol Ngentot Threesome New Dood Doods Pro Pejuang Lendir"},{"download_url":"https://playmogo.com/d/tvg67kok7z66","single_img":"https://ticdn.net/snaps/d5oxfl63u0g5kh3q.jpg","file_code":"tvg67kok7z66","length":"00:02:41","views":"7351","vw_fmt":"7.4K","uploaded":"2023-10-08 11:16:38","up_fmt":"8 Okt 2023","up_short":"8 Okt","title":"Viral Artis Video Bokep Cilbo Xpanas Doostream Bokepin","t_esc":"Viral Artis Video Bokep Cilbo Xpanas Doostream Bokepin"},{"download_url":"https://playmogo.com/d/a9qu9z6v5e3r","single_img":"https://ticdn.net/snaps/rq2cmwjlav8qzrep.jpg","file_code":"a9qu9z6v5e3r","length":"00:01:17","views":"820","vw_fmt":"820","uploaded":"2023-10-08 11:16:38","up_fmt":"8 Okt 2023","up_short":"8 Okt","title":"Viral Twitter Jilbab Disuruh Pacar Nyepong Doods Pro Toketbagus Bochiel Dood Tele","t_esc":"Viral Twitter Jilbab Disuruh Pacar Nyepong Doods Pro Toketbagus Bochiel Dood Tele"},{"download_url":"https://playmogo.com/d/uggicjbkv9md","single_img":"https://ticdn.net/snaps/z171ws3hio5q6s2y.jpg","file_code":"uggicjbkv9md","length":"00:05:39","views":"3194","vw_fmt":"3.2K","uploaded":"2023-10-08 11:16:38","up_fmt":"8 Okt 2023","up_short":"8 Okt","title":"Yang Viral Katanya Kerja Kelompok Padahal Ngentot Pejuang Lendir Popstream Dood Tele","t_esc":"Yang Viral Katanya Kerja Kelompok Padahal Ngentot Pejuang Lendir Popstream Dood Tele"},{"download_url":"https://playmogo.com/d/z5cbktqllevx","single_img":"https://ticdn.net/snaps/1ql3iauqvwh2el46.jpg","file_code":"z5cbktqllevx","length":"00:03:54","views":"9724","vw_fmt":"9.7K","uploaded":"2023-10-08 11:16:38","up_fmt":"8 Okt 2023","up_short":"8 Okt","title":"Viral Pegawai Kai Cantik Tete Mulus Doods Pro Live Website Bochiel Indo","t_esc":"Viral Pegawai Kai Cantik Tete Mulus Doods Pro Live Website Bochiel Indo"},{"download_url":"https://playmogo.com/d/7900px0am8i5","single_img":"https://ticdn.net/snaps/n5k0gn6gsr7hehzk.jpg","file_code":"7900px0am8i5","length":"00:06:04","views":"4258","vw_fmt":"4.3K","uploaded":"2023-10-08 11:16:31","up_fmt":"8 Okt 2023","up_short":"8 Okt","title":"Viral Nyepong Di Sekolah Video Bokep Downloader Pemersatu Cantik Tobrut Cilbo","t_esc":"Viral Nyepong Di Sekolah Video Bokep Downloader Pemersatu Cantik Tobrut Cilbo"},{"download_url":"https://playmogo.com/d/3e6e21zdg819","single_img":"https://ticdn.net/snaps/2w9sfzzvejfq8gc9.jpg","file_code":"3e6e21zdg819","length":"00:01:11","views":"11288","vw_fmt":"11.3K","uploaded":"2023-10-08 11:16:31","up_fmt":"8 Okt 2023","up_short":"8 Okt","title":"Viral Baju Pink Link Web Full Album Telegram Toketbagus Bokepin","t_esc":"Viral Baju Pink Link Web Full Album Telegram Toketbagus Bokepin"},{"download_url":"https://playmogo.com/d/slh4ca5epxd4","single_img":"https://ticdn.net/snaps/56tzv2ed83183v7k.jpg","file_code":"slh4ca5epxd4","length":"00:01:31","views":"7747","vw_fmt":"7.7K","uploaded":"2023-10-08 11:16:31","up_fmt":"8 Okt 2023","up_short":"8 Okt","title":"Rara Nadifa Bokep Fyp Tiktok Viral Video Pekoblive Doodsflix Doodflix","t_esc":"Rara Nadifa Bokep Fyp Tiktok Viral Video Pekoblive Doodsflix Doodflix"},{"download_url":"https://playmogo.com/d/m4ojhvquukcz","single_img":"https://ticdn.net/snaps/le46j3o5ptqk11qj.jpg","file_code":"m4ojhvquukcz","length":"00:03:50","views":"5490","vw_fmt":"5.5K","uploaded":"2023-10-08 11:16:18","up_fmt":"8 Okt 2023","up_short":"8 Okt","title":"Niat Ngintip Malah Dapat Jatah Ngewe Ngentot Memeksiana Bokep Video Terupdate Viral","t_esc":"Niat Ngintip Malah Dapat Jatah Ngewe Ngentot Memeksiana Bokep Video Terupdate Viral"},{"download_url":"https://playmogo.com/d/4qxu4bqadlqp","single_img":"https://ticdn.net/snaps/expx4e7wkqywv24r.jpg","file_code":"4qxu4bqadlqp","length":"00:01:08","views":"6850","vw_fmt":"6.8K","uploaded":"2023-10-08 11:16:17","up_fmt":"8 Okt 2023","up_short":"8 Okt","title":"Jilbab Cantik Polos Kena Paksa Streaming Pekoblive Cilbo Terabox Doodstream","t_esc":"Jilbab Cantik Polos Kena Paksa Streaming Pekoblive Cilbo Terabox Doodstream"},{"download_url":"https://playmogo.com/d/a9m8b65qiyk0","single_img":"https://ticdn.net/snaps/2k290inck5wio5tt.jpg","file_code":"a9m8b65qiyk0","length":"00:36:23","views":"657","vw_fmt":"657","uploaded":"2023-10-08 04:42:02","up_fmt":"8 Okt 2023","up_short":"8 Okt","title":"Ngewe Ojol Mlive Videos Bokep Asupan Viral Lagi Links","t_esc":"Ngewe Ojol Mlive Videos Bokep Asupan Viral Lagi Links"},{"download_url":"https://playmogo.com/d/1uqvyhxfiane","single_img":"https://ticdn.net/snaps/sd2as5ju2t02sccx.jpg","file_code":"1uqvyhxfiane","length":"00:06:07","views":"1237","vw_fmt":"1.2K","uploaded":"2023-10-08 04:41:43","up_fmt":"8 Okt 2023","up_short":"8 Okt","title":"Suami Coli Tante Panlok Bbw Dieue Ojol Sampe Creampie Viral Bokep31 Bokepin","t_esc":"Suami Coli Tante Panlok Bbw Dieue Ojol Sampe Creampie Viral Bokep31 Bokepin"},{"download_url":"https://playmogo.com/d/g6yswtlcxpsn","single_img":"https://ticdn.net/snaps/lhn3mrlfx1n2x96b.jpg","file_code":"g6yswtlcxpsn","length":"00:04:18","views":"557","vw_fmt":"557","uploaded":"2023-10-08 04:41:36","up_fmt":"8 Okt 2023","up_short":"8 Okt","title":"Isep Kontol Gede Gak Mau Crot Dodstream Telegram Doodstream Pejuang Lendir Streaming","t_esc":"Isep Kontol Gede Gak Mau Crot Dodstream Telegram Doodstream Pejuang Lendir Streaming"},{"download_url":"https://playmogo.com/d/84jj1413wg8b","single_img":"https://ticdn.net/snaps/ssppm04pb8k6mza9.jpg","file_code":"84jj1413wg8b","length":"00:02:51","views":"1241","vw_fmt":"1.2K","uploaded":"2023-10-08 04:41:36","up_fmt":"8 Okt 2023","up_short":"8 Okt","title":"Disuruh Isep Kontol Ceweknya Gak Mau Live Jilbab Memeksiana Cilbo Pekoblive","t_esc":"Disuruh Isep Kontol Ceweknya Gak Mau Live Jilbab Memeksiana Cilbo Pekoblive"},{"download_url":"https://playmogo.com/d/i4d4q09mum7w","single_img":"https://ticdn.net/snaps/qizngrrdqywdm9ao.jpg","file_code":"i4d4q09mum7w","length":"00:00:45","views":"2610","vw_fmt":"2.6K","uploaded":"2023-10-08 04:41:36","up_fmt":"8 Okt 2023","up_short":"8 Okt","title":"Dipaksa Pacar Isep Kontol Sampai Muncrat Toketbagus Bokepsatset Dodstream Link Web Cantik","t_esc":"Dipaksa Pacar Isep Kontol Sampai Muncrat Toketbagus Bokepsatset Dodstream Link Web Cantik"},{"download_url":"https://playmogo.com/d/elu2lg7elj2j","single_img":"https://ticdn.net/snaps/z2u7rg1ho0hd52jq.jpg","file_code":"elu2lg7elj2j","length":"00:50:00","views":"1412","vw_fmt":"1.4K","uploaded":"2023-10-08 04:41:36","up_fmt":"8 Okt 2023","up_short":"8 Okt","title":"Ega Prank Ojol New Downloader Poophd Simintok Pekoblive Update","t_esc":"Ega Prank Ojol New Downloader Poophd Simintok Pekoblive Update"},{"download_url":"https://playmogo.com/d/duboxmwzleby","single_img":"https://ticdn.net/snaps/vtt0p8mqa404va4a.jpg","file_code":"duboxmwzleby","length":"00:08:03","views":"1350","vw_fmt":"1.4K","uploaded":"2023-10-08 04:41:31","up_fmt":"8 Okt 2023","up_short":"8 Okt","title":"Hijab Disuruh Kulum Kontol Terus Dalam Mobil Live Video Indo Doodstreem Twitter","t_esc":"Hijab Disuruh Kulum Kontol Terus Dalam Mobil Live Video Indo Doodstreem Twitter"},{"download_url":"https://playmogo.com/d/p92fzq0v0mex","single_img":"https://ticdn.net/snaps/32v2qcpld9e0o1u9.jpg","file_code":"p92fzq0v0mex","length":"00:04:15","views":"593","vw_fmt":"593","uploaded":"2023-10-08 04:41:31","up_fmt":"8 Okt 2023","up_short":"8 Okt","title":"Pernah Viral Abg Jilbab Main Dipondok Dood Tele Video Colmek Links Bokep","t_esc":"Pernah Viral Abg Jilbab Main Dipondok Dood Tele Video Colmek Links Bokep"},{"download_url":"https://playmogo.com/d/0uwueabrj67i","single_img":"https://ticdn.net/snaps/thyos9i5nj0q94kv.jpg","file_code":"0uwueabrj67i","length":"00:00:58","views":"2308","vw_fmt":"2.3K","uploaded":"2023-10-08 04:41:31","up_fmt":"8 Okt 2023","up_short":"8 Okt","title":"Hijab Cantik Yg Lagi Viral Asupan Bokepsatset Bokepin Tobrut Bokep","t_esc":"Hijab Cantik Yg Lagi Viral Asupan Bokepsatset Bokepin Tobrut Bokep"},{"download_url":"https://playmogo.com/d/mobjingbbzmp","single_img":"https://ticdn.net/snaps/97br078jn5ghr0wp.jpg","file_code":"mobjingbbzmp","length":"00:01:05","views":"1682","vw_fmt":"1.7K","uploaded":"2023-10-08 04:41:27","up_fmt":"8 Okt 2023","up_short":"8 Okt","title":"Desahan Nikmat Jilbab Saat Ngentot Staklam Tele Pejuang Lendir Video Viral","t_esc":"Desahan Nikmat Jilbab Saat Ngentot Staklam Tele Pejuang Lendir Video Viral"},{"download_url":"https://playmogo.com/d/igtgstmfrom5","single_img":"https://ticdn.net/snaps/s02ro4a42hlnyxd1.jpg","file_code":"igtgstmfrom5","length":"00:03:50","views":"1428","vw_fmt":"1.4K","uploaded":"2023-10-08 04:41:27","up_fmt":"8 Okt 2023","up_short":"8 Okt","title":"Cewek Hijab Ngemut Kontol Di Ruang Ganti Baju Bokepsin Telegram Bokep Update","t_esc":"Cewek Hijab Ngemut Kontol Di Ruang Ganti Baju Bokepsin Telegram Bokep Update"},{"download_url":"https://playmogo.com/d/5xqbw68eee21","single_img":"https://ticdn.net/snaps/k4j9ywwsglquxrjt.jpg","file_code":"5xqbw68eee21","length":"00:03:49","views":"863","vw_fmt":"863","uploaded":"2023-10-08 04:41:23","up_fmt":"8 Okt 2023","up_short":"8 Okt","title":"Abg Bule Semprot Di Luar Jilbab Lagi Viral Cantik Tobrut Doodstream Dood","t_esc":"Abg Bule Semprot Di Luar Jilbab Lagi Viral Cantik Tobrut Doodstream Dood"},{"download_url":"https://playmogo.com/d/bpyy7ilvsqwi","single_img":"https://ticdn.net/snaps/o29kvffw1uilm04g.jpg","file_code":"bpyy7ilvsqwi","length":"00:02:15","views":"9481","vw_fmt":"9.5K","uploaded":"2023-10-08 04:41:23","up_fmt":"8 Okt 2023","up_short":"8 Okt","title":"Arachu Ngewe Pertama Kali Sama Pacar Staklam Lokal Update Ful Album Video","t_esc":"Arachu Ngewe Pertama Kali Sama Pacar Staklam Lokal Update Ful Album Video"},{"download_url":"https://playmogo.com/d/ueluavbfpdl7","single_img":"https://ticdn.net/snaps/02vge5t2bwly7qwa.jpg","file_code":"ueluavbfpdl7","length":"00:06:49","views":"29649","vw_fmt":"29.6K","uploaded":"2023-10-08 04:41:19","up_fmt":"8 Okt 2023","up_short":"8 Okt","title":"Nekat Ngentotin Stw Pemilik Warung Dood Jilbab Doodsflix Toketbagus Cantik Tobrut","t_esc":"Nekat Ngentotin Stw Pemilik Warung Dood Jilbab Doodsflix Toketbagus Cantik Tobrut"},{"download_url":"https://playmogo.com/d/701rw18tcr97","single_img":"https://ticdn.net/snaps/y2xxlqxy9as3bxz4.jpg","file_code":"701rw18tcr97","length":"00:03:09","views":"1025","vw_fmt":"1.0K","uploaded":"2023-10-08 04:41:19","up_fmt":"8 Okt 2023","up_short":"8 Okt","title":"Me Llisa Mahasiswi Uph Lg Nyepong Cantik Tobrut Twitter Lagi Viral Doodsflix","t_esc":"Me Llisa Mahasiswi Uph Lg Nyepong Cantik Tobrut Twitter Lagi Viral Doodsflix"},{"download_url":"https://playmogo.com/d/fbxrf5kzg4y0","single_img":"https://ticdn.net/snaps/v51e3rc02duboxql.jpg","file_code":"fbxrf5kzg4y0","length":"00:01:38","views":"1352","vw_fmt":"1.4K","uploaded":"2023-10-08 04:41:19","up_fmt":"8 Okt 2023","up_short":"8 Okt","title":"Ceweknya Males Disuruh Nyepong Indonesia Bochiel Asupan Bokepind Doods Pro","t_esc":"Ceweknya Males Disuruh Nyepong Indonesia Bochiel Asupan Bokepind Doods Pro"},{"download_url":"https://playmogo.com/d/baojeqje8rni","single_img":"https://ticdn.net/snaps/ekcdst6zuhslngjt.jpg","file_code":"baojeqje8rni","length":"00:00:45","views":"1378","vw_fmt":"1.4K","uploaded":"2023-10-08 04:41:19","up_fmt":"8 Okt 2023","up_short":"8 Okt","title":"Bos Dan Karyawan Konter Jilbab Bokepind Links Bokepin Popstream","t_esc":"Bos Dan Karyawan Konter Jilbab Bokepind Links Bokepin Popstream"},{"download_url":"https://playmogo.com/d/npaozd46420n","single_img":"https://ticdn.net/snaps/gmqs9339eg76bznn.jpg","file_code":"npaozd46420n","length":"00:01:31","views":"1071","vw_fmt":"1.1K","uploaded":"2023-10-08 04:41:05","up_fmt":"8 Okt 2023","up_short":"8 Okt","title":"Disepongin Cewek Berkerudung Di Mobil Full Album Bokepsin Jilbab Video Colmek Indo","t_esc":"Disepongin Cewek Berkerudung Di Mobil Full Album Bokepsin Jilbab Video Colmek Indo"},{"download_url":"https://playmogo.com/d/omqpo1xjpx72","single_img":"https://ticdn.net/snaps/z1w4a6jqzf1men17.jpg","file_code":"omqpo1xjpx72","length":"00:01:12","views":"2630","vw_fmt":"2.6K","uploaded":"2023-10-08 04:41:05","up_fmt":"8 Okt 2023","up_short":"8 Okt","title":"Abg Jilbab Goyangannya Mantap Mendesah Keenakan Video Bokep Sotwe Indo Website Doodflix","t_esc":"Abg Jilbab Goyangannya Mantap Mendesah Keenakan Video Bokep Sotwe Indo Website Doodflix"},{"download_url":"https://playmogo.com/d/tmpqpd6pq6op","single_img":"https://ticdn.net/snaps/avk0fmx04jf0jnv5.jpg","file_code":"tmpqpd6pq6op","length":"00:01:05","views":"2393","vw_fmt":"2.4K","uploaded":"2023-10-08 04:41:05","up_fmt":"8 Okt 2023","up_short":"8 Okt","title":"Viral Tukang Parkir Menang Banyak Dapat Colmek Gratis Lagi Lulustream Tele Terabox","t_esc":"Viral Tukang Parkir Menang Banyak Dapat Colmek Gratis Lagi Lulustream Tele Terabox"},{"download_url":"https://playmogo.com/d/87kvcphjbkcr","single_img":"https://ticdn.net/snaps/bhq0p5x93ehl6jmj.jpg","file_code":"87kvcphjbkcr","length":"00:01:38","views":"713","vw_fmt":"713","uploaded":"2023-10-08 04:40:56","up_fmt":"8 Okt 2023","up_short":"8 Okt","title":"Jilbab Isep Kontol Papa Tiri Video Sma Cantik Tobrut Simintok Lokal Twitter","t_esc":"Jilbab Isep Kontol Papa Tiri Video Sma Cantik Tobrut Simintok Lokal Twitter"},{"download_url":"https://playmogo.com/d/cd1djxs9xvjk","single_img":"https://ticdn.net/snaps/8vkjxjqts4myy705.jpg","file_code":"cd1djxs9xvjk","length":"00:00:13","views":"1946","vw_fmt":"1.9K","uploaded":"2023-10-08 04:40:56","up_fmt":"8 Okt 2023","up_short":"8 Okt","title":"Jilbab Hitam Kena Crot Dimuka Lulustream Ngentot Toketbagus Full Album Tele","t_esc":"Jilbab Hitam Kena Crot Dimuka Lulustream Ngentot Toketbagus Full Album Tele"},{"download_url":"https://playmogo.com/d/4yum3fv9wld1","single_img":"https://ticdn.net/snaps/8sp27leilmn3a5q6.jpg","file_code":"4yum3fv9wld1","length":"00:01:42","views":"1062","vw_fmt":"1.1K","uploaded":"2023-10-08 04:40:56","up_fmt":"8 Okt 2023","up_short":"8 Okt","title":"Jilbab Biru Disuruh Kulum Peler Dalam Mobil Tele Toketbagus Doodsflix Simintok","t_esc":"Jilbab Biru Disuruh Kulum Peler Dalam Mobil Tele Toketbagus Doodsflix Simintok"},{"download_url":"https://playmogo.com/d/grin9oyi1ivi","single_img":"https://ticdn.net/snaps/x6h097pue3zclod2.jpg","file_code":"grin9oyi1ivi","length":"00:01:15","views":"708","vw_fmt":"708","uploaded":"2023-10-08 04:40:56","up_fmt":"8 Okt 2023","up_short":"8 Okt","title":"Hijab Nyepong Crot Dalem Mobil Tele Doodstream Doodflix Video Sma Links","t_esc":"Hijab Nyepong Crot Dalem Mobil Tele Doodstream Doodflix Video Sma Links"},{"download_url":"https://playmogo.com/d/a2kcom2ftavz","single_img":"https://ticdn.net/snaps/kxkse2g6oxvnz9hr.jpg","file_code":"a2kcom2ftavz","length":"00:03:55","views":"1687","vw_fmt":"1.7K","uploaded":"2023-10-08 04:40:49","up_fmt":"8 Okt 2023","up_short":"8 Okt","title":"Ustazah Sepongin Kontol Crot Dimulut Asupan Viral Video Indo Bokepsin Dood Bokep","t_esc":"Ustazah Sepongin Kontol Crot Dimulut Asupan Viral Video Indo Bokepsin Dood Bokep"},{"download_url":"https://playmogo.com/d/dsaljketuhcd","single_img":"https://ticdn.net/snaps/982x5jw2yskjbq5i.jpg","file_code":"dsaljketuhcd","length":"00:00:41","views":"2103","vw_fmt":"2.1K","uploaded":"2023-10-08 04:40:49","up_fmt":"8 Okt 2023","up_short":"8 Okt","title":"Ustazah Juga Ternyata Doyan Kulum Kontol Doodstreem Bokep31 Ful Album Indonesia Asupan","t_esc":"Ustazah Juga Ternyata Doyan Kulum Kontol Doodstreem Bokep31 Ful Album Indonesia Asupan"},{"download_url":"https://playmogo.com/d/urmtihgd08r8","single_img":"https://ticdn.net/snaps/w1uls7i8zehj2yn7.jpg","file_code":"urmtihgd08r8","length":"00:00:30","views":"1182","vw_fmt":"1.2K","uploaded":"2023-10-08 04:40:49","up_fmt":"8 Okt 2023","up_short":"8 Okt","title":"Jilbab Smp Isep Batang Kontol Gede Doodflix Terupdate Telegram Doodstream Ngentot","t_esc":"Jilbab Smp Isep Batang Kontol Gede Doodflix Terupdate Telegram Doodstream Ngentot"},{"download_url":"https://playmogo.com/d/l4vexbsvteay","single_img":"https://ticdn.net/snaps/dtpngeguuv0wb57l.jpg","file_code":"l4vexbsvteay","length":"00:00:38","views":"358","vw_fmt":"358","uploaded":"2023-10-08 04:40:35","up_fmt":"8 Okt 2023","up_short":"8 Okt","title":"Anggraini Wahyudi Jilbab Bj Update Pemersatu Pejuang Lendir Bokep Simontok","t_esc":"Anggraini Wahyudi Jilbab Bj Update Pemersatu Pejuang Lendir Bokep Simontok"},{"download_url":"https://playmogo.com/d/q8u116tspwbv","single_img":"https://ticdn.net/snaps/7bhuwblg42t33hlm.jpg","file_code":"q8u116tspwbv","length":"00:01:18","views":"1358","vw_fmt":"1.4K","uploaded":"2023-10-08 04:40:25","up_fmt":"8 Okt 2023","up_short":"8 Okt","title":"Hijab Nyepong Keluar Dimulut Lagi Viral Video Indo Tobrut Terabox Staklam","t_esc":"Hijab Nyepong Keluar Dimulut Lagi Viral Video Indo Tobrut Terabox Staklam"},{"download_url":"https://playmogo.com/d/jcedwxrrvg5t","single_img":"https://ticdn.net/snaps/bj0wfsbyaur5fg3m.jpg","file_code":"jcedwxrrvg5t","length":"00:00:30","views":"463","vw_fmt":"463","uploaded":"2023-10-08 04:40:07","up_fmt":"8 Okt 2023","up_short":"8 Okt","title":"Jablay Berhijab Suka Emut Peler Video Colmek Doostream Indo Pekoblive Yakwad","t_esc":"Jablay Berhijab Suka Emut Peler Video Colmek Doostream Indo Pekoblive Yakwad"},{"download_url":"https://playmogo.com/d/zhgbypttwvbk","single_img":"https://ticdn.net/snaps/dtlafdazok24wj4v.jpg","file_code":"zhgbypttwvbk","length":"00:00:46","views":"1243","vw_fmt":"1.2K","uploaded":"2023-10-08 04:39:57","up_fmt":"8 Okt 2023","up_short":"8 Okt","title":"Jilbab Bj Pelan Tapi Pasti New Video Sma Indonesia Ful Album Xpanas","t_esc":"Jilbab Bj Pelan Tapi Pasti New Video Sma Indonesia Ful Album Xpanas"},{"download_url":"https://playmogo.com/d/0defwpxvylcx","single_img":"https://ticdn.net/snaps/qsmvmfdqdtbcnq78.jpg","file_code":"0defwpxvylcx","length":"00:14:35","views":"517","vw_fmt":"517","uploaded":"2023-10-08 04:39:57","up_fmt":"8 Okt 2023","up_short":"8 Okt","title":"Jilbab Biru Suka Sepong New Update Folder Doodflix Indonesia","t_esc":"Jilbab Biru Suka Sepong New Update Folder Doodflix Indonesia"},{"download_url":"https://playmogo.com/d/vzh2f8uknsfb","single_img":"https://ticdn.net/snaps/c27t36j4r90ni366.jpg","file_code":"vzh2f8uknsfb","length":"00:04:21","views":"1643","vw_fmt":"1.6K","uploaded":"2023-10-08 04:39:43","up_fmt":"8 Okt 2023","up_short":"8 Okt","title":"Jilbab Hitam Isep Kontol Bule New Video Sma Telegram Ngentot Popstream Bokepsin","t_esc":"Jilbab Hitam Isep Kontol Bule New Video Sma Telegram Ngentot Popstream Bokepsin"},{"download_url":"https://playmogo.com/d/k3zdxn1t2ppa","single_img":"https://ticdn.net/snaps/nbxqo94isf2eb96s.jpg","file_code":"k3zdxn1t2ppa","length":"00:02:20","views":"2823","vw_fmt":"2.8K","uploaded":"2023-10-08 04:39:27","up_fmt":"8 Okt 2023","up_short":"8 Okt","title":"Sepongan Jilbab Binor Yakwad Terabox Pemersatu Viral Ful Album","t_esc":"Sepongan Jilbab Binor Yakwad Terabox Pemersatu Viral Ful Album"},{"download_url":"https://playmogo.com/d/42ha3us7kiy6","single_img":"https://ticdn.net/snaps/zzdha6naoksmx4c1.jpg","file_code":"42ha3us7kiy6","length":"00:01:29","views":"463","vw_fmt":"463","uploaded":"2023-10-08 04:39:23","up_fmt":"8 Okt 2023","up_short":"8 Okt","title":"Hijab Muslim Emut Peler Di Mobil Doods Pro Dodstream Popstream Bokep","t_esc":"Hijab Muslim Emut Peler Di Mobil Doods Pro Dodstream Popstream Bokep"},{"download_url":"https://playmogo.com/d/lfjep4x8m7mq","single_img":"https://ticdn.net/snaps/0mdwoyhxizdmibc2.jpg","file_code":"lfjep4x8m7mq","length":"00:00:53","views":"892","vw_fmt":"892","uploaded":"2023-10-08 04:39:12","up_fmt":"8 Okt 2023","up_short":"8 Okt","title":"Jilbab Bj Yang Lagi Viral Nih Bokepsin Doods Pro Video Dood Tele","t_esc":"Jilbab Bj Yang Lagi Viral Nih Bokepsin Doods Pro Video Dood Tele"},{"download_url":"https://playmogo.com/d/5ykoixk212i4","single_img":"https://ticdn.net/snaps/yymtddvihjwnrwh8.jpg","file_code":"5ykoixk212i4","length":"00:01:50","views":"1308","vw_fmt":"1.3K","uploaded":"2023-10-08 04:39:12","up_fmt":"8 Okt 2023","up_short":"8 Okt","title":"Nenen Sama Pacar Jilbab Links Video Viral Indonesia Bebasindo","t_esc":"Nenen Sama Pacar Jilbab Links Video Viral Indonesia Bebasindo"},{"download_url":"https://playmogo.com/d/h78gywz8im2f","single_img":"https://ticdn.net/snaps/e64ufnjq08zcn949.jpg","file_code":"h78gywz8im2f","length":"00:00:18","views":"262","vw_fmt":"262","uploaded":"2023-10-08 04:39:12","up_fmt":"8 Okt 2023","up_short":"8 Okt","title":"Jilbab Pamer Belahan Toket Links Viral Video Colmek Terupdate","t_esc":"Jilbab Pamer Belahan Toket Links Viral Video Colmek Terupdate"},{"download_url":"https://playmogo.com/d/cjkm0412o3rs","single_img":"https://ticdn.net/snaps/xsa377u7650p1biw.jpg","file_code":"cjkm0412o3rs","length":"00:02:05","views":"1423","vw_fmt":"1.4K","uploaded":"2023-10-08 04:39:02","up_fmt":"8 Okt 2023","up_short":"8 Okt","title":"Anak Pramuka Di Hukum Nyepong Kontol Kakak Pembina Video Viral Terupdate Link","t_esc":"Anak Pramuka Di Hukum Nyepong Kontol Kakak Pembina Video Viral Terupdate Link"},{"download_url":"https://playmogo.com/d/zliasrvoxsgf","single_img":"https://ticdn.net/snaps/o37vc6npn5wz1oiz.jpg","file_code":"zliasrvoxsgf","length":"00:00:41","views":"4553","vw_fmt":"4.6K","uploaded":"2023-10-08 04:39:02","up_fmt":"8 Okt 2023","up_short":"8 Okt","title":"Anak Pramuka Nyasar Malah Di Jilmek Bochiel Bokepsin Telegram Doodstreem Viral","t_esc":"Anak Pramuka Nyasar Malah Di Jilmek Bochiel Bokepsin Telegram Doodstreem Viral"},{"download_url":"https://playmogo.com/d/u82vx9jjlpm1","single_img":"https://ticdn.net/snaps/44mu1cu9lnvekg7f.jpg","file_code":"u82vx9jjlpm1","length":"00:06:04","views":"2472","vw_fmt":"2.5K","uploaded":"2023-10-08 04:39:02","up_fmt":"8 Okt 2023","up_short":"8 Okt","title":"Selebgram Di Ewe Jamet Lulustream Twitter Bokep Dood Bochiel Links","t_esc":"Selebgram Di Ewe Jamet Lulustream Twitter Bokep Dood Bochiel Links"},{"download_url":"https://playmogo.com/d/2grcd5x2s4iu","single_img":"https://ticdn.net/snaps/rvm985n3ctfyijae.jpg","file_code":"2grcd5x2s4iu","length":"00:04:27","views":"3383","vw_fmt":"3.4K","uploaded":"2023-10-08 04:39:02","up_fmt":"8 Okt 2023","up_short":"8 Okt","title":"Kompilasi Video Viral Tiktokers Inshira Vieta Pekoblive Twitter Toketbagus Bokepin Bokepind","t_esc":"Kompilasi Video Viral Tiktokers Inshira Vieta Pekoblive Twitter Toketbagus Bokepin Bokepind"},{"download_url":"https://playmogo.com/d/qhy1z91n2wjb","single_img":"https://ticdn.net/snaps/6lwas1a1my162h75.jpg","file_code":"qhy1z91n2wjb","length":"00:03:05","views":"2267","vw_fmt":"2.3K","uploaded":"2023-10-08 04:38:47","up_fmt":"8 Okt 2023","up_short":"8 Okt","title":"Bokep Viral Pak Guru Sodok Memek Jilbab Pramuka Di Kosan Dood Bokepsin","t_esc":"Bokep Viral Pak Guru Sodok Memek Jilbab Pramuka Di Kosan Dood Bokepsin"},{"download_url":"https://playmogo.com/d/06rmazfujbnz","single_img":"https://ticdn.net/snaps/rp6ytlzcarsmgofl.jpg","file_code":"06rmazfujbnz","length":"00:00:37","views":"1454","vw_fmt":"1.5K","uploaded":"2023-10-08 04:38:47","up_fmt":"8 Okt 2023","up_short":"8 Okt","title":"Davina Novira Viral Tiktok Simintok Lagi Live Bokepin","t_esc":"Davina Novira Viral Tiktok Simintok Lagi Live Bokepin"},{"download_url":"https://playmogo.com/d/pu9khlwwi74q","single_img":"https://ticdn.net/snaps/1qaoy9ceb9y1kwxt.jpg","file_code":"pu9khlwwi74q","length":"00:11:31","views":"2011","vw_fmt":"2.0K","uploaded":"2023-10-08 04:38:36","up_fmt":"8 Okt 2023","up_short":"8 Okt","title":"Meruchan Full Doodsflix Bokepsin Lokal Downloader Dodstream","t_esc":"Meruchan Full Doodsflix Bokepsin Lokal Downloader Dodstream"},{"download_url":"https://playmogo.com/d/pnd1wi60401x","single_img":"https://ticdn.net/snaps/8yh05wshlt7b0d2l.jpg","file_code":"pnd1wi60401x","length":"00:06:38","views":"742","vw_fmt":"742","uploaded":"2023-10-08 04:38:36","up_fmt":"8 Okt 2023","up_short":"8 Okt","title":"Siswi Sma Main Sama Teman Crot Didalam Bebasindo Indo Simontok Website Bokep","t_esc":"Siswi Sma Main Sama Teman Crot Didalam Bebasindo Indo Simontok Website Bokep"},{"download_url":"https://playmogo.com/d/qfalnlhifp53","single_img":"https://ticdn.net/snaps/xr5n5nehov4ke1ax.jpg","file_code":"qfalnlhifp53","length":"00:01:05","views":"2601","vw_fmt":"2.6K","uploaded":"2023-10-08 04:38:36","up_fmt":"8 Okt 2023","up_short":"8 Okt","title":"Bolos Sekolah Siswi Smp Ngeseks Dikamar Xpanas Link Web Doodstream Tiktok Popstream","t_esc":"Bolos Sekolah Siswi Smp Ngeseks Dikamar Xpanas Link Web Doodstream Tiktok Popstream"},{"download_url":"https://playmogo.com/d/fbxhyh9ophzf","single_img":"https://ticdn.net/snaps/0iueld9huzosk2ee.jpg","file_code":"fbxhyh9ophzf","length":"00:09:54","views":"1474","vw_fmt":"1.5K","uploaded":"2023-10-08 04:38:31","up_fmt":"8 Okt 2023","up_short":"8 Okt","title":"Viral Video Ayu Tocil From Nganjuk Streaming Pemersatu Simintok Doods Pro Simontok","t_esc":"Viral Video Ayu Tocil From Nganjuk Streaming Pemersatu Simintok Doods Pro Simontok"},{"download_url":"https://playmogo.com/d/67aospd41cl6","single_img":"https://ticdn.net/snaps/71hvx38n81al1ocd.jpg","file_code":"67aospd41cl6","length":"00:02:08","views":"4533","vw_fmt":"4.5K","uploaded":"2023-10-08 04:38:31","up_fmt":"8 Okt 2023","up_short":"8 Okt","title":"Viral Video Anak Gadis Ngewe Sama Ayah Kandung Twitter Dodstream Popstream Dood","t_esc":"Viral Video Anak Gadis Ngewe Sama Ayah Kandung Twitter Dodstream Popstream Dood"},{"download_url":"https://playmogo.com/d/picjevnpcgmi","single_img":"https://ticdn.net/snaps/du1n4mkxrekb79nt.jpg","file_code":"picjevnpcgmi","length":"00:05:32","views":"3515","vw_fmt":"3.5K","uploaded":"2023-10-08 04:38:31","up_fmt":"8 Okt 2023","up_short":"8 Okt","title":"Open Bo Ngentotnya Kok Dikebun Pisang Bokep31 Bokep Video Memeksiana Viral Indo","t_esc":"Open Bo Ngentotnya Kok Dikebun Pisang Bokep31 Bokep Video Memeksiana Viral Indo"},{"download_url":"https://playmogo.com/d/2p4vgx11lcrb","single_img":"https://ticdn.net/snaps/mnh4wxzdybthft8w.jpg","file_code":"2p4vgx11lcrb","length":"00:01:00","views":"1715","vw_fmt":"1.7K","uploaded":"2023-10-08 04:38:31","up_fmt":"8 Okt 2023","up_short":"8 Okt","title":"Kuli Bangunan Perkosa Anak Sma Streaming Tobrut Lagi Viral Staklam Jilbab","t_esc":"Kuli Bangunan Perkosa Anak Sma Streaming Tobrut Lagi Viral Staklam Jilbab"},{"download_url":"https://playmogo.com/d/ajwkamkx30pd","single_img":"https://ticdn.net/snaps/xze9jew428rr894f.jpg","file_code":"ajwkamkx30pd","length":"00:02:20","views":"1656","vw_fmt":"1.7K","uploaded":"2023-10-08 04:38:31","up_fmt":"8 Okt 2023","up_short":"8 Okt","title":"Mirip Artis Jessica Iskandar Poophd Viral Lokal Streaming","t_esc":"Mirip Artis Jessica Iskandar Poophd Viral Lokal Streaming"},{"download_url":"https://playmogo.com/d/ba9p4i5awrn9","single_img":"https://ticdn.net/snaps/2hc9g02b16lw9l24.jpg","file_code":"ba9p4i5awrn9","length":"00:00:58","views":"2521","vw_fmt":"2.5K","uploaded":"2023-10-08 04:38:27","up_fmt":"8 Okt 2023","up_short":"8 Okt","title":"Goyangan Pantat Bikin Ngilu Bebasindo Twitter Bokepsatset Doodflix Dood","t_esc":"Goyangan Pantat Bikin Ngilu Bebasindo Twitter Bokepsatset Doodflix Dood"},{"download_url":"https://playmogo.com/d/tm52g1d7ap78","single_img":"https://ticdn.net/snaps/gbpxfko73ldz33hg.jpg","file_code":"tm52g1d7ap78","length":"00:01:37","views":"1086","vw_fmt":"1.1K","uploaded":"2023-10-08 04:38:18","up_fmt":"8 Okt 2023","up_short":"8 Okt","title":"Abg Bandung Omeg Pkai Timun Video Bokep Pemersatu Live Lagi Viral Links","t_esc":"Abg Bandung Omeg Pkai Timun Video Bokep Pemersatu Live Lagi Viral Links"},{"download_url":"https://playmogo.com/d/vsrvtombl7tr","single_img":"https://ticdn.net/snaps/b3uxjseqreuo2sbb.jpg","file_code":"vsrvtombl7tr","length":"00:05:43","views":"392","vw_fmt":"392","uploaded":"2023-10-08 04:38:18","up_fmt":"8 Okt 2023","up_short":"8 Okt","title":"Ngewe Sambil Ngerokok Biar Pacar Yang Goyang Bokep Doodsflix Video Indo Pekoblive","t_esc":"Ngewe Sambil Ngerokok Biar Pacar Yang Goyang Bokep Doodsflix Video Indo Pekoblive"},{"download_url":"https://playmogo.com/d/jvxsxagxauor","single_img":"https://ticdn.net/snaps/j5hhedq9u392ctm5.jpg","file_code":"jvxsxagxauor","length":"00:05:48","views":"1482","vw_fmt":"1.5K","uploaded":"2023-10-08 04:38:13","up_fmt":"8 Okt 2023","up_short":"8 Okt","title":"Disepongin Sama Kakak Ipar Terabox Tobrut Simintok Bokepin Video Bokep","t_esc":"Disepongin Sama Kakak Ipar Terabox Tobrut Simintok Bokepin Video Bokep"},{"download_url":"https://playmogo.com/d/5ug0n2nytt7c","single_img":"https://ticdn.net/snaps/rjpsi92x29w6x3pn.jpg","file_code":"5ug0n2nytt7c","length":"00:01:10","views":"828","vw_fmt":"828","uploaded":"2023-10-08 04:38:09","up_fmt":"8 Okt 2023","up_short":"8 Okt","title":"Masih Smp Udah Pengalaman Emut Peler Downloader Pejuang Lendir Bokepsin Sotwe Video","t_esc":"Masih Smp Udah Pengalaman Emut Peler Downloader Pejuang Lendir Bokepsin Sotwe Video"},{"download_url":"https://playmogo.com/d/qgstz59igahe","single_img":"https://ticdn.net/snaps/a7wg6x3i9ow0pku5.jpg","file_code":"qgstz59igahe","length":"00:01:00","views":"466","vw_fmt":"466","uploaded":"2023-10-08 04:38:05","up_fmt":"8 Okt 2023","up_short":"8 Okt","title":"Ngocokin Kontol Pacar Xpanas Bokepsin Telegram Doods Pro","t_esc":"Ngocokin Kontol Pacar Xpanas Bokepsin Telegram Doods Pro"},{"download_url":"https://playmogo.com/d/oj78644yo6vc","single_img":"https://ticdn.net/snaps/lkvimq40ubwuzdse.jpg","file_code":"oj78644yo6vc","length":"00:02:00","views":"1277","vw_fmt":"1.3K","uploaded":"2023-10-08 04:38:01","up_fmt":"8 Okt 2023","up_short":"8 Okt","title":"Paksa Nyepong Pacar Muncrat Dimuka Popstream Twitter Links Terupdate Bokepin","t_esc":"Paksa Nyepong Pacar Muncrat Dimuka Popstream Twitter Links Terupdate Bokepin"},{"download_url":"https://playmogo.com/d/cr6rywm1p1rg","single_img":"https://ticdn.net/snaps/vr2jqsahz7q0595f.jpg","file_code":"cr6rywm1p1rg","length":"00:01:55","views":"2721","vw_fmt":"2.7K","uploaded":"2023-10-08 04:38:01","up_fmt":"8 Okt 2023","up_short":"8 Okt","title":"Open Bo Boleh Cek Dulu Sblm Bayar Indo Asupan Website Yakwad Bokepsin","t_esc":"Open Bo Boleh Cek Dulu Sblm Bayar Indo Asupan Website Yakwad Bokepsin"},{"download_url":"https://playmogo.com/d/wfjsspkuty3u","single_img":"https://ticdn.net/snaps/ml2apmelze9zjnec.jpg","file_code":"wfjsspkuty3u","length":"00:02:20","views":"1487","vw_fmt":"1.5K","uploaded":"2023-10-08 04:37:19","up_fmt":"8 Okt 2023","up_short":"8 Okt","title":"Beli Rokok Bayar Pakai Kontol Pejuang Lendir Simontok Bochiel Pekoblive Lokal","t_esc":"Beli Rokok Bayar Pakai Kontol Pejuang Lendir Simontok Bochiel Pekoblive Lokal"},{"download_url":"https://playmogo.com/d/cn7a1dcb76g6","single_img":"https://ticdn.net/snaps/q3gzjhbvy7tx4505.jpg","file_code":"cn7a1dcb76g6","length":"00:02:16","views":"2100","vw_fmt":"2.1K","uploaded":"2023-10-08 04:37:19","up_fmt":"8 Okt 2023","up_short":"8 Okt","title":"Dianal Sama Suami Sampai Nyebut Downloader Telegram Jilbab Terabox Bochiel","t_esc":"Dianal Sama Suami Sampai Nyebut Downloader Telegram Jilbab Terabox Bochiel"},{"download_url":"https://playmogo.com/d/ltb7jy2w8qk2","single_img":"https://ticdn.net/snaps/5qrwbp3z6n5x4uxk.jpg","file_code":"ltb7jy2w8qk2","length":"00:03:00","views":"1344","vw_fmt":"1.3K","uploaded":"2023-10-08 04:37:15","up_fmt":"8 Okt 2023","up_short":"8 Okt","title":"Jilbab Malaysia Viral Doodstream Downloader Ngentot Streaming Memeksiana","t_esc":"Jilbab Malaysia Viral Doodstream Downloader Ngentot Streaming Memeksiana"},{"download_url":"https://playmogo.com/d/7szd7wcds0ux","single_img":"https://ticdn.net/snaps/qy4qdbvwg82rhgic.jpg","file_code":"7szd7wcds0ux","length":"00:00:06","views":"2375","vw_fmt":"2.4K","uploaded":"2023-10-08 04:37:10","up_fmt":"8 Okt 2023","up_short":"8 Okt","title":"Nyepong Kontol Muncratin Sperma Dimulut Pekoblive Video Colmek Asupan Indo Viral","t_esc":"Nyepong Kontol Muncratin Sperma Dimulut Pekoblive Video Colmek Asupan Indo Viral"},{"download_url":"https://playmogo.com/d/r9ejjv8wy8x9","single_img":"https://ticdn.net/snaps/se9uhbv4i9z6qo7h.jpg","file_code":"r9ejjv8wy8x9","length":"00:12:57","views":"1351","vw_fmt":"1.4K","uploaded":"2023-10-08 04:37:10","up_fmt":"8 Okt 2023","up_short":"8 Okt","title":"Ceweknya Bilang Cepet Keluarin Jangan Ditahan Bokep Video Viral Popstream Full Album","t_esc":"Ceweknya Bilang Cepet Keluarin Jangan Ditahan Bokep Video Viral Popstream Full Album"},{"download_url":"https://playmogo.com/d/ra7utowwd5vm","single_img":"https://ticdn.net/snaps/c3xo0bbfo8hxi3wy.jpg","file_code":"ra7utowwd5vm","length":"00:08:18","views":"754","vw_fmt":"754","uploaded":"2023-10-08 04:37:10","up_fmt":"8 Okt 2023","up_short":"8 Okt","title":"Abg Dasteran Emut Kontol Pacar Cantik Tobrut Asupan Viral Doods Pro Links","t_esc":"Abg Dasteran Emut Kontol Pacar Cantik Tobrut Asupan Viral Doods Pro Links"},{"download_url":"https://playmogo.com/d/itjp8mo8pdl1","single_img":"https://ticdn.net/snaps/hg47uy75ej5cnbpw.jpg","file_code":"itjp8mo8pdl1","length":"00:00:38","views":"507","vw_fmt":"507","uploaded":"2023-10-08 02:47:22","up_fmt":"8 Okt 2023","up_short":"8 Okt","title":"Disuruh Pacar Emut Kontol Dalam Mobil Folder Videos Pejuang Lendir Ful Album","t_esc":"Disuruh Pacar Emut Kontol Dalam Mobil Folder Videos Pejuang Lendir Ful Album"},{"download_url":"https://playmogo.com/d/r2yn6yw33uuv","single_img":"https://ticdn.net/snaps/cx09y7pa2o3h6ub6.jpg","file_code":"r2yn6yw33uuv","length":"00:02:13","views":"1090","vw_fmt":"1.1K","uploaded":"2023-10-08 02:47:22","up_fmt":"8 Okt 2023","up_short":"8 Okt","title":"Kenangan Saat Disepongin Kontol Oleh Mantan Pacar Ful Album Popstream Video Viral","t_esc":"Kenangan Saat Disepongin Kontol Oleh Mantan Pacar Ful Album Popstream Video Viral"},{"download_url":"https://playmogo.com/d/cnzxyiiq0i49","single_img":"https://ticdn.net/snaps/dyp19yhxkbrrho7r.jpg","file_code":"cnzxyiiq0i49","length":"00:11:36","views":"3305","vw_fmt":"3.3K","uploaded":"2023-10-08 02:47:14","up_fmt":"8 Okt 2023","up_short":"8 Okt","title":"Dikocokin Dulu Kontolnya Sebelum Ngentot Ya Say Streaming Sotwe Terabox Memeksiana","t_esc":"Dikocokin Dulu Kontolnya Sebelum Ngentot Ya Say Streaming Sotwe Terabox Memeksiana"},{"download_url":"https://playmogo.com/d/ev4duivs7th6","single_img":"https://ticdn.net/snaps/c1ji31ur8ajgjaf4.jpg","file_code":"ev4duivs7th6","length":"00:00:38","views":"1662","vw_fmt":"1.7K","uploaded":"2023-10-08 02:47:14","up_fmt":"8 Okt 2023","up_short":"8 Okt","title":"Siswi Smp Nyepong Kontol Di Kelas Doodsflix Jilbab Simontok Toketbagus Downloader","t_esc":"Siswi Smp Nyepong Kontol Di Kelas Doodsflix Jilbab Simontok Toketbagus Downloader"},{"download_url":"https://playmogo.com/d/g7e95pit3bmb","single_img":"https://ticdn.net/snaps/6bwi5pxhe8rsyf3i.jpg","file_code":"g7e95pit3bmb","length":"00:02:12","views":"1467","vw_fmt":"1.5K","uploaded":"2023-10-08 02:47:14","up_fmt":"8 Okt 2023","up_short":"8 Okt","title":"Sepongan Maut Cewe Cantik Bikin Ngilu Kontol Dodstream Doods Pro Lokal Staklam","t_esc":"Sepongan Maut Cewe Cantik Bikin Ngilu Kontol Dodstream Doods Pro Lokal Staklam"},{"download_url":"https://playmogo.com/d/d86ymwapujca","single_img":"https://ticdn.net/snaps/al0uknkh0qwyfgh8.jpg","file_code":"d86ymwapujca","length":"00:02:20","views":"5923","vw_fmt":"5.9K","uploaded":"2023-10-08 02:47:09","up_fmt":"8 Okt 2023","up_short":"8 Okt","title":"Dikocokin Batang Kontol Sama Abg Cantik Cilbo Bokepind Simontok Tobrut Video Viral","t_esc":"Dikocokin Batang Kontol Sama Abg Cantik Cilbo Bokepind Simontok Tobrut Video Viral"},{"download_url":"https://playmogo.com/d/v7pgfqgm7unr","single_img":"https://ticdn.net/snaps/fw485ec6kb9v9w1y.jpg","file_code":"v7pgfqgm7unr","length":"00:02:43","views":"1470","vw_fmt":"1.5K","uploaded":"2023-10-08 02:47:05","up_fmt":"8 Okt 2023","up_short":"8 Okt","title":"Bacol Vcs Cewek Semok Toket Montok Bugil Dodstream Xpanas Indo Bochiel Sotwe","t_esc":"Bacol Vcs Cewek Semok Toket Montok Bugil Dodstream Xpanas Indo Bochiel Sotwe"},{"download_url":"https://playmogo.com/d/qwi9ypq6kr82","single_img":"https://ticdn.net/snaps/uqmybi8fg0ne3148.jpg","file_code":"qwi9ypq6kr82","length":"00:18:15","views":"4108","vw_fmt":"4.1K","uploaded":"2023-10-08 02:47:05","up_fmt":"8 Okt 2023","up_short":"8 Okt","title":"Viral Video Dayuni Live Prank Ojol Dood Tele Doodstream Bokepind Streaming","t_esc":"Viral Video Dayuni Live Prank Ojol Dood Tele Doodstream Bokepind Streaming"},{"download_url":"https://playmogo.com/d/jdg5g3qupyod","single_img":"https://ticdn.net/snaps/qrb46x18fe642rnx.jpg","file_code":"jdg5g3qupyod","length":"00:15:29","views":"7265","vw_fmt":"7.3K","uploaded":"2023-10-08 02:47:05","up_fmt":"8 Okt 2023","up_short":"8 Okt","title":"Kebaya Coklat Viral Indonesia Toketbagus Dodstream Twitter Link Web","t_esc":"Kebaya Coklat Viral Indonesia Toketbagus Dodstream Twitter Link Web"}],"results_total":"26783","results":200}}